Workbook
Name BRANDS: Diverse!$J$4:$J$40
Name COUNTRIES: Diverse!$R$3:$R$235
Name CURRENCY: Diverse!$X$4:$X$168
Name DAYS: Diverse!$G$3:$G$34
Name DAYSTRS: Diverse!$G$45:$G$75
Name GRADINGS: Diverse!$U$3:$U$43
Name HOUSINGLAY: Diverse!$N$3:$N$10
Name HOUSINGREARING: Diverse!$N$17:$N$19
Name Languages: Diverse!$AC$4:$AC$19
Name MONTH: Diverse!$D$3:$D$15
Name MONTHTRS: Diverse!$D$44:$D$56
Name YEAR: Diverse!$B$3:$B$16
Name YEARTRS: Diverse!$B$45:$B$57

Sheet Std
A1: Breed | B1: ISA BROWN Baiada ALT 2021
B2: L | C2: O | D2: H | E2: AG | F2: X | G2: V | H2: I | I2: J | J2: C | K2: D | L2: B | M2: K
A3: Age | B3: %lay HD | C3: AEW | D3: BW | E3: Daily egg mass | F3: Cumulative egg mass HH | G3: Eggs HH | H3: Average of BW MIN | I3: Average of BW MAX | J3: Feed min | K3: Feed max | L3: Feed avg | M3: Liveability rearing
A4: 1 | B4: 0 | C4: 0 | D4: 65.5 | E4: 0 | F4: 0 | G4: 0 | H4: 63.8625 | I4: 67.1375 | J4: 10 | K4: 12 | L4: 11 | M4: 99.7
A5: 2 | B5: 0 | C5: 0 | D5: 117.5 | E5: 0 | F5: 0 | G5: 0 | H5: 114.5625 | I5: 120.4375 | J5: 17.224768 | K5: 19.224768 | L5: 18.224768 | M5: 99.45
A6: 3 | B6: 0 | C6: 0 | D6: 191.5 | E6: 0 | F6: 0 | G6: 0 | H6: 186.7125 | I6: 196.2875 | J6: 24.165692 | K6: 26.165692 | L6: 25.165692 | M6: 99.25
A7: 4 | B7: 0 | C7: 0 | D7: 275.5 | E7: 0 | F7: 0 | G7: 0 | H7: 268.6125 | I7: 282.3875 | J7: 30.387181 | K7: 32.387181 | L7: 31.387181 | M7: 99.1
A8: 5 | B8: 0 | C8: 0 | D8: 370 | E8: 0 | F8: 0 | G8: 0 | H8: 360.75 | I8: 379.25 | J8: 35.969504 | K8: 37.969504 | L8: 36.969504 | M8: 98.95
A9: 6 | B9: 0 | C9: 0 | D9: 471 | E9: 0 | F9: 0 | G9: 0 | H9: 459.225 | I9: 482.775 | J9: 40.99015 | K9: 42.99015 | L9: 41.99015 | M9: 98.8
A10: 7 | B10: 0 | C10: 0 | D10: 577.5 | E10: 0 | F10: 0 | G10: 0 | H10: 563.0625 | I10: 591.9375 | J10: 45.523827 | K10: 47.523827 | L10: 46.523827 | M10: 98.65
A11: 8 | B11: 0 | C11: 0 | D11: 686.5 | E11: 0 | F11: 0 | G11: 0 | H11: 669.3375 | I11: 703.6625 | J11: 49.64246 | K11: 51.64246 | L11: 50.64246 | M11: 98.55
A12: 9 | B12: 0 | C12: 0 | D12: 793.5 | E12: 0 | F12: 0 | G12: 0 | H12: 773.6625 | I12: 813.3375 | J12: 53.415196 | K12: 55.415196 | L12: 54.415196 | M12: 98.45
A13: 10 | B13: 0 | C13: 0 | D13: 894.5 | E13: 0 | F13: 0 | G13: 0 | H13: 872.1375 | I13: 916.8625 | J13: 56.908399 | K13: 58.908399 | L13: 57.908399 | M13: 98.35
A14: 11 | B14: 0 | C14: 0 | D14: 989 | E14: 0 | F14: 0 | G14: 0 | H14: 964.275 | I14: 1013.725 | J14: 60.185653 | K14: 62.185653 | L14: 61.185653 | M14: 98.25
A15: 12 | B15: 0 | C15: 0 | D15: 1076.5 | E15: 0 | F15: 0 | G15: 0 | H15: 1049.5875 | I15: 1103.4125 | J15: 63.307761 | K15: 65.307761 | L15: 64.307761 | M15: 98.15
... A113: 110 | B113: 0 | C113: 0 | D113: 0 | E113: 0 | F113: 29.019946 | G113: 460.13022 | H113: 0 | I113: 0 | J113: -1 | K113: 1 | L113: 0 | M113: 0

Sheet Language
B1: ='General Input'!B12 -> English
A2: WS1 | B2: =VLOOKUP(Languages!B2,Languages!$B$2:$S$400,MATCH($B$1,Languages!$B$1:$S$1,0),FALSE) -> General input
B3: =VLOOKUP(Languages!B3,Languages!$B$2:$S$400,MATCH($B$1,Languages!$B$1:$S$1,0),FALSE) -> Spread sheet explanation
B4: =VLOOKUP(Languages!B4,Languages!$B$2:$S$400,MATCH($B$1,Languages!$B$1:$S$1,0),FALSE) -> 0
B5: =VLOOKUP(Languages!B5,Languages!$B$2:$S$400,MATCH($B$1,Languages!$B$1:$S$1,0),FALSE) -> Please fill in the coloured cells.
B6: =VLOOKUP(Languages!B6,Languages!$B$2:$S$400,MATCH($B$1,Languages!$B$1:$S$1,0),FALSE) -> Your document name will be in cell B25
B7: =VLOOKUP(Languages!B7,Languages!$B$2:$S$400,MATCH($B$1,Languages!$B$1:$S$1,0),FALSE) -> You can use this format to name your document.
B8: =VLOOKUP(Languages!B8,Languages!$B$2:$S$400,MATCH($B$1,Languages!$B$1:$S$1,0),FALSE) -> Required informations
B9: =VLOOKUP(Languages!B9,Languages!$B$2:$S$400,MATCH($B$1,Languages!$B$1:$S$1,0),FALSE) -> Every calculation and graph will generate themselves from the data
B10: =VLOOKUP(Languages!B10,Languages!$B$2:$S$400,MATCH($B$1,Languages!$B$1:$S$1,0),FALSE) -> entered in "input general", "input rearing" and "input laying" worksheets.
B11: =VLOOKUP(Languages!B11,Languages!$B$2:$S$400,MATCH($B$1,Languages!$B$1:$S$1,0),FALSE) -> Hatch date
B12: =VLOOKUP(Languages!B12,Languages!$B$2:$S$400,MATCH($B$1,Languages!$B$1:$S$1,0),FALSE) -> Breed
B13: =VLOOKUP(Languages!B13,Languages!$B$2:$S$400,MATCH($B$1,Languages!$B$1:$S$1,0),FALSE) -> Housing system during laying period
B14: =VLOOKUP(Languages!B14,Languages!$B$2:$S$400,MATCH($B$1,Languages!$B$1:$S$1,0),FALSE) -> Company name / Egg Organisation
... B60: =VLOOKUP(Languages!B60,Languages!$B$2:$S$400,MATCH($B$1,Languages!$B$1:$S$1,0),FALSE) -> Version:
A61: WS2 | B61: =VLOOKUP(Languages!B61,Languages!$B$2:$S$400,MATCH($B$1,Languages!$B$1:$S$1,0),FALSE) -> Rearing input
B62: =VLOOKUP(Languages!B62,Languages!$B$2:$S$400,MATCH($B$1,Languages!$B$1:$S$1,0),FALSE) -> Date
B63: =VLOOKUP(Languages!B63,Languages!$B$2:$S$400,MATCH($B$1,Languages!$B$1:$S$1,0),FALSE) -> Age
B64: =VLOOKUP(Languages!B64,Languages!$B$2:$S$400,MATCH($B$1,Languages!$B$1:$S$1,0),FALSE) -> Mortality
B65: =VLOOKUP(Languages!B65,Languages!$B$2:$S$400,MATCH($B$1,Languages!$B$1:$S$1,0),FALSE) -> Daily
B66: =VLOOKUP(Languages!B66,Languages!$B$2:$S$400,MATCH($B$1,Languages!$B$1:$S$1,0),FALSE) -> Weekly
B67: =VLOOKUP(Languages!B67,Languages!$B$2:$S$400,MATCH($B$1,Languages!$B$1:$S$1,0),FALSE) -> Cum.
B68: =VLOOKUP(Languages!B68,Languages!$B$2:$S$400,MATCH($B$1,Languages!$B$1:$S$1,0),FALSE) -> Transfer
B69: =VLOOKUP(Languages!B69,Languages!$B$2:$S$400,MATCH($B$1,Languages!$B$1:$S$1,0),FALSE) -> Mortality %
B70: =VLOOKUP(Languages!B70,Languages!$B$2:$S$400,MATCH($B$1,Languages!$B$1:$S$1,0),FALSE) -> Number of birds end of period
B71: =VLOOKUP(Languages!B71,Languages!$B$2:$S$400,MATCH($B$1,Languages!$B$1:$S$1,0),FALSE) -> Body weight
B72: =VLOOKUP(Languages!B72,Languages!$B$2:$S$400,MATCH($B$1,Languages!$B$1:$S$1,0),FALSE) -> Actual (g)
B73: =VLOOKUP(Languages!B73,Languages!$B$2:$S$400,MATCH($B$1,Languages!$B$1:$S$1,0),FALSE) -> Unif. %
... B99: =VLOOKUP(Languages!B99,Languages!$B$2:$S$400,MATCH($B$1,Languages!$B$1:$S$1,0),FALSE) -> Water/feed ratio
A100: WS3 | B100: =VLOOKUP(Languages!B100,Languages!$B$2:$S$400,MATCH($B$1,Languages!$B$1:$S$1,0),FALSE) -> Laying input
B101: =VLOOKUP(Languages!B101,Languages!$B$2:$S$400,MATCH($B$1,Languages!$B$1:$S$1,0),FALSE) -> Farm name:
B102: =VLOOKUP(Languages!B102,Languages!$B$2:$S$400,MATCH($B$1,Languages!$B$1:$S$1,0),FALSE) -> House no. :
B103: =VLOOKUP(Languages!B103,Languages!$B$2:$S$400,MATCH($B$1,Languages!$B$1:$S$1,0),FALSE) -> Hatch date:
B104: =VLOOKUP(Languages!B104,Languages!$B$2:$S$400,MATCH($B$1,Languages!$B$1:$S$1,0),FALSE) -> Date at 18 weeks old :
B105: =VLOOKUP(Languages!B105,Languages!$B$2:$S$400,MATCH($B$1,Languages!$B$1:$S$1,0),FALSE) -> Transfer date:
B106: =VLOOKUP(Languages!B106,Languages!$B$2:$S$400,MATCH($B$1,Languages!$B$1:$S$1,0),FALSE) -> Number of laying birds housed:
B107: =VLOOKUP(Languages!B107,Languages!$B$2:$S$400,MATCH($B$1,Languages!$B$1:$S$1,0),FALSE) -> 0
B108: =VLOOKUP(Languages!B108,Languages!$B$2:$S$400,MATCH($B$1,Languages!$B$1:$S$1,0),FALSE) -> Date beginning of the week
B109: =VLOOKUP(Languages!B109,Languages!$B$2:$S$400,MATCH($B$1,Languages!$B$1:$S$1,0),FALSE) -> Age in weeks
B110: =VLOOKUP(Languages!B110,Languages!$B$2:$S$400,MATCH($B$1,Languages!$B$1:$S$1,0),FALSE) -> No. of birds end of week
B111: =VLOOKUP(Languages!B111,Languages!$B$2:$S$400,MATCH($B$1,Languages!$B$1:$S$1,0),FALSE) -> Weekly mortality No. of birds
B112: =VLOOKUP(Languages!B112,Languages!$B$2:$S$400,MATCH($B$1,Languages!$B$1:$S$1,0),FALSE) -> 0
... B146: =VLOOKUP(Languages!B146,Languages!$B$2:$S$400,MATCH($B$1,Languages!$B$1:$S$1,0),FALSE) -> Comments
A147: WS4 | B147: =VLOOKUP(Languages!B147,Languages!$B$2:$S$400,MATCH($B$1,Languages!$B$1:$S$1,0),FALSE) -> Egg grading input
B148: =VLOOKUP(Languages!B148,Languages!$B$2:$S$400,MATCH($B$1,Languages!$B$1:$S$1,0),FALSE) -> Egg weight distribution
B149: =VLOOKUP(Languages!B149,Languages!$B$2:$S$400,MATCH($B$1,Languages!$B$1:$S$1,0),FALSE) -> S
B150: =VLOOKUP(Languages!B150,Languages!$B$2:$S$400,MATCH($B$1,Languages!$B$1:$S$1,0),FALSE) -> M
B151: =VLOOKUP(Languages!B151,Languages!$B$2:$S$400,MATCH($B$1,Languages!$B$1:$S$1,0),FALSE) -> L
B152: =VLOOKUP(Languages!B152,Languages!$B$2:$S$400,MATCH($B$1,Languages!$B$1:$S$1,0),FALSE) -> XL
B153: =VLOOKUP(Languages!B153,Languages!$B$2:$S$400,MATCH($B$1,Languages!$B$1:$S$1,0),FALSE) -> max.
B154: =VLOOKUP(Languages!B154,Languages!$B$2:$S$400,MATCH($B$1,Languages!$B$1:$S$1,0),FALSE) -> Table of egg weight distribution
B155: =VLOOKUP(Languages!B155,Languages!$B$2:$S$400,MATCH($B$1,Languages!$B$1:$S$1,0),FALSE) -> Age
B156: =VLOOKUP(Languages!B156,Languages!$B$2:$S$400,MATCH($B$1,Languages!$B$1:$S$1,0),FALSE) -> Average weight week
B157: =VLOOKUP(Languages!B157,Languages!$B$2:$S$400,MATCH($B$1,Languages!$B$1:$S$1,0),FALSE) -> Standard
B158: =VLOOKUP(Languages!B158,Languages!$B$2:$S$400,MATCH($B$1,Languages!$B$1:$S$1,0),FALSE) -> Current average weight
B159: =VLOOKUP(Languages!B159,Languages!$B$2:$S$400,MATCH($B$1,Languages!$B$1:$S$1,0),FALSE) -> Percentage grade
... B167: =VLOOKUP(Languages!B167,Languages!$B$2:$S$400,MATCH($B$1,Languages!$B$1:$S$1,0),FALSE) -> Cumulative No's of eggs produced
A168: WS5 | B168: =VLOOKUP(Languages!B168,Languages!$B$2:$S$400,MATCH($B$1,Languages!$B$1:$S$1,0),FALSE) -> Production costs
B169: =VLOOKUP(Languages!B169,Languages!$B$2:$S$400,MATCH($B$1,Languages!$B$1:$S$1,0),FALSE) -> Date
B170: =VLOOKUP(Languages!B170,Languages!$B$2:$S$400,MATCH($B$1,Languages!$B$1:$S$1,0),FALSE) -> Age in weeks
B171: =VLOOKUP(Languages!B171,Languages!$B$2:$S$400,MATCH($B$1,Languages!$B$1:$S$1,0),FALSE) -> Feed consumption
B172: =VLOOKUP(Languages!B172,Languages!$B$2:$S$400,MATCH($B$1,Languages!$B$1:$S$1,0),FALSE) -> Weekly (kg)
B173: =VLOOKUP(Languages!B173,Languages!$B$2:$S$400,MATCH($B$1,Languages!$B$1:$S$1,0),FALSE) -> Cum (kg)
B174: =VLOOKUP(Languages!B174,Languages!$B$2:$S$400,MATCH($B$1,Languages!$B$1:$S$1,0),FALSE) -> Feed price
B175: =VLOOKUP(Languages!B175,Languages!$B$2:$S$400,MATCH($B$1,Languages!$B$1:$S$1,0),FALSE) -> /ton
B176: =VLOOKUP(Languages!B176,Languages!$B$2:$S$400,MATCH($B$1,Languages!$B$1:$S$1,0),FALSE) -> /egg
B177: =VLOOKUP(Languages!B177,Languages!$B$2:$S$400,MATCH($B$1,Languages!$B$1:$S$1,0),FALSE) -> /kg egg mass
B178: =VLOOKUP(Languages!B178,Languages!$B$2:$S$400,MATCH($B$1,Languages!$B$1:$S$1,0),FALSE) -> Cumulative average
B179: =VLOOKUP(Languages!B179,Languages!$B$2:$S$400,MATCH($B$1,Languages!$B$1:$S$1,0),FALSE) -> Feed cost
B180: =VLOOKUP(Languages!B180,Languages!$B$2:$S$400,MATCH($B$1,Languages!$B$1:$S$1,0),FALSE) -> /bird/day
... B183: =VLOOKUP(Languages!B183,Languages!$B$2:$S$400,MATCH($B$1,Languages!$B$1:$S$1,0),FALSE) -> Cumulative average
A184: WS6 | B184: =VLOOKUP(Languages!B184,Languages!$B$2:$S$400,MATCH($B$1,Languages!$B$1:$S$1,0),FALSE) -> Production data
B185: =VLOOKUP(Languages!B185,Languages!$B$2:$S$400,MATCH($B$1,Languages!$B$1:$S$1,0),FALSE) -> Farm name :
B186: =VLOOKUP(Languages!B186,Languages!$B$2:$S$400,MATCH($B$1,Languages!$B$1:$S$1,0),FALSE) -> House No. / Housing system:
B187: =VLOOKUP(Languages!B187,Languages!$B$2:$S$400,MATCH($B$1,Languages!$B$1:$S$1,0),FALSE) -> Hatch date:
B188: =VLOOKUP(Languages!B188,Languages!$B$2:$S$400,MATCH($B$1,Languages!$B$1:$S$1,0),FALSE) -> Transfer date:
B189: =VLOOKUP(Languages!B189,Languages!$B$2:$S$400,MATCH($B$1,Languages!$B$1:$S$1,0),FALSE) -> No. of laying birds housed:
B190: =VLOOKUP(Languages!B190,Languages!$B$2:$S$400,MATCH($B$1,Languages!$B$1:$S$1,0),FALSE) -> Feed company:
B191: =VLOOKUP(Languages!B191,Languages!$B$2:$S$400,MATCH($B$1,Languages!$B$1:$S$1,0),FALSE) -> House No.
B192: =VLOOKUP(Languages!B192,Languages!$B$2:$S$400,MATCH($B$1,Languages!$B$1:$S$1,0),FALSE) -> Housing system
B193: =VLOOKUP(Languages!B193,Languages!$B$2:$S$400,MATCH($B$1,Languages!$B$1:$S$1,0),FALSE) -> 0
B194: =VLOOKUP(Languages!B194,Languages!$B$2:$S$400,MATCH($B$1,Languages!$B$1:$S$1,0),FALSE) -> Week of the year
B195: =VLOOKUP(Languages!B195,Languages!$B$2:$S$400,MATCH($B$1,Languages!$B$1:$S$1,0),FALSE) -> Age in weeks
B196: =VLOOKUP(Languages!B196,Languages!$B$2:$S$400,MATCH($B$1,Languages!$B$1:$S$1,0),FALSE) -> Liveability %
... B214: =VLOOKUP(Languages!B214,Languages!$B$2:$S$400,MATCH($B$1,Languages!$B$1:$S$1,0),FALSE) -> Cum.
A215: WS7 | B215: =VLOOKUP(Languages!B215,Languages!$B$2:$S$400,MATCH($B$1,Languages!$B$1:$S$1,0),FALSE) -> Summary
B216: =VLOOKUP(Languages!B216,Languages!$B$2:$S$400,MATCH($B$1,Languages!$B$1:$S$1,0),FALSE) -> Name :
B217: =VLOOKUP(Languages!B217,Languages!$B$2:$S$400,MATCH($B$1,Languages!$B$1:$S$1,0),FALSE) -> House No. :
B218: =VLOOKUP(Languages!B218,Languages!$B$2:$S$400,MATCH($B$1,Languages!$B$1:$S$1,0),FALSE) -> Transfer date :
B219: =VLOOKUP(Languages!B219,Languages!$B$2:$S$400,MATCH($B$1,Languages!$B$1:$S$1,0),FALSE) -> Hatch date:
B220: =VLOOKUP(Languages!B220,Languages!$B$2:$S$400,MATCH($B$1,Languages!$B$1:$S$1,0),FALSE) -> Date at 18 weeks old :
B221: =VLOOKUP(Languages!B221,Languages!$B$2:$S$400,MATCH($B$1,Languages!$B$1:$S$1,0),FALSE) -> Feed company :
B222: =VLOOKUP(Languages!B222,Languages!$B$2:$S$400,MATCH($B$1,Languages!$B$1:$S$1,0),FALSE) -> Number of layers :
B223: =VLOOKUP(Languages!B223,Languages!$B$2:$S$400,MATCH($B$1,Languages!$B$1:$S$1,0),FALSE) -> Housing system:
B224: =VLOOKUP(Languages!B224,Languages!$B$2:$S$400,MATCH($B$1,Languages!$B$1:$S$1,0),FALSE) -> 0
B225: =VLOOKUP(Languages!B225,Languages!$B$2:$S$400,MATCH($B$1,Languages!$B$1:$S$1,0),FALSE) -> Age
B226: =VLOOKUP(Languages!B226,Languages!$B$2:$S$400,MATCH($B$1,Languages!$B$1:$S$1,0),FALSE) -> % Mortality
B227: =VLOOKUP(Languages!B227,Languages!$B$2:$S$400,MATCH($B$1,Languages!$B$1:$S$1,0),FALSE) -> % Laying rate
... B234: =VLOOKUP(Languages!B234,Languages!$B$2:$S$400,MATCH($B$1,Languages!$B$1:$S$1,0),FALSE) -> Cum seconds %
A235: WS8 | B235: =VLOOKUP(Languages!B235,Languages!$B$2:$S$400,MATCH($B$1,Languages!$B$1:$S$1,0),FALSE) -> Diverse
...

Sheet Languages
B1: 1 | C1: Deutsch | D1: English | E1: Español | F1: Français | G1: Indonesia | H1: Italiano | I1: Nederland | J1: Polski | K1: Português | L1: Slovenský | M1: South Slavic | N1: русский | O1: العربية | P1: 한국의 | Q1: 中国 | R1: 日本の
A2: WS1 | B2: 2 | C2: Haupteingabe | D2: General input | E2: Datos generales | F2: Informations générales | G2: Input umum | H2: Informazioni Generali | I2: Invoer | J2: Dane ogólne I informacje | K2: Entrada geral | L2: Všeobecné vstupné údaje | M2: Generalni unos podataka | N2: Общие данные | O2: بيانات عامة | P2: 일반 | Q2: 一般数据输入 | R2: 一般情報入力
B3: 3 | C3: Arbeitsanweisung | D3: Spread sheet explanation | E3: Explicación de la hoja de cálculo | F3: Explications sur le fichier | G3: Lembar penjelasan | H3: Spiegazione Foglio Di Calcolo | I3: Uitleg excel document | J3: Wyjaśnienia | K3: Explicação do programa | L3: Vysvetlenie | M3: Objašnjenje tabele | N3: Объяснение | O3: شرح لجدول البيانات | P3: 스프레드시트설명 | Q3: 填表说明 | R3: エクセルシートの説明
B4: 4
B5: 5 | C5: Bitte die farbigen Cellen auffüllen | D5: Please fill in the coloured cells. | E5: Por favor, rellene las celdas coloreadas | F5: Merci de remplir les cellules colorées | G5: Silahkan mengisi di sel yang diwarnai | H5: Prego Completare Le Celle Colorate | I5: Gelieve de gekleurde cellen in te voeren | J5: Należy wypełnić komórki z kolorowym tłem | K5: Por favor preencher as células coloridas | L5: Vyplňte prosím farebné bunky | M5: Molim Vas unesite označena polja | N5: Заполните закрашенные клетки | O5: يرجى ملأ الخلايا الملونة | P5: 색칠된 셀에 기입 | Q5: 请将数字填入蓝色空格. | R5: 色のついたセルのみに入力してください。
B6: 6 | C6: Ihr Dokumentenname wird in Celle B27 | D6: Your document name will be in cell B25 | E6: El nombre del documento aparecerá en la celda B27 | F6: Vous trouverez le nom du fichier en cellule B27 | G6: Nama dokumen Anda akan berada di sel B25 | H6: Nome Vostro Documento Nella Cella B25 | I6: Uw documentnaam staat in cel B27 | J6: Nazwa dokumentu będzie znajdować się w komórce B25 | K6: O nome do documento será na célula B27 | L6: Názov vašej tabuľky bude v bunke B27 | M6: Naziv dokumenta će biti u polju B25 | N6: Название документа в клетке B25 | O6: إسم سجلك سيكون في الخلية رقم ب27 | P6: 문서명은 셀B25에 표시됨 | Q6: 文件名在表格B27 | R6: このドキュメントの名前はセルB25に記入してください。
B7: 7 | C7: Sie können dieses Fromat sur Benennung des Dokumentes | D7: You can use this format to name your document. | E7: Puede usar este formato como nombre para su documento. | F7: Vous pouvez utiliser ce nom afin de sauvegarder votre fichier. | G7: Anda dapat menggunakan format ini untuk memberi nama dokumen anda. | H7: Usare Questo Formato Per Nominare Il Vostro Documento | I7: U kunt dit format gebruiken als documentnaam | J7: Można wykorzystać ten format dla określenia nazwy dokumentu | K7: Você pode usar este formato para nomear seu documento | L7: Pre názov Vášho dokumentu môžete použiť tento formát | M7: Možete koristiti ovaj format za naziv dokumenta | N7: Вы можете дать собственное название этому документу | O7: يمكنك إستعمال هذا النموذج لتسمية سجلك | P7: 이 형식을 문서제목에 사용가능함 | Q7: 可以此格式命名文件 | R7: このフォーマット名は自由に変更できます。
B8: 8 | C8: benötigte Information | D8: Required informations | E8: Informaciones necesarias | F8: Informations requises. | G8: Informasi yang dibutuhkan | H8: Informazioni Richieste | I8: Vereiste informatie | J8: Pole z wymaganym wpisem | K8: Informações necessárias | L8: Požadované informácie | M8: Potrebne informacije | N8: Необходимая информация | O8: المعلومات المطلوبة | P8: 필수정보 | Q8: 所需信息/数据 | R8: 一般情報入力
B9: 9 | C9: Die Berechnungen für die Graphen werden automatisch erstellt. | D9: Every calculation and graph will generate themselves from the data | E9: Los cálculos y gráficos se generarán automáticamente a partir de los datos | F9: Chaque calcul et graphique se générera à partir des données saisies | G9: Setiap perhitungan dan grafik akan dihasilkan dari data | H9: Ogni Calcolo E Grafico Sarà Generato Dai Dati | I9: Grafieken en gecalculeerde data worden automatisch gegenereerd uit uw invoer | J9: Wszystkie wykresy i obliczenia będą wygenerowane automatycznie | K9: Todos os cálculos e gráficos serão gerados a partir dos dados inseridos | L9: Všetky kalkulácie a grafy sa automaticky vygenerujú z údajov | M9: Svaka kalkulacija i grafikon će se generisati sam od podataka | N9: Указанные данные будут посчитаны и отражены на графике | O9: كل عملية حسابية ورسم بياني ينتج نفسه من المعلومات | P9: 모든 계산 및 그래프는 데이터로부터 생성합니다 | Q9: 计算结果和曲线将自动生成 | R9: 入力データより、性能値とグラフは自動的に作られます。
B10: 10 | C10: In folgende Arbeitsblätter muss eingetragen werden: Eingabe Allgemein, Eingabe Aufzucht, Eingabe Lege | D10: entered in "input general", "input rearing" and "input laying" worksheets. | E10: introducidos en las hojas "datos generales", "datos de recría" y "datos de puesta". | F10: dans les feuilles "Informations générales", "Données d'élevage" et "Données de ponte" | G10: Masukan dalam lembar kerja "input umum", "input growing" dan "input laying". | H10: Inseriti In Foglio Lavoro"Info Generali","Info Svezzamento" E "Info Deposizione" | I10: in de tabbladen "input general", "input rearing" en "input laying". | J10: Proszę wprowadzić "dane podstawowe", "dane odchowu" i "dane produkcyjne" | K10: Entrada na planilha "Dados Gerais", "Dados de cria" e "Dados de postura" | L10: ktoré vložíte do listov "Všeobecné vstupné údaje", "Obdobie odchovu" a "Obdobie produkcie" | M10: uneto u tabele ‚‚ generalni unos‚‚ , ‚‚unos za odgoj‚, i ‚‚unos za proizvodnju‚‚ | N10: Обратите внимание на вкладки "общие данные", "данные по выращиванию" и "данные по кладке". | P10: "일반입력", "육성입력", "산란입력"을 기입한다. | Q10: 进入"一般数据", "生长期记录" 和 "产蛋期记录"工作表. | R10: 「一般情報入力」, 「育雛/育成入力」 と 「産卵入力」 ワークシートにデータを入力してください
B11: 11 | C11: Schlupfdatum | D11: Hatch date | E11: Fecha de nacimiento | F11: Date d'éclosion | G11: Tanggal menetas | H11: Data Schiusa | I11: Uitkomstdatum | J11: Data wylęgu | K11: Data de eclosão | L11: Dátum liahnutia | M11: Datum inkubiranja | N11: Дата вывода | O11: تاريخ التفقيس | P11: 부화데이터 | Q11: 出雏日期 | R11: 孵化日
B12: 12 | C12: Zucht/ Genetik | D12: Breed | E12: Estirpe | F12: Souche | G12: Jenis Bibit | H12: Incrocio | I12: Ras/Merk | J12: Linia | K12: Linhagem | L12: Hybrid | M12: Hibrid | N12: Кросс | O12: العرق | P12: 육성 | Q12: 品种 | R12: 鶏種
B13: 13 | C13: Einrichtungssystem durch die Legeperiode | D13: Housing system during laying period | E13: Sistema de alojamiento en producción | F13: Système de production | G13: Sistem kandang selama periode bertelur | H13: Sistema Di Allevamento Durante Lo Svezzamento | I13: Huisvestingssysteem legperiode | J13: system produkcyjny | K13: Sistema de alojamento durante o período de postura | L13: Systém ustajnenia v produkcii | M13: Sistem držanja u periodu nošenja | N13: Система содержания в период кладки | O13: نظام التربية خلال مرحلة إنتاج البيض | P13: 산란기 계사 시스템 | Q13: 产蛋期鸡舍类型 | R13: 産卵期間中の鶏舎構造
B14: 14 | C14: Firmenname, Eierorganisation | D14: Company name / Egg Organisation | E14: Nombre de la compañía | F14: Organisation | G14: Nama Perusahaan/ Organisasi | H14: Nome Azienda/Organizzazione | I14: Bedrijfsnaam | J14: Nazwa firmy/ integracji | K14: Nome da companhia/ Empresa de ovos | L14: Názov firmy/Výrobcu vajec | M14: Naziv kompanije/ Farme | N14: Название компании | O14: إسم الشركة\منظمة البيض | P14: 회사명/계란협회 | Q14: 公司名称/产蛋场名称 | R14: 御社名
B15: 15 | C15: Betriebsname | D15: Laying farm name | E15: Nombre de la granja de puesta | F15: Ferme de production | G15: Nama Farm | H15: Nome Azienda Deposizione | I15: Bedrijfsnaam (2) | J15: Nazwa fermy produkcyjnej | K15: Nome da granja | L15: Názov znáškovej farmy | M15: Naziv farme za eksploataciju | N15: Название фермы | O15: إسم مزرعة إنتاج البيض | P15: 산란농장명 | Q15: 产蛋鸡场名称 | R15: 採卵農場名
B16: 16 | C16: Stallnummer | D16: House No. during laying period | E16: Nº de nave de puesta | F16: Bâtiment n° | G16: Nomor Kandang selama periode produksi | H16: Nr.Del Capannone Durante Il Periodo Di Deposizione | I16: Stalnummer | J16: Nr. kurnika produkcyjnego | K16: Numero do Galpão durante o período de postura | L16: Číslo haly v období produkcie | M16: Broj objekta u periodu nošenja | N16: Номер птичника в течении периода кладки | O16: عنبر رقم. خلال مرحلة إنتاج البيض | P16: 산란기 계사번호 | Q16: 产蛋鸡舍编号 | R16: 産卵鶏舎番号
B17: 17 | C17: Land | D17: Country | E17: País | F17: Pays | G17: Negara | H17: Paese | I17: Land | J17: Kraj | K17: País | L17: Krajina | M17: Zemlja | N17: Страна | O17: البلد | P17: 국가 | Q17: 国家 | R17: 国
B18: 18 | C18: aktuell | D18: Currency | E18: Moneda | F18: Devise | G18: Mata uang | H18: Valuta | I18: Valuta | J18: Waluta | K18: Moeda | L18: Mena | M18: Valuta | N18: Текущие | O18: العملة | P18: 전화 | Q18: 货币名称 | R18: 通貨
B19: 19 | C19: Berater Kontakt | D19: Technical contact (e-mail) | E19: Contacto técnico (e-mail) | F19: Contact technique (e-mail) | G19: Kontak e-mail | H19: Contatto Tecnico(E-Mail) | I19: Technisch adviseur (e-mail) | J19: Osoba kontaktowa (e-mail) | K19: Contato técnico (e-mail) | L19: Kontakt (e-mail) | M19: Tehnički kontakt(email) | N19: Контакты (e-mail) | O19: العنوان الإلكتروني | P19: 기술지원연락처(e-mail) | Q19: 技术支持联系方式(e-mail) | R19: 技術担当者 (e-mail)
B20: 20 | C20: Eingefüllter Name | D20: File name | E20: Nombre del archivo | F20: Nom du fichier | G20: Nama file | H20: Nome Del File | I20: Bestandsnaam | J20: Nazwa pliku | K20: Nome do arquivo | L20: Názov súboru (dokumentu) | M20: Naziv datoteke | N20: Имя файла | O20: إسم الملف | P20: 파일명 | Q20: 文件名 | R20: ファイル名
B21: 21 | C21: Bitte senden sie ihre Ergebnisse zu uns | D21: Please send your results to us by clicking on the following button. | E21: Por favor, envíenos los resultados | F21: Merci de nous envoyez vos résultats. | G21: Silakan kirim hasil anda kepada kami. | H21: Prego Inviare I Risultati | I21: ISA is zeer benieuwd naar uw resultaten | J21: Prosimy o przesłanie informacji do nas | K21: Por favor nos envie os resultados. | L21: Prosím, pošlite nám svoje výsledky | M21: Molim Vas da nam pošaljete rezultate klikom na sledeće sivo dugme | N21: Отправляйте нам свои результаты | O21: يرجى إرسال النتائج إلينا | P21: 다음의 회색 버튼을 클릭하여 결과를 보내 주시기 바랍니다. | Q21: 请将鸡群数据发送给我们. | R21: 情報をISAに送信
B22: 22
B23: 23 | C23: Auswahl Blatt | D23: Available sheets | E23: Hojas disponibles | F23: Feuilles disponibles | G23: Lembar tersedia | H23: Fogli Disponibili | I23: BESCHIKBARE TAB BLADEN | J23: dostępne arkusze | K23: Folhas disponíveis | L23: Dostupné listy | M23: Dostupne tabele | N23: Доступные листы | O23: النسخ المتوفرة | P23: 가능한 시트 | Q23: 各表名称 | R23: ワークシート名
A24: Sheets | B24: 24 | C24: Eingabe Aufzucht | D24: Input rearing | E24: Datos de recría | F24: Données d'élevage | G24: Input growing | H24: Informazioni Svezzamento | I24: Invoer opfokperiode | J24: dane odchowu | K24: Dados de cria | L24: Obdobie odchovu | M24: Unos odgoja | N24: Данные по выращиванию | O24: بيانات النمو | P24: 육성기입력 | Q24: 生长期记录表 | R24: 育雛育成入力
B25: 25 | C25: Aufzuchtgraf | D25: Rearing graph | E25: Gráfico de recría | F25: Courbe d'élevage | G25: Grafik growing | H25: Grafico Svezzamento | I25: Grafieken opfokperiode | J25: wykresu odchowu | K25: Gráfico de crescimento | L25: Odchovný graf | M25: Grafikon odgoja | N25: График выращивания | O25: رسم بيانات النمو | P25: 육성기그래프 | Q25: 生长期曲线表 | R25: 育雛育成グラフ
B26: 26 | C26: Eingabe Lege | D26: Input Laying | E26: Datos de puesta | F26: Données de ponte | G26: Input laying | H26: Informazioni Deposizione | I26: Invoer legperiode | J26: produkcyjne | K26: Dados de postura | L26: Obdobie produkcie | M26: Unos nosivosti | N26: Данные кладки | O26: بيانات الإنتاج | P26: 산란기입력 | Q26: 产蛋期记录表 | R26: 産卵入力
B27: 27 | C27: Legeleistungsgrafik | D27: Laying graph | E27: Gráfico de puesta | F27: Courbe de ponte | G27: Grafik laying | H27: Grafico Deposizione | I27: Grafieken legperiode | J27: wykres produkcji | K27: Gráfico de postura | L27: Graf produkcie | M27: Grafikon nosivosti | N27: График кладки | O27: رسم بيانات الإنتاج | P27: 산란기그래프 | Q27: 产蛋期曲线表 | R27: 産卵グラフ
B28: 28 | C28: Masse- & Verbrauchsgrafik | D28: Mass & cons graph | E28: Gráf. masa de huevo y consumo | F28: Masse et conso | G28: Grafik Egg mass & kons. pakan | H28: Grafico Massa E Consumo | I28: Eimassa en voeropname grafiek | J28: Masa jaj i spożycie paszy | K28: Gráfico de Massa e consumo | L28: Vaječná Hmota & Príjem KZ | M28: Grafikon mase | N28: Масса & график потребления | O28: رسم كتلة البيض & إستهلاك العلف | P28: 에그매스(산란량) 및 사료섭취량 | Q28: 产蛋量和饲料消耗曲线 | R28: 採卵 飼料グラフ
B29: 29 | C29: Futterverwertungsgrafik | D29: FCR graph | E29: Gráfico de IC | F29: Courbe d'indice | G29: Grafik FCR | H29: Grafico Indice Di Conversione | I29: VC grafiek | J29: wykres FCR | K29: Gráfico de C.A. | L29: Konverzia KZ | M29: Grafikon konverzije hrane | N29: График конверсии корма | O29: رسم معدل تحويل العلف | P29: 사료전환율그래프 | Q29: 饲料转化率曲线 | R29: 要求率グラフ
B30: 30 | C30: Grafik für eigene Sortierung | D30: Down grading graph | E30: Gráfico de huevos de segunda | F30: Courbe des déclassés | G30: Grafik non standar | H30: Grafico Sottopeso | I30: Grafiek 2e soort | J30: wykres odpadów | K30: Gráfico de ovos de segunda | L30: Neštandard | M30: Opadajuće gradiranje | N30: График сортировки | O30: رسم بياني للبيض درجة ثانية | P30: 다운등급그래프 | Q30: 次品蛋曲线表 | R30: 格外卵グラフ
B31: 31 | C31: Eiersortierung | D31: Egg grading | E31: Clasificación de los huevos | F31: Calibres | G31: Grading Telur | H31: Peso Uova | I31: Verdeling eigewichten | J31: rozkład klas wagowych | K31: Classificação dos ovos | L31: Hmotnostné triedenie vajec | M31: Klasiranje jaja | N31: Категорийеость яйца | O31: حجم البيض | P31: 계란등급 | Q31: 蛋重分级 | R31: 規格卵グラフ
B32: 32 | C32: Graf. Größenverteilung | D32: Egg grading distribution graph | E32: Gráf. clasific. de huevos | F32: Répartition des calibres en % | G32: Grafik grading telur | H32: Grafico Ripartizione Peso Uova | I32: Graf verdeling eigewichten proc | J32: wykres rozkładu klasowego jaj | K32: Gráf. Classif. Ovos. | L32: Rozdelenie hmot. tried vajec | M32: Distribucija klasa jaja | N32: Сортировка яйца по классификаци | O32: رسم توزيعي لحجم البيض | P32: 계란 등급 분포 그래프 | Q32: 蛋重分布图 | R32: 規格等級付卵グラフ
B33: 33 | C33: Eisortierung kum. | D33: Egg grading cum | E33: Clasific. huevos acum. | F33: Répartition des calibres en qt | G33: Kum. telur grading | H33: Peso Uova Cumulativo | I33: Graf verdeling eigewichten week | J33: rozkład klas narastająco | K33: Classificação de ovos acumulado | L33: Triedenie vajec nápočtom | M33: Kumulativno klasiranje jaja | N33: Прирост яиц по классификациям | O33: حجم البيض التراكمي | P33: 계란등급축적 | Q33: 累计蛋重分级 | R33: 累計規格卵グラフ
B34: 34 | C34: Finanselles Blatt | D34: Financial sheet | E34: Cálculos financieros | F34: Profits | G34: Lembar keuangan | H34: Foglio Finanziario | I34: Financiele data | J34: arkusz finansowy | K34: Ficha Financeira | L34: List finančného zhodnotenia | M34: Finansijska lista | N34: Финансы | O34: كشف مالي | P34: 재정시트 | Q34: 经济效益核算表 | R34: 経済性表
B35: 35 | C35: Produktionsdaten | D35: Production data | E35: Datos de producción | F35: Performances de production | G35: Data produksi | H35: Dati Di Produzione | I35: Productie data | J35: dane produkcyjne | K35: Dados de produção | L35: Produkčné údaje | M35: Proizvodni podaci | N35: Данные продуктивности | O35: بيانات الإنتاج | P35: 생산데이터 | Q35: 生产数据 | R35: 生産性データ
B36: 36 | C36: Summe | D36: Summary | E36: Resumen | F36: Résumé de production | G36: Ringkasan | H36: Sommario | I36: Samenvatting | J36: podsumowanie | K36: Resumo | L36: Sumár | M36: Zbir | N36: Итог | O36: ملخص | P36: 정리 | Q36: 总结 | R36: サマリー
B37: 37
B38: 38 | C38: Aktuell | D38: Content | E38: Contenido | F38: Contenu | G38: Daftar Isi | H38: Contenuto | I38: INHOUD | J38: zawartość | K38: Conteúdo | L38: Obsah | M38: Sadržaj | N38: Содержание | O38: محتويات | P38: 함유량 | Q38: 内容 | R38: 内容
B39: 39 | C39: Tägliche und wöchentliche Moratlität, Körpergewicht, Verbrauch und Lichtprogramm. | D39: Daily and weekly mortality, body weight, consumptions and light programs. | E39: Mortalidad diaria y semanal, peso corporal, consumo y programa de iluminación. | F39: Mortalité journalière et hebdomadaire, Poids corporel, consommation et programmes lumineux. | G39: Kematian harian dan mingguan, berat badan, konsumsi dan program pencahayaan. | H39: Mortalita' Giornaliera E Sett.Le,Peso Corporeo,Consumo E Programma Luce | I39: dagelijkse en wekelijkse uitval, lichaamsgewichten, voederopname en lichtprogramma's | J39: Upadki dzienne i tygodniowe, masa ciała, spożycie paszy i program świetlny | K39: Mortalidade diária e semanal, peso corporal, consumo e programa de luz | L39: Denný, týždenný úhyn, ŽH, príjem KZ, svetelný režim | M39: Dnevno i nedeljno uginuće, telesne težine, potrošnje hrane i svetlosni program | N39: Недельный и месячный отход, живая масса, потребление и программа освещения. | O39: الوفيات اليومية و الأسبوعية, وزن الجسم,الإستهلاك العلفي و برامج الإضاءة | P39: 일간/주간 폐사율, 체중, 소비량과 점등프로그램 | Q39: 每天及每周的死亡鸡数、体重、采食量和光照时数。 | R39: 日々と週間の斃死状況、体重、飼料摂取量、光線管理プログラム
B40: 40 | C40: Mortalität, Futterverbrauch, Körpergewicht und Uniformität | D40: Mortality, feed consumption, body weight and uniformity | E40: Mortalidad, consumo de pienso, peso corporal y uniformidad | F40: Mortalité, consommation d'aliment, Poids corporel et homogénéité. | G40: Kematian, konsumsi pakan, berat badan dan keseragaman | H40: Mortalita',Consumo Mangime,Peso Corporeo E Uniformita' | I40: uitval, voeropname, lichaamsgewichten en uniformiteit | J40: upadki, spożycie paszy, masa ciała i wyrównanie | K40: Mortalidade, consumo de alimento, peso corporal e uniformidade | L40: Úhyn, príjem KZ, ŽH, uniformita | M40: Uginuće, potrošnja hrane, telesna težina i ujednačenost | N40: Падеж, потребление корма, живая масса и однородность | O40: الوفيات,استهلاك العلف, وزن الجسم ومعدل التجانس | P40: 폐사율 사료 소비량, 체중 및 균일도 | Q40: 死亡鸡数、采食量、体重和均匀度。 | R40: 斃死、飼料摂取、体重、均一性
B41: 41 | C41: Tägliche und wöchentliche Produktion, wöchentliches Ei- und Körpergewicht, Verbrauchs- und Futterpreis. | D41: Daily and weekly production, weekly egg and body weights, consumptions and feed price. | E41: Producción diaria y semanal, peso de huevo y peso corporal semanal, consumo y precio del pienso. | F41: Production journalière et hebdomadaire, Poids d'œuf et Poids corporel hebdos, consommation et prix d'aliment. | G41: Produksi harian dan mingguan, berat telur dan berat badan mingguan, konsumsi dan harga pakan. | H41: Prod.Giorn.E Sett.Le,Peso Uovo E Peso Corporeo Sett.Le,Consumo E Prezzo Mangime. | I41: dagelikse en wekelijkse productie, ei en lichaamsgewichten, voeropnamen en voerprijzen | J41: dzienna i tygodniowa produkcja, tygodniowa masa jaj i masa ciała, spożycie i cena paszy | K41: Produção diária e semanal, ovo semanal e peso corporal, consumo e preço de alimento | L41: Dennná a týždenná produkcia, hmot vajec, ŽH, príjem a cena KZ | M41: Dnevna i nedeljna proizvodnja , nedeljna telesna težina i težina jaja, konzumacija i cena hrane. | N41: Недельная и масячная продуктивность, кол. яйца, живая масса, потребление и стоимость корма. | O41: الإنتاج اليومي والإسبوعي,أوزان البيض والجسم الأسبوعية , إستهلاك وسعر العلف | P41: 일간/주간 생산성, 주간 난중 및 체중, 사료가격 및 소비량 | Q41: 每天及每周的产蛋数、每周平均蛋重和体重、饲料消耗和饲料价格。 | R41: 日々と週間の産卵、週毎の卵重と体重、飼料摂取量、飼料価格
B42: 42 | C42: Lebensfähigkeit, % Lege, Eigewicht und Körpergeicht | D42: Liveability, % lay, egg weight and body weight | E42: Viabilidad, % puesta, peso de huevo y peso corporal | F42: Viabilité, pourcentage de ponte, Poids moyen d'œuf et Poids corporel. | G42: Daya hidup, % produksi , berat telur dan berat badan | H42: Vitalita',%Deposizione,Peso Dell'Uovo E Peso Corporeo | I42: leefbaarheid, legpercentage, eigewicht en lichaamsgewicht | J42: przeżywalność, % nieśności, waga jaj i masa ciała | K42: Viabilidade, % Postura, peso de ovos e peso corporal | L42: Životaschopnosť, % znášky, hmotnosť vajec a ŽH | M42: Vitalnost %, nosivost, težina jaja i telesna težina. | N42: Сохранность, % кладки, вес яйца и живая масса. | O42: نسبة الحيوية, نسبة الإنتاج, وزن البيض و وزن الجسم | P42: 생존율, 산란율(%), 난중 및 체중 | Q42: 存活率、产蛋率、蛋重及体重。 | R42: 生存率、産卵率、卵重、体重
B43: 43 | C43: Eimasse, Ver rauch und kum. Eiansahl | D43: Egg mass, consumption and cum. egg no. | E43: Masa de huevo, consumo y nº de huevos acumulado. | F43: Masse d'œuf, consommation et nombre d'œufs cumulés. | G43: Egg mass, konsumsi dan kum. Jml. telur | H43: Massa Uova,Consumo E Nr.Cumulativo Di Uova | I43: eimassa, voeropname en cumulatief aantal eieren | J43: Masa jaj, spożycie paszy i liczba jaj narastająco | K43: Massa de ovos, consumo e numero de ovos acumulado | L43: Množstvo vaječnej hmoty, príjem KZ a kumulatívny počet vajec | M43: Jajčana masa, konzumacija i kumulativan broj jaja | N43: Яйцемасса, потребление и общее количество яйца. | O43: كتلة البيض, استهلاك العلف وعدد البيض التراكمي | P43: 에그매스(산란량), 소비량 및 합산, 계란수 | Q43: 产蛋重、饲料消耗和累计产蛋数。 | R43: 採卵重量、飼料摂取量、累計産卵数
B44: 44 | C44: Futterverwertungsrate und Futterverwertung pro Ei | D44: Feed conversion ratio and feed conversion/egg | E44: Índice de conversión y conversión pienso/huevo | F44: Indice de conversion au kilo et à l'œuf. | G44: Rasio konversi pakan dan konversi pakan / telur | H44: Conversione Mangime E Conversione Mangime Per Uovo | I44: voederconversie en voederconversie per ei | J44: wykorzystanie paszy i spożycie paszy na jajo | K44: Taxa de conversão alimentar e conversão alimento/ovo | L44: Konverzia KZ kg/kg a konverzia na vajce | M44: Konverzija hrane i konverzija hrane /jaja | N44: Конверсия корма и конверсия корма на яйцо. | O44: معدل تحويل العلف و معدل تحويل/البيض | P44: 사료 전환율 및 개당 사료 효율 | Q44: 饲料转换率及每枚蛋的饲料消耗。 | R44: 飼料要求率
B45: 45 | C45: Graph für die Farmsortierung und Eierhändlersortierung | D45: Downgrading farm and packing station, weekly and cum. | E45: Huevos de segunda en granja y centro de clasificación, semanal y acumulado. | F45: Nombre de déclassés en ferme et en centre de conditionnement hebdo et cumulé. | G45: Non standar dari farm , dari gudang telur, mingguan dan kumulatif | H45: Downgrading Farm And Packing Station, Weekly And Cum. | I45: 2e soort af legbedrijf en pakstation, per week en cumulatief | J45: ilość odpadów na fermie i zakładzie pakowym tygodniowo i narastająco | K45: Ovos de segunda granja e sala de classificação, semanal e acumulado | L45: Množstvo neštandardných na farme a v triediarni, týždenne a kumulatívne | M45: Klasiranje jaja na farmi i u centru za klasiranje, nedeljno i kumulativno | N45: Сортировка, еженедельный прирост. | O45: عدد البيض درجة ثانية الإسبوعي والمتراكم في المزرعة و في محطة التوضيب | P45: 다운 그레이드 농장 및 포장 시설, 주간성적 및 누적. | Q45: 每周及累计次品蛋数（鸡场及分级站）。 | R45: 農場とパッキングセンターにおける格外卵（週毎と累計）
B46: 46 | C46: Eigewichtsverteilung und Anzahl von produzierten Eiern pro Sorte | D46: Egg weight distribution and number of eggs produced per grading | E46: Clasificación de huevos por tamaño y número de huevos producidos por clase | F46: Répartition des calibres en % et en quantité. | G46: Distribusi berat telur dan jumlah telur yang dihasilkan per grade | H46: Distribuzione Peso Uovo E N°Di Uova Prodotte Per Classe Di Peso | I46: verdeling van de eigewichten en aantal eieren per gewichtsklasse | J46: rozkład wagi jaj i ilość jaj zniesiona w poszczególnych klasach | K46: Distribuição de peso dos ovos e numero de ovos por classificação | L46: Rozdelenie hmotnosti vajec a počty vajec v hmotnostných triedach | M46: Distribucija težine jaja i broj jaja prema klasi | N46: Вес яйца и количество яйца по котегориям. | O46: توزيع وزن البيض و عدد البيض المنتج حسب الحجم | P46: 난중분포, 등급 별 계란 수 | Q46: 蛋重分布及每级蛋数 | R46: 卵重分布と規格卵数
B47: 47 | C47: % Eisortierung Reperation | D47: % egg grading repartion. | E47: % clasificación de huevo. | F47: Répartition des calibres en % | G47: % pembagian grading telur | H47: % Egg Grading Repartion. | I47: procentuele verdeling van de gewichtsklassen van de eieren | J47: % rozkład wagowy jaj w wg klas | K47: Repartição do % de ovos por classificação | L47: % rozdelenie vajec v hmotnostných triedach | M47: % klasiranje jaja | N47: % яйца по категориям. | O47: نسبة توزيع حجم البيض (%) | P47: 등급 비율별 계란 재분할. | Q47: 每等级蛋的百分比 | R47: 規格卵割合
B48: 48 | C48: Quantitative Eiproduktion pro Sortierung | D48: Quantity egg produced per grading | E48: Cantidad de huevos producidos por clase de peso | F48: Répartition des calibres en quantité | G48: Jumlah telur yang dihasilkan per grading | H48: Quantita' Di Uova Prodotte Per Classe Di Peso | I48: hoeveelheid eieren per gewichtsklasse | J48: ilość jaj wyprodukowana w danej klasie | K48: Quantidade de ovos por classificação | L48: Množstvo vajec v hmotnostných triedach | M48: Količina proizvedenih jaja po klasama | N48: Количество яйца по категориям. | O48: كمية البيض المنتج حسب الحجم | P48: 등급 당 계란 생산량 | Q48: 每等级蛋的数量 | R48: 規格分別毎の産卵数
B49: 49 | C49: Wöchentliche Futterkosten pro Tonne, kg Ei und Vogel. | D49: Weekly feed cost in ton, kg, egg and bird. | E49: Coste semanal del pienso en Tm, kg, huevo y ave. | F49: Coût hebdo en aliment par tonne, kilo d'œuf, œuf et poule. | G49: Biaya pakan mingguan dalam ton, kg, telur dan ayam. | H49: Weekly Feed Cost In Ton, Kg, Egg And Bird. | I49: wekelijkse voerkosten per ton, per ei en per hen | J49: tygodniowy koszt paszy na tonę, kg jaj i na nioskę | K49: Custo semanal de alimento em ton., kg, ovos e aves | L49: Týždenné náklady na KZ, v t, kg, na vajce a na sliepku | M49: Nedeljni trošak hrane po toni, kg, jajetu i ptici | N49: Еженедельная стоимость тонны корма, кг, яйца и птицы. | O49: كلفة العلف الأسبوعي في طن,كلع,بيضة و دجاجة | P49: 주간 사료비(톤, kg, 계란, 계군) | Q49: 每周每吨饲料成本，公斤蛋成本及鸡的成本。 | R49: 飼料コスト計算（産卵重、卵、鶏当り）
... B51: 51 | C51: Detailierte Übersicht über die Herdendaten durch die Legeperiode alle 5 Wochen | D51: Detailed overview of the flock performance during the laying period every 5 weeks | E51: Vista detallada de los resultados del lote en producción por periodos de 5 semanas | F51: Vue détaillée des performances de ponte du lot toutes les 5 semaines | G51: Gambaran rinci tentang performa flock selama periode bertelur setiap 5 minggu | H51: Detailed Overview Of The Flock Performance During The Laying Period Every 5 Weeks | I51: gedetailleerd overzicht van de resultaten per 5 weken | J51: szczegółowy przegląd wyników stada w produkcji w okresach 5-tygodniowych | K51: Visão detalhada do desempenho do lote durante o período de postura a cada 5 semanas | L51: Detailný prehľad úžitkovosti kŕdľa v 5 týždňových intervaloch | M51: Detaljni prikaz performansi jata u periodu nosivosti svakih 5 nedelja | N51: Подробный обзор продуктивности стада каждые пять недель. | O51: لمحة مفصلة عن أداء الفوج خلال مرحلة الإنتاج كل خمسة أسابيع | P51: 5주 산란 기간 동안 자세한 계군 성적 개요 | Q51: 产蛋期每5周生产性能概况。 | R51: ５週齢ごとの産卵性成績のまとめ
B52: 52
B53: 53 | C53: Jahr | D53: Year | E53: Año | F53: Année | G53: Tahun | H53: Anno | I53: Jaar | J53: rok | K53: Ano | L53: Rok | M53: Godina | N53: Год | O53: السنة | P53: 연 | Q53: 年 | R53: 年
B54: 54 | C54: Monat | D54: Month | E54: Mes | F54: Mois | G54: Bulan | H54: Mese | I54: Maand | J54: miesiąc | K54: Mês | L54: Mesiac | M54: Mesec | N54: Месяц | O54: الشهر | P54: 월 | Q54: 月 | R54: 月
B55: 55 | C55: Datum | D55: Date | E55: Día | F55: Jours | G55: Tanggal | H55: Data | I55: Dag | J55: data | K55: Data | L55: Dátum | M55: Datum | N55: Число | O55: التاريخ | P55: 일 | Q55: 日 | R55: 日
B56: 56 | C56: Wir wären sehr dankbar für die Rückgabe ihrer Daten. | D56: We would be very pleased to receive your results | E56: Estaríamos muy agradecidos de recibir sus resultados | F56: Merci de nous envoyer vos résultats de performance | G56: Kami akan sangat senang menerima hasil anda | H56: We Would Be Very Pleased To Receive Your Results | I56: Wij zouden het zeer op prijs stellen uw resultaten te ontvangen, | J56: Będziemy bardzo wdzięczni za podzielenie się z nami wynikami | K56: Ficaríamos muito agradecidos de receber os resultados | L56: Budeme veľmi radi, ak nám pošlete svoje výsledky | M56: Veoma smo zahvalni da dobijemo vaše rezultate | N56: Мы будем рады получить выши результаты. | O56: مسرورين جداً لتلقي نتائجك الحقلية | P56: 농가의 결과를받게되어 매우 감사합니다. | Q56: 非常高兴能收到你的鸡群记录 | R56: データのご提供に感謝申し上げます
B57: 57 | C57: In Zusammenarbeit wird eine Übersicht über verschiedene Genitiken und deren Leistungen gesammelt. | D57: In order to create overviews of different breeds and compare their performances. | E57: El sistema permite generar resúmenes de resultados de las diferentes estirpes y comparar sus rendimientos. | F57: afin de vous procurer un meilleur support technique. | G57: Dalam rangka menciptakan gambaran jenis bibit (breed) yang berbeda dan membandingkan performa mereka. | H57: In Order To Create Overviews Of Different Breeds And Compare Their Performances. | I57: om beter inzicht te krijgen in praktijkcijfers en om overzichten van de verschillende rassen te kunnen maken. | J57: w celu stworzenia przeglądu linii i porównania wyników | K57: A fim de criar visões de diferentes linhagens e comparar suas performances. | L57: aby sme mohli vytvoriť prehľad za rôzne hybridy a porovnať ich úžitkovosť | M57: Kako bi dobili pregled različitih hibrida i uporedili njihove performanse | N57: Вы можете указывать несколько кроссов для сравнения показателей. | O57: بهدف خلق بيانات لعدة أعراق ومقارنة أدائهم | P57: 각기 다른 성적을 비교하여 전반적인 개요를 만들어갑니다. | Q57: 为了制定不同品种的生产标准及对比其产蛋性能. | R57: それぞれの入力で、複数の鶏種の性能についての比較が行えます
B58: 58 | C58: Die Übersicht ist möglich für alle ISA Mitarbeiter über OxyGen | D58: The overviews will be available on OxyGen for all ISA employees | G58: Gambaran ikhtisarnya akan tersedia pada oksigen untuk semua karyawan ISA | H58: The Overviews Will Be Available On Oxygen For All Isa Employees | J58: przegląd wyników będzie dostępny dla pracowników ISA na platformie Oxygen | M58: Pregled će biti dostupan na Oxygenu za sve zaposlene u ISA-i | N58: Все данные доступны в сервисе OxyGen для всех сотрудников ISA. | P58: 만들어진 개요는 모든 ISA임직원에게 산소와 같습니다. | R58: 現在は、ISA社関係者に対してのみ情報公開が可能です
B59: 59 | C59: Bitte senden sie das Dokument zu: isa.technicalfieldresults@hendrix-genetics.com | D59: Please send this document to: isa.technicalfieldresults@hendrix-genetics.com | E59: Por favor, envíe este documento a: isa.technicalfieldresults@hendrix-genetics.com | F59: Pour toute suggestion ou réclamation merci de vous adressez à : isa.technicalfieldresults@hendrix-genetics.com | G59: Silakan kirim dokumen ini ke: isa.technicalfieldresults @ hendrix-genetics.com | H59: Please Send This Document To: Isa.Technicalfieldresults@Hendrix-Genetics.Com | I59: Gelieve dit document te sturen naar ISA: isa.technicalfieldresults@hendrix-genetics.com | J59: prosimy o przesłanie wyników na adres: isa.technicalfieldresults@hendrix-genetics.com | K59: Por favor envie este documento para: Isa. technicalfieldresults@hendrix-genetics.com | L59: Prosím pošlite tento dokument na: isa.technicalfieldresults@hendrix-genetics.com | M59: Molim vas pošaljite ovaj dokument na : isa.technicalfieldresults@hendrix-genetics.com | N59: Отправьте ваши данные на: isa.technicalfieldresults@hendrix-genetics.com | O59: يرجى إرسال هذا المستند على البريد الإلكتروني التالي : isa.technicalfieldresults@hendrix-genetics.com | P59: 이 문서를 다음의 메일로 전송해주시기 바랍니다. isa.technicalfieldresults@hendrix-genetics.com | Q59: 请将此文件发往: isa.technicalfieldresults@hendrix-genetics.com | R59: このファイルは、isa.technicalfieldresults@hendrix-genetics.com へお送りください
B60: 60 | C60: Version | D60: Version: | E60: Versión: | F60: Version: | G60: Versi: | H60: Version: | I60: Versie | J60: versia : | K60: Versão: | L60: Verzia | M60: Verzija : | N60: Варианты: | O60: النسخة : | P60: 버전: | Q60: 版本: | R60: バージョン
A61: WS2 | B61: 61 | C61: Aufsuchteingabe | D61: Rearing input | E61: Datos de recría | F61: Suivi d'élevage | G61: Input growing | H61: Allevamento | I61: Invoer Opfok | J61: DANE ODCHOWU | K61: Dados de cria/recria | L61: Obdobie odchovu | M61: Unos odgoja | N61: Данные по выращиванию | O61: بيانات مرحلة النمو | P61: 육성기 입력 | Q61: 生长期记录 | R61: 育雛/育成期入力
B62: 62 | C62: Datum | D62: Date | E62: Fecha | F62: Date | G62: Tanggal | H62: Data | I62: Datum | J62: data | K62: Data | L62: Dátum | M62: Datum | N62: Дата | O62: التاريخ | P62: 일령 | Q62: 日期 | R62: 日付
B63: 63 | C63: Alter | D63: Age | E63: Edad | F63: Age | G63: Umur | H63: Eta' | I63: Leeftijd | J63: wiek | K63: Idade | L63: Vek | M63: Starost | N63: Возраст | O63: العمر | P63: 연령 | Q63: 周龄 | R63: 齢
B64: 64 | C64: Mortalität | D64: Mortality | E64: Mortalidad | F64: Mortalité | G64: Deplesi | H64: Mortalita' | I64: Uitval | J64: upadki | K64: Mortalidade | L64: Úhyn | M64: Uginuće | N64: Падеж | O64: الوفيات | P64: 폐사율 | Q64: 死亡 | R64: 斃死
B65: 65 | C65: Täglich | D65: Daily | E65: Diario | F65: Journalière | G65: Harian | H65: Giornaliero | I65: / dag | J65: dziennie | K65: Diário | L65: Denne | M65: Dnevno | N65: Ежедневно | O65: اليومي | P65: 일 | Q65: 每日 | R65: 日毎
B66: 66 | C66: wöchentlich | D66: Weekly | E66: Semanal | F66: Hebdo | G66: Mingguan | H66: Settimanale | I66: / week | J66: tygodniowo | K66: Semanal | L66: Týždenne | M66: Nedeljno | N66: Еженедельно | O66: الاسبوعي | P66: 주간 | Q66: 每周 | R66: 週毎
B67: 67 | C67: Kum. | D67: Cum. | E67: Acum. | F67: Cumulée | G67: Kum. | H67: Cum. | I67: Cum. | J67: narast. | K67: Acum. | L67: Kumulatív | M67: Kumulativno | N67: Нарастающим итогом | O67: التراكمي | P67: 누적 | Q67: 累计死亡 | R67: 累計
B68: 68 | C68: Austausch | D68: Transfer | E68: Traslado | F68: Transferts | G68: Transfer | H68: Trasferimento | I68: Overhokken | J68: przeklasowanie | K68: Transferência | L68: Presun | M68: Transfer | N68: Перевод | O68: نقل | P68: 이동 | Q68: 转群 | R68: 移動
B69: 69 | C69: Mortalität % | D69: Mortality % | E69: Mortalidad % | F69: % de mortalité | G69: Deplesi (%) | H69: Mortalita' % | I69: Uitval % | J69: upadki % | K69: % Mortalidade | L69: % úhynu | M69: Uginuće % | N69: Падеж % | O69: الوفيات (%) | P69: 폐사율(%) | Q69: 死亡率 % | R69: 斃死率 %
B70: 70 | C70: Anzahl an Hennen am ende der Periode | D70: Number of birds end of period | E70: Nª aves al final del periodo | F70: Nombre de poules | G70: Jumlah ayam akhir periode | H70: N° Di Animali A Fine Periodo | I70: # hennen eind periode | J70: liczba ptaków na koniec okresu | K70: Numero de aves no final do período | L70: Konečný stav sliepok | M70: Broj prica na kraju perioda | N70: Кол. птиц на конец периода | O70: عدد الطيور نهاية الفترة | P70: 계군 종료시 수수 | Q70: 期末鸡数 | R70: 期間最終羽数
B71: 71 | C71: Körpergewicht | D71: Body weight | E71: Peso corporal | F71: Poids corporel | G71: Berat badan | H71: Peso Corporeo | I71: lichaamsgewicht | J71: masa ciała | K71: Peso Corporal | L71: ŽH | M71: Telesna težina | N71: Живая масса | O71: وزن الجسم | P71: 체중 | Q71: 体重 | R71: 体重
B72: 72 | C72: aktuell (g) | D72: Actual (g) | E72: Real (g) | F72: Réel | G72: Aktual (g) | H72: Attuale(G) | I72: Actueel (g) | J72: rzeczywista (g) | K72: Atual (g) | L72: Skut (g) | M72: Stvarna gr. | N72: Фактически (г) | O72: الحالي (غ) | P72: 실제(g) | Q72: 实际 (g) | R72: 実績 (g)
B73: 73 | C73: Uniformität % | D73: Unif. % | E73: Unif. % | F73: Unif. % | G73: Keseragaman (%) | H73: Uniformita'% | I73: Unif. % | J73: wyrównanie % | K73: Unif. % (g) | L73: Unif. % | M73: Ujednačenost % | N73: Однородность % | O73: تجانس (%) | P73: 균일도(%) | Q73: 均匀度 % | R73: 均一性 %
... B84: 84 | C84: Impfungen oder Aktionen | D84: Vaccination or Operations | E84: Vacunaciones e intervenciones | F84: Vaccinations et opérations | G84: Vaksinasi atau pelaksanaan | H84: Vaccinazioni O Altre Operazioni | I84: Vaccinaties en behandelingen | J84: szczepienia i zabiegi | K84: Vacinações e manejos | L84: Vakcinácie a operácie | M84: Vakcinacije i operacije | N84: Вакцинации | O84: تطعيم أو العمليات | P84: 백신/작업 | Q84: 免疫或管理工作 | R84: ワクチン、その他管理事項
B85: 85
B86: 86 | C86: Name der Aufsuchtfarm | D86: Rearing farm name | E86: Nombre de la granja de recría: | F86: Poussinière | G86: Nama farm growing | H86: Nome Azienda Svezzamento | I86: Naam opfokbedrijf | J86: nazwa odchowalni | K86: Nome da granja de recria | L86: Názov odchovnej farmy | M86: Naziv farme za odgoj | N86: Где выращена птица | O86: إسم مزرعة التربية | P86: 육성농장명 | Q86: 育成场名称 | R86: 育雛・育成農場名
B87: 87 | C87: Anzahl an Eintagsküken | D87: Number of day old chickens | E87: Nº pollitos de 1 día: | F87: Nombre de poulettes départ | G87: Jumlah DOC | H87: Numero Pulcini Di 1 Giorno | I87: Aantal opgehokte kuikens | J87: liczba wstawionych ptaków | K87: Numero de pintainhas | L87: Počet JDK | M87: Broj jednodnevnih pilića | N87: Количество суточных цыплят | O87: عدد الفراخ عمر يوم واحد | P87: 초생추수 | Q87: 入舍雏鸡数 | R87: 餌付羽数
B88: 88 | C88: Stalleinrichtung | D88: Housing system | E88: Sistema de alojamiento: | F88: Système d'élevage | G88: Sistem kandang | H88: Sistema Di Allevamento | I88: Huisvestingssyteem | J88: rodzaj systemu utrzymania | K88: Sistema de alojamento | L88: Systém ustajnenia | M88: Sistem držanja | N88: Система содержания | O88: نظام السكني | P88: 계사구조 | Q88: 鸡舍类型 | R88: 鶏舎システム
B89: 89 | C89: Herdennr. | D89: Flock no. : | E89: Lote nº: | F89: Troupeau n°: | G89: Nomor Flock . : | H89: Gruppo N° | I89: Koppel nr. | J89: stado nr: | K89: Lote no.: | L89: Číslo kŕdľa.: | M89: Broj jata | N89: Стадо № : | O89: رقم الفوج | P89: 계군번호 | Q89: 鸡群编号： | R89: 鶏群番号
B90: 90 | C90: Stallnr. | D90: House no. | E90: Nave nº: | F90: Batiment n°: | G90: Nomor Kandang . | H90: Capannone N° | I90: Stal nr. | J90: hala nr: | K90: Galpão no.: | L90: Číslo haly | M90: Broj objekta | N90: Птичник №. | O90: رقم العنبر | P90: 계사번호 | Q90: 鸡舍编号： | R90: 鶏舎番号
B91: 91 | C91: Tranportdatum (Tag/Monat/Jahr) | D91: Transfer date (dd/mm/yyyy) | E91: Fecha de traslado (dd/mm/aaaa): | F91: Date de transfert (jj/mm/aaaa): | G91: Tanggal transfer (tgl /bln /tahun) | H91: Data Trasferimento(Gg/Mm/Aa) | I91: Ophokdatum (dd/mm/jjjj) | J91: data transferu (dd/mm/rrrr) | K91: Data de transferência (dd/mm/aaaa) | L91: Dátum presunu (dd/mm/rrrr) | M91: Datum transfera (dd/mm/gggg) | N91: Дата перевода (д/мес/год) | O91: تاريخ النقل (يوم/شهر/سنة) | P91: 이동날짜(일/월/년) | Q91: 转群时间(日/月/年) | R91: 移動日 (dd/mm/yyyy)
B92: 92 | C92: Alter beim Transport | D92: Age at transfer | E92: Edad al traslado: | F92: Age lors du transfert | G92: Umur saat transfer | H92: Eta'Al Trasferimento | I92: Leeftijd overhokken | J92: wiek przy transferze | K92: Idade na transferência | L92: Vek pri presune | M92: Starost pri preseljenju | N92: Возраст на момент перевода | O92: العمر عند النقل | P92: 이동주령 | Q92: 转群时周龄 | R92: 移動日齢
B93: 93 | C93: Wochen | D93: Weeks | E93: Semanas | F93: Semaines | G93: Minggu | H93: Settimane | I93: Weken | J93: tygodnie | K93: Semanas | L93: Týždne | M93: Nedelje | N93: Недели | O93: أسابيع | P93: 주령 | Q93: 第几周 | R93: 週
B94: 94 | C94: Tage | D94: Days | E94: Días | F94: Jours | G94: Hari | H94: Giorni | I94: Dagen | J94: dni | K94: Dias | L94: Dni | M94: Dani | N94: Дни | O94: أيام | P94: 일령 | Q94: 第几天 | R94: 日
B95: 95 | C95: Anzahl an eingestallten Junghennne | D95: No. of pullets transferred | E95: Nº de pollitas trasladadas | F95: Nombre de poulettes transférées | G95: Jumlah pullet yang ditransfer | H95: Nr.Di Pollastre Trasferite | I95: Aantal overgehokte hennen | J95: liczba ptaków przeniesionych | K95: Numero de frangas transferidas | L95: Počet presunutých kuričiek | M95: Broj preseljenih kokica | N95: Количество переведенных | O95: عدد الفراخ المنقولة | P95: 계군이동번호 | Q95: 转入育成鸡数量 | R95: 移動若雌数
B96: 96 | C96: Wasserverbrauch in Litern | D96: Water Cons in Ltrs | E96: Consumo de agua en l. | F96: Conso d'eau en litres | G96: Konsumsi air (liter) | H96: Consumo Acqua In Litri | I96: Water opn. in Ltrs | J96: spożycie wody (l) | K96: Consumo de água em Litros | L96: Spotreba vody v l | M96: Potrošnja vode u litrima | N96: Потребление воды в литрах | O96: إستهلاك المياه في الليترات | P96: 물소비량(리터) | Q96: 饮水量（升） | R96: 飲水量（ﾘｯﾄﾙ）
B97: 97 | C97: Verbrauch | D97: Consumptions | E97: Consumos | F97: Consommation | G97: Konsumsi | H97: Consumi | I97: Opnames: | J97: spożycie | K97: Consumo | L97: Spotreby | M97: Konzumacija | N97: Потребление | O97: الإستهلاك | P97: 소비량 | Q97: 料水消耗 | R97: 摂取量
... B99: 99 | C99: Wasser-/ Futterverhältniss | D99: Water/feed ratio | E99: Relación agua/pienso | F99: Ratio eau/aliment | G99: Rasio air / pakan | H99: Acqua/Mangime | I99: W/V verhouding | J99: stosunek woda/pasza | K99: Água/Consumo de alim. | L99: Pomer voda/krmivo | M99: Odnos vode/hrane | N99: Соотношение вода/корм | O99: نسبة مياه/علف | P99: 음사비 | Q99: 水料比 | R99: 飲水/飼料 比
A100: WS3 | B100: 100 | C100: Legeeingabe | D100: Laying input | E100: Datos de puesta | F100: Suivi de production | G100: Input laying | H100: Deposizione | I100: Invoer legbedrijf | J100: DANE PRODUKCYJNE | K100: Dados de Produção | L100: Obdobie produkcie | M100: Unos nosivosti | N100: Данные по кладке | O100: بيانات مرحلة الإنتاج | P100: 산란기 입력 | Q100: 产蛋期记录 | R100: 産卵期入力
B101: 101 | C101: Betriebsname | D101: Farm name: | E101: Nombre de la granja: | F101: Ferme: | G101: Nama Farm: | H101: Nome Allevamento | I101: Bedrijfsnaam | J101: Ferma: | K101: Nome da Granja | L101: Meno farmy: | M101: Naziv fame: | N101: Название фермы: | O101: إسم المزرعة | Q101: 鸡场名称: | R101: 農場名
B102: 102 | C102: Stallnummer | D102: House no. : | E102: Nave nº: | F102: N° Batiment: | G102: No. Kandang : | H102: Capannone Nr. | I102: Stal nr. | J102: nr hali: | K102: Galpão no.: | L102: Číslo haly: | M102: Broj objekta: | N102: Номер птичнике : | O102: رقم العنبر | P102: 계사번호: | Q102: 鸡舍编号 : | R102: 鶏舎番号
B103: 103 | C103: Schlupfdatum | D103: Hatch date: | E103: Fecha de nacimiento: | F103: Date d'éclosion | G103: Tanggal menetas: | H103: Data Di Schiusa | I103: Uitkomstdatum: | J103: data wylęgu: | K103: Data de nascimento: | L103: Dátum liahnutia: | M103: Datum inkubacije : | N103: Дата вывода: | O103: تاريخ التفقيس | P103: 부화일자: | Q103: 出雏日期: | R103: 孵化日
B104: 104 | C104: Datum der 18. Lebenswoche | D104: Date at 18 weeks old : | E104: Fecha a las 18 sem.: | F104: Date à 18 semaines d'age: | G104: Tanggal saat umur 18 minggu: | H104: Data A 18 Settimane | I104: 18 weken oud: | J104: data osiągnięcia 18 tyg. życia | K104: Data às 18 sem. de idade | L104: Dátum v 18 týždni veku: | M104: Datum 18 ned. Starosti: | N104: Дата на момент 18 недельного возраста: | O104: التاريخ في عمر 18 أسبوع | P104: 18주령일자: | Q104: 18周龄日期 : | R104: 18週齢日付
B105: 105 | C105: Umstallungsdatum | D105: Transfer date: | E105: Fecha de traslado: | F105: Date de transfert: | G105: Tanggal transfer: | H105: Date Del Trasferimento | I105: Opfhokdatum: | J105: data transferu: | K105: Data da transferência | L105: Dátum presunu: | M105: Datum preseljenja: | N105: Дата перевода: | O105: تاريخ النقل: | P105: 이동날짜: | Q105: 转群日期: | R105: 移動日
B106: 106 | C106: Anzahl an eingestallten Junghennne | D106: Number of laying birds housed: | E106: Número de aves alojadas: | F106: Nombre de poules départ: | G106: Jumlah ayam produksi di kandang : | H106: Nr.Di Ovaiole Accasate | I106: Aantal opgehokte hennen: | J106: liczba ptaków przeklasowanych | K106: Numero de aves alojadas | L106: Počet zastavených nosníc: | M106: Broj useljenih nosilja: | N106: Количество несушек в птичнике: | O106: عدد الفراخ المسكنة | P106: 가임계사수: | Q106: 入舍鸡数: | R106: 成鶏移動羽数
B107: 107
B108: 108 | C108: Datum des Wochenbeginns | D108: Date beginning of the week | E108: Fecha inicio de semana | F108: Date en début de semaine | G108: Tanggal awal minggu | H108: Data Di Inizio Settimana | I108: Begindatum week | J108: data początku tyg. | K108: Data no inicio da semana | L108: Dátum začiatku týždňa | M108: Datum početka nedelje: | N108: Дата на начало недели | O108: تاريخ بداية الإسبوع | P108: 주령시작일자 | Q108: 本周开始的日期 | R108: 週開始日
B109: 109 | C109: Lebenswochen | D109: Age in weeks | E109: Edad en sem. | F109: Age en semaine | G109: Umur (minggu) | H109: Età In Settimane | I109: Leeft. In wkn | J109: wiek w tyg. | K109: Idade em semanas | L109: Vek v týždňoch | M109: Starost u nedeljama | N109: Возраст в неделях | O109: العمر في الأسابيع | P109: 주령 | Q109: 周龄 | R109: 週齢
B110: 110 | C110: Anzahl an Tieren am Ende der Woche | D110: No. of birds end of week | E110: Nº de aves al final de sem. | F110: Nombre de poules fin de semaine | G110: Jumlah ayam akhir minggu | H110: Nr.Di Animali A Fine Settimana | I110: Aant. Hennen eind wk. | J110: liczba ptaków na koniec tyg. | K110: Número de aves no final da semana | L110: Konečný stav v týždni | M110: Br.ptica na kraju nedelje | N110: Кол. птиц на конец недели | O110: عدد الطيور نهاية الأسبوع | P110: 주령 말일 수수 | Q110: 周末存栏鸡数 | R110: 週最終残存羽数
B111: 111 | C111: Wöchentliche Mortalität Anzahl an Tieren | D111: Weekly mortality No. of birds | E111: Mortalidad semanal (nº de aves) | F111: Mortalité hebdo | G111: Jumlah deplesi ayam mingguan | H111: Nr.Di Animali Settimanali | I111: Uitval / week (aant. Hennen) | J111: upadki w tyg. | K111: Mortalidade semanal No. de aves | L111: Týždenný úhyn v ks | M111: Nedeljno uginuće br. Ptica | N111: Количество падежа за неделю | O111: عدد الوفيات الأسبوعية | P111: 주간폐사수수 | Q111: 本周死亡鸡数 | R111: 週間死亡羽数
B112: 112
...

Sheet Graph values
B4: =Language!B258 -> Liveability | C4: =Language!B259 -> Weekly mortality % | D4: =Language!B260 -> Laying % | E4: =Language!B261 -> Laying rate std. | F4: =Language!B262 -> Egg Weight | G4: =Language!B263 -> Egg weight std. | H4: =Language!B264 -> Body weight | J4: =Language!B265 -> Laying body weight std. | K4: =Language!B266 -> Cons | L4: =Language!B267 -> Egg mass | M4: =Language!B268 -> Daily egg mass std. | N4: =Language!B269 -> Rearing | O4: =Language!B273 -> Cum. | P4: =Language!B271 -> Seconds farm | Q4: =Language!B272 -> Packing station | R4: =Language!B182 -> Weekly | S4: =Language!B274 -> Day hen | T4: =Language!B275 -> Cum. feed/bird /day | U4: =Language!B276 -> Wk FCR | V4: =Language!B277 -> Cum. FCR | W4: =Language!B278 -> Wk FCR/egg | X4: =Language!B279 -> Cum FCR/egg | Y4: =Language!B280 -> Cumulative egg number | Z4: =Language!B281 -> Std. | AD4: Semaine de présence cumulées | AF4: STD | AM4: STD
B5: Real | C5: Real | D5: Real | F5: Real | H5: Graph redone | K5: Daily | L5: Real | AE5: Wk | AF5: Lay 1 | AG5: Lay 2 | AH5: Lay 3 | AI5: Lay 4 | AJ5: Lay 5 | AK5: Lay 6 | AL5: Lay 7 | AM5: EW 1 | AN5: EW 2 | AO5: EW 3 | AP5: EW 4 | AQ5: EW 5 | AR5: EW 6 | AS5: EW 7 | AT5: eggs HD | AU5: eggs HD cum | AV5: Week | AW5: egg mass HD wk | AX5: egg mass HD cum | BA5: PMO RETENU | BC5: Cumul Petit | BD5: Cumul Moyen | BE5: Cumul Gros | BF5: Cumul Très gros
A6: 16 | B6: #N/A | C6: #N/A | D6: #N/A | E6: #N/A | F6: #N/A | G6: #N/A | H6: #N/A | I6: #N/A | J6: #N/A | K6: #N/A | L6: #N/A | M6: #N/A | O6: #N/A | P6: #N/A | Q6: #N/A | R6: #N/A | T6: #N/A | U6: #N/A | V6: #N/A | W6: #N/A | X6: #N/A | Y6: #N/A | Z6: #N/A | BA6: =IF('Egg grading'!C10="",IF('Egg grading'!B10="","",'Egg grading'!B10),'Egg grading'!C10) | BC6: ='Egg grading'!K10 | BD6: ='Egg grading'!L10 | BE6: ='Egg grading'!M10 | BF6: ='Egg grading'!N10
A7: ='Production data'!B14 -> 17 | B7: =IF('Production data'!C14="",#N/A,'Production data'!C14) -> #N/A | C7: =IF(OR('Input Laying'!E15=0),#N/A,'Input Laying'!E15/'Input Laying'!$G$6*100*25) -> #N/A | D7: =IF(OR('Production data'!D14="",'Production data'!D14=0),0,'Production data'!D14) -> 0 | E7: =IF(OR(Std!B20="",Std!B20=0),0,Std!B20) -> 0 | F7: =IF('Production data'!H14="",0,'Production data'!H14) -> 0 | G7: =IF(OR(Std!C20="",Std!C20=0),0,Std!C20) -> 0 | H7: =IF(I7<0,#N/A,I7) -> #N/A | I7: =('Input Laying'!AH15-1000)/25 -> -40 | J7: =IF((Std!D20-1000)/25<15,#N/A,(Std!D20-1000)/25) -> 17.58 | K7: =IF('Production data'!P14="",#N/A,'Production data'!P14) -> #N/A | L7: =IF('Production data'!L14="",#N/A,'Production data'!L14) -> #N/A | M7: =IF(Std!E20=0,0,Std!E20) -> 0 | O7: =IF('Input Laying'!V15=0,NA(),IF('Input Laying'!V15="",NA(),'Input Laying'!W15/'Input Laying'!O15*100)) -> #N/A | P7: =IF('Input Laying'!T15="",#N/A,'Input Laying'!T15/'Input Laying'!N15*100) -> #N/A | Q7: =IF('Input Laying'!U15="",#N/A,'Input Laying'!U15/'Input Laying'!N15*100) -> #N/A | R7: =IF('Input Laying'!V15="",#N/A,'Production data'!W14) | S7: ='Input Laying'!D15*7 -> 0 | T7: =IF(OR('Input Laying'!AF15="",'Input Laying'!D15=0,'Input Laying'!O15=0),"#N/A",'Input Laying'!AF15/'Input Laying'!D15/(AD7*7)*1000) -> #N/A | U7: =IF('Production data'!U14="",#N/A,'Production data'!U14) -> #N/A | V7: =IF('Production data'!V14="",#N/A,'Production data'!V14) -> #N/A | W7: =IF('Production data'!S14="",#N/A,'Production data'!S14) -> #N/A | X7: =IF('Production data'!T14="",#N/A,'Production data'!T14) -> #N/A | Y7: =IF('Input Laying'!E15="",#N/A,'Production data'!F14) -> #N/A | Z7: =IF('Production data'!G14="",#N/A,'Production data'!G14) -> #N/A | AD7: =IF('Input Laying'!AF15=0,0,(IF('Input Laying'!N15>0,1,IF('Input Laying'!O15>0,0,1)))) -> 0 | AM7: =G7 -> 0 | AT7: =E7*7/100 -> 0 | AU7: =AT7+AU6 -> 0 | AW7: =(G7*E7/100)*7 -> 0 | AX7: =AX6+(AW7/1000) -> 0 | AZ7: 17 | BA7: =IF('Egg grading'!C11="",IF('Egg grading'!B11="","",'Egg grading'!B11),'Egg grading'!C11) | BC7: =IF(BC6="",'Egg grading'!K11,BC6+'Egg grading'!K11) | BD7: =IF(BD6="",'Egg grading'!L11,BD6+'Egg grading'!L11) | BE7: =IF(BE6="",'Egg grading'!M11,BE6+'Egg grading'!M11) | BF7: =IF(BF6="",'Egg grading'!N11,BF6+'Egg grading'!N11)
A8: ='Production data'!B15 -> 18 | B8: =IF('Production data'!C15="",#N/A,'Production data'!C15) -> #N/A | C8: =IF(OR('Input Laying'!E16=0,'Input Laying'!D15=0),#N/A,'Input Laying'!E16/'Input Laying'!D15*100*25) -> #N/A | D8: =IF(OR('Production data'!D15="",'Production data'!D15=0),0,'Production data'!D15) -> 0 | E8: =IF(OR(Std!B21="",Std!B21=0),0,Std!B21) -> 3 | F8: =IF('Production data'!H15="",0,'Production data'!H15) -> 0 | G8: =IF(OR(Std!C21="",Std!C21=0),0,Std!C21) -> 42.49223 | H8: =IF(I8<0,#N/A,I8) -> #N/A | I8: =('Input Laying'!AH16-1000)/25 -> -40 | J8: =IF((Std!D21-1000)/25<15,#N/A,(Std!D21-1000)/25) -> 20 | K8: =IF('Production data'!P15="",#N/A,'Production data'!P15) -> #N/A | L8: =IF('Production data'!L15="",#N/A,'Production data'!L15) -> #N/A | M8: =IF(Std!E21=0,#N/A,Std!E21) -> 1.2747669 | O8: =IF('Input Laying'!V16=0,NA(),IF('Input Laying'!V16="",NA(),'Input Laying'!W16/'Input Laying'!O16*100)) -> #N/A | P8: =IF('Input Laying'!T16="",#N/A,'Input Laying'!T16/'Input Laying'!N16*100) -> #N/A | Q8: =IF('Input Laying'!U16="",#N/A,'Input Laying'!U16/'Input Laying'!N16*100) -> #N/A | R8: =IF('Input Laying'!V16="",#N/A,'Production data'!W15) | S8: ='Input Laying'!D16*7+'Graph values'!S7 -> 0 | T8: =IF(OR('Input Laying'!AF16="",'Input Laying'!D16=0,'Input Laying'!O16=0),"#N/A",'Input Laying'!AF16/'Input Laying'!D16/(AD8*7)*1000) -> #N/A | U8: =IF('Production data'!U15="",#N/A,'Production data'!U15) -> #N/A | V8: =IF('Production data'!V15="",#N/A,'Production data'!V15) -> #N/A | W8: =IF('Production data'!S15="",#N/A,'Production data'!S15) -> #N/A | X8: =IF('Production data'!T15="",#N/A,'Production data'!T15) -> #N/A | Y8: =IF('Input Laying'!E16="",#N/A,'Production data'!F15) -> #N/A | Z8: =IF('Production data'!G15="",#N/A,'Production data'!G15) -> 0.2097984 | AD8: =IF('Input Laying'!AF16=0,0,(IF('Input Laying'!N16>0,1,IF('Input Laying'!O16>0,0,1))))+AD7 -> 0 | AE8: 18 | AF8: =IF(E8<1,#N/A,E8) -> 3 | AG8: =AF8-1.5 -> 1.5 | AH8: =AG8-1.5 -> 0 | AI8: =AH8-1.5 -> -1.5 | AJ8: =AI8-1.5 -> -3 | AK8: =AJ8-1.5 -> -4.5 | AL8: =AK8-1.5 -> -6 | AM8: =G8 -> 42.49223 | AN8: =AM8-0.3 -> 42.19223 | AO8: =AN8-0.3 -> 41.89223 | AP8: =AO8-0.3 -> 41.59223 | AQ8: =AP8-0.3 -> 41.29223 | AR8: =AQ8-0.3 -> 40.99223 | AS8: =AR8-0.3 -> 40.69223 | AT8: =E8*7/100 -> 0.21 | AU8: =AT8+AU7 -> 0.21 | AV8: 18 | AW8: =(G8*E8/100)*7 -> 8.9233682 | AX8: =AX7+(AW8/1000) -> 0.0089233682 | AZ8: 18 | BA8: =IF('Egg grading'!C12="",IF('Egg grading'!B12="","",'Egg grading'!B12),'Egg grading'!C12) -> 42.49223 | BC8: =IF(BC7="",'Egg grading'!K12,BC7+'Egg grading'!K12) | BD8: =IF(BD7="",'Egg grading'!L12,BD7+'Egg grading'!L12) | BE8: =IF(BE7="",'Egg grading'!M12,BE7+'Egg grading'!M12) | BF8: =IF(BF7="",'Egg grading'!N12,BF7+'Egg grading'!N12)
A9: ='Production data'!B16 -> 19 | B9: =IF('Production data'!C16="",#N/A,'Production data'!C16) -> #N/A | C9: =IF(OR('Input Laying'!E17=0,'Input Laying'!D16=0),#N/A,'Input Laying'!E17/'Input Laying'!D16*100*25) -> #N/A | D9: =IF(OR('Production data'!D16="",'Production data'!D16=0),0,'Production data'!D16) -> 0 | E9: =IF(OR(Std!B22="",Std!B22=0),0,Std!B22) -> 10.981495 | F9: =IF('Production data'!H16="",0,'Production data'!H16) -> 0 | G9: =IF(OR(Std!C22="",Std!C22=0),#N/A,Std!C22) -> 46.165714 | H9: =IF(I9<0,#N/A,I9) -> #N/A | I9: =('Input Laying'!AH17-1000)/25 -> -40 | J9: =IF((Std!D22-1000)/25<15,#N/A,(Std!D22-1000)/25) -> 22.345926 | K9: =IF('Production data'!P16="",#N/A,'Production data'!P16) -> #N/A | L9: =IF('Production data'!L16="",#N/A,'Production data'!L16) -> #N/A | M9: =IF(Std!E22=0,#N/A,Std!E22) -> 5.0696855 | O9: =IF('Input Laying'!V17=0,NA(),IF('Input Laying'!V17="",NA(),'Input Laying'!W17/'Input Laying'!O17*100)) -> #N/A | P9: =IF('Input Laying'!T17="",#N/A,'Input Laying'!T17/'Input Laying'!N17*100) -> #N/A | Q9: =IF('Input Laying'!U17="",#N/A,'Input Laying'!U17/'Input Laying'!N17*100) -> #N/A | R9: =IF('Input Laying'!V17="",#N/A,'Production data'!W16) | S9: ='Input Laying'!D17*7+'Graph values'!S8 -> 0 | T9: =IF(OR('Input Laying'!AF17="",'Input Laying'!D17=0,'Input Laying'!O17=0),"#N/A",'Input Laying'!AF17/'Input Laying'!D17/(AD9*7)*1000) -> #N/A | U9: =IF('Production data'!U16="",#N/A,'Production data'!U16) -> #N/A | V9: =IF('Production data'!V16="",#N/A,'Production data'!V16) -> #N/A | W9: =IF('Production data'!S16="",#N/A,'Production data'!S16) -> #N/A | X9: =IF('Production data'!T16="",#N/A,'Production data'!T16) -> #N/A | Y9: =IF('Input Laying'!E17="",#N/A,'Production data'!F16) -> #N/A | Z9: =IF('Production data'!G16="",#N/A,'Production data'!G16) -> 0.97702713 | AD9: =IF('Input Laying'!AF17=0,0,(IF('Input Laying'!N17>0,1,IF('Input Laying'!O17>0,0,1))))+AD8 -> 0 | AE9: 19 | AF9: =IF(E9<1,#N/A,E9) -> 10.981495 | AG9: =IF(AF9-1.5<1,#N/A,AF9-1.5) -> 9.4814948 | AH9: =IF(AG9-1.5<1,#N/A,AG9-1.5) -> 7.9814948 | AI9: =IF(AH9-1.5<1,#N/A,AH9-1.5) -> 6.4814948 | AJ9: =IF(AI9-1.5<1,#N/A,AI9-1.5) -> 4.9814948 | AK9: =IF(AJ9-1.5<1,#N/A,AJ9-1.5) -> 3.4814948 | AL9: =IF(AK9-1.5<1,#N/A,AK9-1.5) -> 1.9814948 | AM9: =G9 -> 46.165714 | AN9: =AM9-0.3 -> 45.865714 | AO9: =AN9-0.3 -> 45.565714 | AP9: =AO9-0.3 -> 45.265714 | AQ9: =AP9-0.3 -> 44.965714 | AR9: =AQ9-0.3 -> 44.665714 | AS9: =AR9-0.3 -> 44.365714 | AT9: =E9*7/100 -> 0.76870464 | AU9: =AT9+AU8 -> 0.97870464 | AV9: 19 | AW9: =IFERROR((G9*E9/100)*7,0) -> 35.487798 | AX9: =AX8+(AW9/1000) -> 0.044411166 | AZ9: 19 | BA9: =IF('Egg grading'!C13="",IF('Egg grading'!B13="","",'Egg grading'!B13),'Egg grading'!C13) -> 46.165714 | BC9: =IF(BC8="",'Egg grading'!K13,BC8+'Egg grading'!K13) | BD9: =IF(BD8="",'Egg grading'!L13,BD8+'Egg grading'!L13) | BE9: =IF(BE8="",'Egg grading'!M13,BE8+'Egg grading'!M13) | BF9: =IF(BF8="",'Egg grading'!N13,BF8+'Egg grading'!N13)
A10: ='Production data'!B17 -> 20 | B10: =IF('Production data'!C17="",#N/A,'Production data'!C17) -> #N/A | C10: =IF(OR('Input Laying'!E18=0,'Input Laying'!D17=0),#N/A,'Input Laying'!E18/'Input Laying'!D17*100*25) -> #N/A | D10: =IF(OR('Production data'!D17="",'Production data'!D17=0),0,'Production data'!D17) -> 0 | E10: =IF(OR(Std!B23="",Std!B23=0),0,Std!B23) -> 31.090326 | F10: =IF('Production data'!H17="",#N/A,'Production data'!H17) -> #N/A | G10: =IF(OR(Std!C23="",Std!C23=0),#N/A,Std!C23) -> 49.278199 | H10: =IF(I10<0,#N/A,I10) -> #N/A | I10: =('Input Laying'!AH18-1000)/25 -> -40 | J10: =IF((Std!D23-1000)/25<15,#N/A,(Std!D23-1000)/25) -> 24.860649 | K10: =IF('Production data'!P17="",#N/A,'Production data'!P17) -> #N/A | L10: =IF('Production data'!L17="",#N/A,'Production data'!L17) -> #N/A | M10: =IF(Std!E23=0,#N/A,Std!E23) -> 15.320753 | O10: =IF('Input Laying'!V18=0,NA(),IF('Input Laying'!V18="",NA(),'Input Laying'!W18/'Input Laying'!O18*100)) -> #N/A | P10: =IF('Input Laying'!T18="",#N/A,'Input Laying'!T18/'Input Laying'!N18*100) -> #N/A | Q10: =IF('Input Laying'!U18="",#N/A,'Input Laying'!U18/'Input Laying'!N18*100) -> #N/A | R10: =IF('Input Laying'!V18="",#N/A,'Production data'!W17) | S10: ='Input Laying'!D18*7+'Graph values'!S9 -> 0 | T10: =IF(OR('Input Laying'!AF18="",'Input Laying'!D18=0,'Input Laying'!O18=0),"#N/A",'Input Laying'!AF18/'Input Laying'!D18/(AD10*7)*1000) -> #N/A | U10: =IF('Production data'!U17="",#N/A,'Production data'!U17) -> #N/A | V10: =IF('Production data'!V17="",#N/A,'Production data'!V17) -> #N/A | W10: =IF('Production data'!S17="",#N/A,'Production data'!S17) -> #N/A | X10: =IF('Production data'!T17="",#N/A,'Production data'!T17) -> #N/A | Y10: =IF('Input Laying'!E18="",#N/A,'Production data'!F17) -> #N/A | Z10: =IF('Production data'!G17="",#N/A,'Production data'!G17) -> 3.1470821 | AD10: =IF('Input Laying'!AF18=0,0,(IF('Input Laying'!N18>0,1,IF('Input Laying'!O18>0,0,1))))+AD9 -> 0 | AE10: 20 | AF10: =IF(E10<10,#N/A,E10) -> 31.090326 | AG10: =IF(AF10-1.5<10,#N/A,AF10-1.5) -> 29.590326 | AH10: =IF(AG10-1.5<10,#N/A,AG10-1.5) -> 28.090326 | AI10: =IF(AH10-1.5<10,#N/A,AH10-1.5) -> 26.590326 | AJ10: =IF(AI10-1.5<10,#N/A,AI10-1.5) -> 25.090326 | AK10: =IF(AJ10-1.5<10,#N/A,AJ10-1.5) -> 23.590326 | AL10: =IF(AK10-1.5<10,#N/A,AK10-1.5) -> 22.090326 | AM10: =G10 -> 49.278199 | AN10: =AM10-0.3 -> 48.978199 | AO10: =AN10-0.3 -> 48.678199 | AP10: =AO10-0.3 -> 48.378199 | AQ10: =AP10-0.3 -> 48.078199 | AR10: =AQ10-0.3 -> 47.778199 | AS10: =AR10-0.3 -> 47.478199 | AT10: =E10*7/100 -> 2.1763228 | AU10: =AT10+AU9 -> 3.1550274 | AV10: 20 | AW10: =(G10*E10/100)*7 -> 107.24527 | AX10: =AX9+(AW10/1000) -> 0.15165643 | AZ10: 20 | BA10: =IF('Egg grading'!C14="",IF('Egg grading'!B14="","",'Egg grading'!B14),'Egg grading'!C14) -> 49.278199 | BC10: =IF(BC9="",'Egg grading'!K14,BC9+'Egg grading'!K14) | BD10: =IF(BD9="",'Egg grading'!L14,BD9+'Egg grading'!L14) | BE10: =IF(BE9="",'Egg grading'!M14,BE9+'Egg grading'!M14) | BF10: =IF(BF9="",'Egg grading'!N14,BF9+'Egg grading'!N14)
A11: ='Production data'!B18 -> 21 | B11: =IF('Production data'!C18="",#N/A,'Production data'!C18) -> #N/A | C11: =IF(OR('Input Laying'!E19=0,'Input Laying'!D18=0),#N/A,'Input Laying'!E19/'Input Laying'!D18*100*25) -> #N/A | D11: =IF(OR('Production data'!D18="",'Production data'!D18=0),0,'Production data'!D18) -> 0 | E11: =IF(OR(Std!B24="",Std!B24=0),0,Std!B24) -> 49.193548 | F11: =IF('Production data'!H18="",#N/A,'Production data'!H18) -> #N/A | G11: =IF(OR(Std!C24="",Std!C24=0),#N/A,Std!C24) -> 51.89266 | H11: =IF(I11<0,#N/A,I11) -> #N/A | I11: =('Input Laying'!AH19-1000)/25 -> -40 | J11: =IF((Std!D24-1000)/25<15,#N/A,(Std!D24-1000)/25) -> 27.375372 | K11: =IF('Production data'!P18="",#N/A,'Production data'!P18) -> #N/A | L11: =IF('Production data'!L18="",#N/A,'Production data'!L18) -> #N/A | M11: =IF(Std!E24=0,#N/A,Std!E24) -> 25.527841 | O11: =IF('Input Laying'!V19=0,NA(),IF('Input Laying'!V19="",NA(),'Input Laying'!W19/'Input Laying'!O19*100)) -> #N/A | P11: =IF('Input Laying'!T19="",#N/A,'Input Laying'!T19/'Input Laying'!N19*100) -> #N/A | Q11: =IF('Input Laying'!U19="",#N/A,'Input Laying'!U19/'Input Laying'!N19*100) -> #N/A | R11: =IF('Input Laying'!V19="",#N/A,'Production data'!W18) | S11: ='Input Laying'!D19*7+'Graph values'!S10 -> 0 | T11: =IF(OR('Input Laying'!AF19="",'Input Laying'!D19=0,'Input Laying'!O19=0),"#N/A",'Input Laying'!AF19/'Input Laying'!D19/(AD11*7)*1000) -> #N/A | U11: =IF('Production data'!U18="",#N/A,'Production data'!U18) -> #N/A | V11: =IF('Production data'!V18="",#N/A,'Production data'!V18) -> #N/A | W11: =IF('Production data'!S18="",#N/A,'Production data'!S18) -> #N/A | X11: =IF('Production data'!T18="",#N/A,'Production data'!T18) -> #N/A | Y11: =IF('Input Laying'!E19="",#N/A,'Production data'!F18) -> #N/A | Z11: =IF('Production data'!G18="",#N/A,'Production data'!G18) -> 6.5774073 | AD11: =IF('Input Laying'!AF19=0,0,(IF('Input Laying'!N19>0,1,IF('Input Laying'!O19>0,0,1))))+AD10 -> 0 | AE11: 21 | AF11: =IF(E11<10,#N/A,E11) -> 49.193548 | AG11: =AF11-1.5 -> 47.693548 | AH11: =AG11-1.5 -> 46.193548 | AI11: =AH11-1.5 -> 44.693548 | AJ11: =AI11-1.5 -> 43.193548 | AK11: =AJ11-1.5 -> 41.693548 | AL11: =AK11-1.5 -> 40.193548 | AM11: =G11 -> 51.89266 | AN11: =AM11-0.3 -> 51.59266 | AO11: =AN11-0.3 -> 51.29266 | AP11: =AO11-0.3 -> 50.99266 | AQ11: =AP11-0.3 -> 50.69266 | AR11: =AQ11-0.3 -> 50.39266 | AS11: =AR11-0.3 -> 50.09266 | AT11: =E11*7/100 -> 3.4435484 | AU11: =AT11+AU10 -> 6.5985758 | AV11: 21 | AW11: =(G11*E11/100)*7 -> 178.69489 | AX11: =AX10+(AW11/1000) -> 0.33035132 | AZ11: 21 | BA11: =IF('Egg grading'!C15="",IF('Egg grading'!B15="","",'Egg grading'!B15),'Egg grading'!C15) -> 51.89266 | BC11: =IF(BC10="",'Egg grading'!K15,BC10+'Egg grading'!K15) | BD11: =IF(BD10="",'Egg grading'!L15,BD10+'Egg grading'!L15) | BE11: =IF(BE10="",'Egg grading'!M15,BE10+'Egg grading'!M15) | BF11: =IF(BF10="",'Egg grading'!N15,BF10+'Egg grading'!N15)
A12: ='Production data'!B19 -> 22 | B12: =IF('Production data'!C19="",#N/A,'Production data'!C19) -> #N/A | C12: =IF(OR('Input Laying'!E20=0,'Input Laying'!D19=0),#N/A,'Input Laying'!E20/'Input Laying'!D19*100*25) -> #N/A | D12: =IF(OR('Production data'!D19="",'Production data'!D19=0),0,'Production data'!D19) -> 0 | E12: =IF(OR(Std!B25="",Std!B25=0),0,Std!B25) -> 66.812852 | F12: =IF('Production data'!H19="",#N/A,'Production data'!H19) -> #N/A | G12: =IF(OR(Std!C25="",Std!C25=0),#N/A,Std!C25) -> 54.068332 | H12: =IF(I12<0,#N/A,I12) -> #N/A | I12: =('Input Laying'!AH20-1000)/25 -> -40 | J12: =IF((Std!D25-1000)/25<15,#N/A,(Std!D25-1000)/25) -> 28.913523 | K12: =IF('Production data'!P19="",#N/A,'Production data'!P19) -> #N/A | L12: =IF('Production data'!L19="",#N/A,'Production data'!L19) -> #N/A | M12: =IF(Std!E25=0,#N/A,Std!E25) -> 36.124595 | O12: =IF('Input Laying'!V20=0,NA(),IF('Input Laying'!V20="",NA(),'Input Laying'!W20/'Input Laying'!O20*100)) -> #N/A | P12: =IF('Input Laying'!T20="",#N/A,'Input Laying'!T20/'Input Laying'!N20*100) -> #N/A | Q12: =IF('Input Laying'!U20="",#N/A,'Input Laying'!U20/'Input Laying'!N20*100) -> #N/A | R12: =IF('Input Laying'!V20="",#N/A,'Production data'!W19) | S12: ='Input Laying'!D20*7+'Graph values'!S11 -> 0 | T12: =IF(OR('Input Laying'!AF20="",'Input Laying'!D20=0,'Input Laying'!O20=0),"#N/A",'Input Laying'!AF20/'Input Laying'!D20/(AD12*7)*1000) -> #N/A | U12: =IF('Production data'!U19="",#N/A,'Production data'!U19) -> #N/A | V12: =IF('Production data'!V19="",#N/A,'Production data'!V19) -> #N/A | W12: =IF('Production data'!S19="",#N/A,'Production data'!S19) -> #N/A | X12: =IF('Production data'!T19="",#N/A,'Production data'!T19) -> #N/A | Y12: =IF('Input Laying'!E20="",#N/A,'Production data'!F19) -> #N/A | Z12: =IF('Production data'!G19="",#N/A,'Production data'!G19) -> 11.231858 | AD12: =IF('Input Laying'!AF20=0,0,(IF('Input Laying'!N20>0,1,IF('Input Laying'!O20>0,0,1))))+AD11 -> 0 | AE12: 22 | AF12: =IF(E12<10,#N/A,E12) -> 66.812852 | AG12: =AF12-1.5 -> 65.312852 | AH12: =AG12-1.5 -> 63.812852 | AI12: =AH12-1.5 -> 62.312852 | AJ12: =AI12-1.5 -> 60.812852 | AK12: =AJ12-1.5 -> 59.312852 | AL12: =AK12-1.5 -> 57.812852 | AM12: =G12 -> 54.068332 | AN12: =AM12-0.3 -> 53.768332 | AO12: =AN12-0.3 -> 53.468332 | AP12: =AO12-0.3 -> 53.168332 | AQ12: =AP12-0.3 -> 52.868332 | AR12: =AQ12-0.3 -> 52.568332 | AS12: =AR12-0.3 -> 52.268332 | AT12: =E12*7/100 -> 4.6768996 | AU12: =AT12+AU11 -> 11.275475 | AV12: 22 | AW12: =(G12*E12/100)*7 -> 252.87216 | AX12: =AX11+(AW12/1000) -> 0.58322348 | AZ12: 22 | BA12: =IF('Egg grading'!C16="",IF('Egg grading'!B16="","",'Egg grading'!B16),'Egg grading'!C16) -> 54.068332 | BC12: =IF(BC11="",'Egg grading'!K16,BC11+'Egg grading'!K16) | BD12: =IF(BD11="",'Egg grading'!L16,BD11+'Egg grading'!L16) | BE12: =IF(BE11="",'Egg grading'!M16,BE11+'Egg grading'!M16) | BF12: =IF(BF11="",'Egg grading'!N16,BF11+'Egg grading'!N16)
A13: ='Production data'!B20 -> 23 | B13: =IF('Production data'!C20="",#N/A,'Production data'!C20) -> #N/A | C13: =IF(OR('Input Laying'!E21=0,'Input Laying'!D20=0),#N/A,'Input Laying'!E21/'Input Laying'!D20*100*25) -> #N/A | D13: =IF(OR('Production data'!D20="",'Production data'!D20=0),0,'Production data'!D20) -> 0 | E13: =IF(OR(Std!B26="",Std!B26=0),0,Std!B26) -> 82.197174 | F13: =IF('Production data'!H20="",#N/A,'Production data'!H20) -> #N/A | G13: =IF(OR(Std!C26="",Std!C26=0),#N/A,Std!C26) -> 55.860707 | H13: =IF(I13<0,#N/A,I13) -> #N/A | I13: =('Input Laying'!AH21-1000)/25 -> -40 | J13: =IF((Std!D26-1000)/25<15,#N/A,(Std!D26-1000)/25) -> 30.013506 | K13: =IF('Production data'!P20="",#N/A,'Production data'!P20) -> #N/A | L13: =IF('Production data'!L20="",#N/A,'Production data'!L20) -> #N/A | M13: =IF(Std!E26=0,#N/A,Std!E26) -> 45.915922 | O13: =IF('Input Laying'!V21=0,NA(),IF('Input Laying'!V21="",NA(),'Input Laying'!W21/'Input Laying'!O21*100)) -> #N/A | P13: =IF('Input Laying'!T21="",#N/A,'Input Laying'!T21/'Input Laying'!N21*100) -> #N/A | Q13: =IF('Input Laying'!U21="",#N/A,'Input Laying'!U21/'Input Laying'!N21*100) -> #N/A | R13: =IF('Input Laying'!V21="",#N/A,'Production data'!W20) | S13: ='Input Laying'!D21*7+'Graph values'!S12 -> 0 | T13: =IF(OR('Input Laying'!AF21="",'Input Laying'!D21=0,'Input Laying'!O21=0),"#N/A",'Input Laying'!AF21/'Input Laying'!D21/(AD13*7)*1000) -> #N/A | U13: =IF('Production data'!U20="",#N/A,'Production data'!U20) -> #N/A | V13: =IF('Production data'!V20="",#N/A,'Production data'!V20) -> #N/A | W13: =IF('Production data'!S20="",#N/A,'Production data'!S20) -> #N/A | X13: =IF('Production data'!T20="",#N/A,'Production data'!T20) -> #N/A | Y13: =IF('Input Laying'!E21="",#N/A,'Production data'!F20) -> #N/A | Z13: =IF('Production data'!G20="",#N/A,'Production data'!G20) -> 16.952518 | AD13: =IF('Input Laying'!AF21=0,0,(IF('Input Laying'!N21>0,1,IF('Input Laying'!O21>0,0,1))))+AD12 -> 0 | AE13: 23 | AF13: =IF(E13<10,#N/A,E13) -> 82.197174 | AG13: =AF13-0.9 -> 81.297174 | AH13: =AG13-0.9 -> 80.397174 | AI13: =AH13-1.5 -> 78.897174 | AJ13: =AI13-0.9 -> 77.997174 | AK13: =AJ13-0.9 -> 77.097174 | AL13: =AK13-0.9 -> 76.197174 | AM13: =G13 -> 55.860707 | AN13: =AM13-0.3 -> 55.560707 | AO13: =AN13-0.3 -> 55.260707 | AP13: =AO13-0.3 -> 54.960707 | AQ13: =AP13-0.3 -> 54.660707 | AR13: =AQ13-0.3 -> 54.360707 | AS13: =AR13-0.3 -> 54.060707 | AT13: =E13*7/100 -> 5.7538022 | AU13: =AT13+AU12 -> 17.029278 | AV13: 23 | AW13: =(G13*E13/100)*7 -> 321.41146 | AX13: =AX12+(AW13/1000) -> 0.90463494 | AZ13: 23 | BA13: =IF('Egg grading'!C17="",IF('Egg grading'!B17="","",'Egg grading'!B17),'Egg grading'!C17) -> 55.860707 | BC13: =IF(BC12="",'Egg grading'!K17,BC12+'Egg grading'!K17) | BD13: =IF(BD12="",'Egg grading'!L17,BD12+'Egg grading'!L17) | BE13: =IF(BE12="",'Egg grading'!M17,BE12+'Egg grading'!M17) | BF13: =IF(BF12="",'Egg grading'!N17,BF12+'Egg grading'!N17)
A14: ='Production data'!B21 -> 24 | B14: =IF('Production data'!C21="",#N/A,'Production data'!C21) -> #N/A | C14: =IF(OR('Input Laying'!E22=0,'Input Laying'!D21=0),#N/A,'Input Laying'!E22/'Input Laying'!D21*100*25) -> #N/A | D14: =IF(OR('Production data'!D21="",'Production data'!D21=0),0,'Production data'!D21) -> 0 | E14: =IF(OR(Std!B27="",Std!B27=0),0,Std!B27) -> 90.322705 | F14: =IF('Production data'!H21="",#N/A,'Production data'!H21) -> #N/A | G14: =IF(OR(Std!C27="",Std!C27=0),#N/A,Std!C27) -> 57.321534 | H14: =IF(I14<0,#N/A,I14) -> #N/A | I14: =('Input Laying'!AH22-1000)/25 -> -40 | J14: =IF((Std!D27-1000)/25<15,#N/A,(Std!D27-1000)/25) -> 30.777683 | K14: =IF('Production data'!P21="",#N/A,'Production data'!P21) -> #N/A | L14: =IF('Production data'!L21="",#N/A,'Production data'!L21) -> #N/A | M14: =IF(Std!E27=0,#N/A,Std!E27) -> 51.77436 | O14: =IF('Input Laying'!V22=0,NA(),IF('Input Laying'!V22="",NA(),'Input Laying'!W22/'Input Laying'!O22*100)) -> #N/A | P14: =IF('Input Laying'!T22="",#N/A,'Input Laying'!T22/'Input Laying'!N22*100) -> #N/A | Q14: =IF('Input Laying'!U22="",#N/A,'Input Laying'!U22/'Input Laying'!N22*100) -> #N/A | R14: =IF('Input Laying'!V22="",#N/A,'Production data'!W21) | S14: ='Input Laying'!D22*7+'Graph values'!S13 -> 0 | T14: =IF(OR('Input Laying'!AF22="",'Input Laying'!D22=0,'Input Laying'!O22=0),"#N/A",'Input Laying'!AF22/'Input Laying'!D22/(AD14*7)*1000) -> #N/A | U14: =IF('Production data'!U21="",#N/A,'Production data'!U21) -> #N/A | V14: =IF('Production data'!V21="",#N/A,'Production data'!V21) -> #N/A | W14: =IF('Production data'!S21="",#N/A,'Production data'!S21) -> #N/A | X14: =IF('Production data'!T21="",#N/A,'Production data'!T21) -> #N/A | Y14: =IF('Input Laying'!E22="",#N/A,'Production data'!F21) -> #N/A | Z14: =IF('Production data'!G21="",#N/A,'Production data'!G21) -> 23.23262 | AD14: =IF('Input Laying'!AF22=0,0,(IF('Input Laying'!N22>0,1,IF('Input Laying'!O22>0,0,1))))+AD13 -> 0 | AE14: 24 | AF14: =IF(E14<10,#N/A,E14) -> 90.322705 | AG14: =AF14-0.45 -> 89.872705 | AH14: =AG14-0.45 -> 89.422705 | AI14: =AH14-1.5 -> 87.922705 | AJ14: =AI14-0.45 -> 87.472705 | AK14: =AJ14-0.45 -> 87.022705 | AL14: =AK14-0.45 -> 86.572705 | AM14: =G14 -> 57.321534 | AN14: =AM14-0.3 -> 57.021534 | AO14: =AN14-0.3 -> 56.721534 | AP14: =AO14-0.3 -> 56.421534 | AQ14: =AP14-0.3 -> 56.121534 | AR14: =AQ14-0.3 -> 55.821534 | AS14: =AR14-0.3 -> 55.521534 | AT14: =E14*7/100 -> 6.3225894 | AU14: =AT14+AU13 -> 23.351867 | AV14: 24 | AW14: =(G14*E14/100)*7 -> 362.42052 | AX14: =AX13+(AW14/1000) -> 1.2670555 | AZ14: 24 | BA14: =IF('Egg grading'!C18="",IF('Egg grading'!B18="","",'Egg grading'!B18),'Egg grading'!C18) -> 57.321534 | BC14: =IF(BC13="",'Egg grading'!K18,BC13+'Egg grading'!K18) | BD14: =IF(BD13="",'Egg grading'!L18,BD13+'Egg grading'!L18) | BE14: =IF(BE13="",'Egg grading'!M18,BE13+'Egg grading'!M18) | BF14: =IF(BF13="",'Egg grading'!N18,BF13+'Egg grading'!N18)
A15: ='Production data'!B22 -> 25 | B15: =IF('Production data'!C22="",#N/A,'Production data'!C22) -> #N/A | C15: =IF(OR('Input Laying'!E23=0,'Input Laying'!D22=0),#N/A,'Input Laying'!E23/'Input Laying'!D22*100*25) -> #N/A | D15: =IF(OR('Production data'!D22="",'Production data'!D22=0),0,'Production data'!D22) -> 0 | E15: =IF(OR(Std!B28="",Std!B28=0),0,Std!B28) -> 92.969804 | F15: =IF('Production data'!H22="",#N/A,'Production data'!H22) -> #N/A | G15: =IF(OR(Std!C28="",Std!C28=0),#N/A,Std!C28) -> 58.498823 | H15: =IF(I15<0,#N/A,I15) -> #N/A | I15: =('Input Laying'!AH23-1000)/25 -> -40 | J15: =IF((Std!D28-1000)/25<15,#N/A,(Std!D28-1000)/25) -> 31.296531 | K15: =IF('Production data'!P22="",#N/A,'Production data'!P22) -> #N/A | L15: =IF('Production data'!L22="",#N/A,'Production data'!L22) -> #N/A | M15: =IF(Std!E28=0,#N/A,Std!E28) -> 54.386241 | O15: =IF('Input Laying'!V23=0,NA(),IF('Input Laying'!V23="",NA(),'Input Laying'!W23/'Input Laying'!O23*100)) -> #N/A | P15: =IF('Input Laying'!T23="",#N/A,'Input Laying'!T23/'Input Laying'!N23*100) -> #N/A | Q15: =IF('Input Laying'!U23="",#N/A,'Input Laying'!U23/'Input Laying'!N23*100) -> #N/A | R15: =IF('Input Laying'!V23="",#N/A,'Production data'!W22) | S15: ='Input Laying'!D23*7+'Graph values'!S14 -> 0 | T15: =IF(OR('Input Laying'!AF23="",'Input Laying'!D23=0,'Input Laying'!O23=0),"#N/A",'Input Laying'!AF23/'Input Laying'!D23/(AD15*7)*1000) -> #N/A | U15: =IF('Production data'!U22="",#N/A,'Production data'!U22) -> #N/A | V15: =IF('Production data'!V22="",#N/A,'Production data'!V22) -> #N/A | W15: =IF('Production data'!S22="",#N/A,'Production data'!S22) -> #N/A | X15: =IF('Production data'!T22="",#N/A,'Production data'!T22) -> #N/A | Y15: =IF('Input Laying'!E23="",#N/A,'Production data'!F22) -> #N/A | Z15: =IF('Production data'!G22="",#N/A,'Production data'!G22) -> 29.690525 | AD15: =IF('Input Laying'!AF23=0,0,(IF('Input Laying'!N23>0,1,IF('Input Laying'!O23>0,0,1))))+AD14 -> 0 | AE15: 25 | AF15: =IF(E15<10,#N/A,E15) -> 92.969804 | AG15: =AF15-0.45 -> 92.519804 | AH15: =AG15-0.45 -> 92.069804 | AI15: =AH15-1.5 -> 90.569804 | AJ15: =AI15-0.45 -> 90.119804 | AK15: =AJ15-0.45 -> 89.669804 | AL15: =AK15-0.45 -> 89.219804 | AM15: =G15 -> 58.498823 | AN15: =AM15-0.3 -> 58.198823 | AO15: =AN15-0.3 -> 57.898823 | AP15: =AO15-0.3 -> 57.598823 | AQ15: =AP15-0.3 -> 57.298823 | AR15: =AQ15-0.3 -> 56.998823 | AS15: =AR15-0.3 -> 56.698823 | AT15: =E15*7/100 -> 6.5078863 | AU15: =AT15+AU14 -> 29.859753 | AV15: 25 | AW15: =(G15*E15/100)*7 -> 380.70368 | AX15: =AX14+(AW15/1000) -> 1.6477591 | AZ15: 25 | BA15: =IF('Egg grading'!C19="",IF('Egg grading'!B19="","",'Egg grading'!B19),'Egg grading'!C19) -> 58.498823 | BC15: =IF(BC14="",'Egg grading'!K19,BC14+'Egg grading'!K19) | BD15: =IF(BD14="",'Egg grading'!L19,BD14+'Egg grading'!L19) | BE15: =IF(BE14="",'Egg grading'!M19,BE14+'Egg grading'!M19) | BF15: =IF(BF14="",'Egg grading'!N19,BF14+'Egg grading'!N19)
A16: ='Production data'!B23 -> 26 | B16: =IF('Production data'!C23="",#N/A,'Production data'!C23) -> #N/A | C16: =IF(OR('Input Laying'!E24=0,'Input Laying'!D23=0),#N/A,'Input Laying'!E24/'Input Laying'!D23*100*25) -> #N/A | D16: =IF(OR('Production data'!D23="",'Production data'!D23=0),0,'Production data'!D23) -> 0 | E16: =IF(OR(Std!B29="",Std!B29=0),0,Std!B29) -> 94.027254 | F16: =IF('Production data'!H23="",#N/A,'Production data'!H23) -> #N/A | G16: =IF(OR(Std!C29="",Std!C29=0),#N/A,Std!C29) -> 59.436839 | H16: =IF(I16<0,#N/A,I16) -> #N/A | I16: =('Input Laying'!AH24-1000)/25 -> -40 | J16: =IF((Std!D29-1000)/25<15,#N/A,(Std!D29-1000)/25) -> 31.648644 | K16: =IF('Production data'!P23="",#N/A,'Production data'!P23) -> #N/A | L16: =IF('Production data'!L23="",#N/A,'Production data'!L23) -> #N/A | M16: =IF(Std!E29=0,#N/A,Std!E29) -> 55.886828 | O16: =IF('Input Laying'!V24=0,NA(),IF('Input Laying'!V24="",NA(),'Input Laying'!W24/'Input Laying'!O24*100)) -> #N/A | P16: =IF('Input Laying'!T24="",#N/A,'Input Laying'!T24/'Input Laying'!N24*100) -> #N/A | Q16: =IF('Input Laying'!U24="",#N/A,'Input Laying'!U24/'Input Laying'!N24*100) -> #N/A | R16: =IF('Input Laying'!V24="",#N/A,'Production data'!W23) | S16: ='Input Laying'!D24*7+'Graph values'!S15 -> 0 | T16: =IF(OR('Input Laying'!AF24="",'Input Laying'!D24=0,'Input Laying'!O24=0),"#N/A",'Input Laying'!AF24/'Input Laying'!D24/(AD16*7)*1000) -> #N/A | U16: =IF('Production data'!U23="",#N/A,'Production data'!U23) -> #N/A | V16: =IF('Production data'!V23="",#N/A,'Production data'!V23) -> #N/A | W16: =IF('Production data'!S23="",#N/A,'Production data'!S23) -> #N/A | X16: =IF('Production data'!T23="",#N/A,'Production data'!T23) -> #N/A | Y16: =IF('Input Laying'!E24="",#N/A,'Production data'!F23) -> #N/A | Z16: =IF('Production data'!G23="",#N/A,'Production data'!G23) -> 36.215565 | AD16: =IF('Input Laying'!AF24=0,0,(IF('Input Laying'!N24>0,1,IF('Input Laying'!O24>0,0,1))))+AD15 -> 0 | AE16: 26 | AF16: =IF(E16<10,#N/A,E16) -> 94.027254 | AG16: =AF16-0.45 -> 93.577254 | AH16: =AG16-0.45 -> 93.127254 | AI16: =AH16-1.5 -> 91.627254 | AJ16: =AI16-0.45 -> 91.177254 | AK16: =AJ16-0.45 -> 90.727254 | AL16: =AK16-0.45 -> 90.277254 | AM16: =G16 -> 59.436839 | AN16: =AM16-0.3 -> 59.136839 | AO16: =AN16-0.3 -> 58.836839 | AP16: =AO16-0.3 -> 58.536839 | AQ16: =AP16-0.3 -> 58.236839 | AR16: =AQ16-0.3 -> 57.936839 | AS16: =AR16-0.3 -> 57.636839 | AT16: =E16*7/100 -> 6.5819078 | AU16: =AT16+AU15 -> 36.441661 | AV16: 26 | AW16: =(G16*E16/100)*7 -> 391.20779 | AX16: =AX15+(AW16/1000) -> 2.0389669 | AZ16: 26 | BA16: =IF('Egg grading'!C20="",IF('Egg grading'!B20="","",'Egg grading'!B20),'Egg grading'!C20) -> 59.436839 | BC16: =IF(BC15="",'Egg grading'!K20,BC15+'Egg grading'!K20) | BD16: =IF(BD15="",'Egg grading'!L20,BD15+'Egg grading'!L20) | BE16: =IF(BE15="",'Egg grading'!M20,BE15+'Egg grading'!M20) | BF16: =IF(BF15="",'Egg grading'!N20,BF15+'Egg grading'!N20)
A17: ='Production data'!B24 -> 27 | B17: =IF('Production data'!C24="",#N/A,'Production data'!C24) -> #N/A | C17: =IF(OR('Input Laying'!E25=0,'Input Laying'!D24=0),#N/A,'Input Laying'!E25/'Input Laying'!D24*100*25) -> #N/A | D17: =IF(OR('Production data'!D24="",'Production data'!D24=0),0,'Production data'!D24) -> 0 | E17: =IF(OR(Std!B30="",Std!B30=0),0,Std!B30) -> 94.815695 | F17: =IF('Production data'!H24="",#N/A,'Production data'!H24) -> #N/A | G17: =IF(OR(Std!C30="",Std!C30=0),#N/A,Std!C30) -> 60.176109 | H17: =IF(I17<0,#N/A,I17) -> #N/A | I17: =('Input Laying'!AH25-1000)/25 -> -40 | J17: =IF((Std!D30-1000)/25<15,#N/A,(Std!D30-1000)/25) -> 31.900726 | K17: =IF('Production data'!P24="",#N/A,'Production data'!P24) -> #N/A | L17: =IF('Production data'!L24="",#N/A,'Production data'!L24) -> #N/A | M17: =IF(Std!E30=0,#N/A,Std!E30) -> 57.056396 | O17: =IF('Input Laying'!V25=0,NA(),IF('Input Laying'!V25="",NA(),'Input Laying'!W25/'Input Laying'!O25*100)) -> #N/A | P17: =IF('Input Laying'!T25="",#N/A,'Input Laying'!T25/'Input Laying'!N25*100) -> #N/A | Q17: =IF('Input Laying'!U25="",#N/A,'Input Laying'!U25/'Input Laying'!N25*100) -> #N/A | R17: =IF('Input Laying'!V25="",#N/A,'Production data'!W24) | S17: ='Input Laying'!D25*7+'Graph values'!S16 -> 0 | T17: =IF(OR('Input Laying'!AF25="",'Input Laying'!D25=0,'Input Laying'!O25=0),"#N/A",'Input Laying'!AF25/'Input Laying'!D25/(AD17*7)*1000) -> #N/A | U17: =IF('Production data'!U24="",#N/A,'Production data'!U24) -> #N/A | V17: =IF('Production data'!V24="",#N/A,'Production data'!V24) -> #N/A | W17: =IF('Production data'!S24="",#N/A,'Production data'!S24) -> #N/A | X17: =IF('Production data'!T24="",#N/A,'Production data'!T24) -> #N/A | Y17: =IF('Input Laying'!E25="",#N/A,'Production data'!F24) -> #N/A | Z17: =IF('Production data'!G24="",#N/A,'Production data'!G24) -> 42.788948 | AD17: =IF('Input Laying'!AF25=0,0,(IF('Input Laying'!N25>0,1,IF('Input Laying'!O25>0,0,1))))+AD16 -> 0 | AE17: 27 | AF17: =IF(E17<10,#N/A,E17) -> 94.815695 | AG17: =AF17-0.45 -> 94.365695 | AH17: =AG17-0.45 -> 93.915695 | AI17: =AH17-1.5 -> 92.415695 | AJ17: =AI17-0.45 -> 91.965695 | AK17: =AJ17-0.45 -> 91.515695 | AL17: =AK17-0.45 -> 91.065695 | AM17: =G17 -> 60.176109 | AN17: =AM17-0.3 -> 59.876109 | AO17: =AN17-0.3 -> 59.576109 | AP17: =AO17-0.3 -> 59.276109 | AQ17: =AP17-0.3 -> 58.976109 | AR17: =AQ17-0.3 -> 58.676109 | AS17: =AR17-0.3 -> 58.376109 | AT17: =E17*7/100 -> 6.6370987 | AU17: =AT17+AU16 -> 43.07876 | AV17: 27 | AW17: =(G17*E17/100)*7 -> 399.39477 | AX17: =AX16+(AW17/1000) -> 2.4383617 | AZ17: 27 | BA17: =IF('Egg grading'!C21="",IF('Egg grading'!B21="","",'Egg grading'!B21),'Egg grading'!C21) -> 60.176109 | BC17: =IF(BC16="",'Egg grading'!K21,BC16+'Egg grading'!K21) | BD17: =IF(BD16="",'Egg grading'!L21,BD16+'Egg grading'!L21) | BE17: =IF(BE16="",'Egg grading'!M21,BE16+'Egg grading'!M21) | BF17: =IF(BF16="",'Egg grading'!N21,BF16+'Egg grading'!N21)
A18: ='Production data'!B25 -> 28 | B18: =IF('Production data'!C25="",#N/A,'Production data'!C25) -> #N/A | C18: =IF(OR('Input Laying'!E26=0,'Input Laying'!D25=0),#N/A,'Input Laying'!E26/'Input Laying'!D25*100*25) -> #N/A | D18: =IF(OR('Production data'!D25="",'Production data'!D25=0),0,'Production data'!D25) -> 0 | E18: =IF(OR(Std!B31="",Std!B31=0),0,Std!B31) -> 95.375174 | F18: =IF('Production data'!H25="",#N/A,'Production data'!H25) -> #N/A | G18: =IF(OR(Std!C31="",Std!C31=0),#N/A,Std!C31) -> 60.753415 | H18: =IF(I18<0,#N/A,I18) -> #N/A | I18: =('Input Laying'!AH26-1000)/25 -> -40 | J18: =IF((Std!D31-1000)/25<15,#N/A,(Std!D31-1000)/25) -> 32.24 | K18: =IF('Production data'!P25="",#N/A,'Production data'!P25) -> #N/A | L18: =IF('Production data'!L25="",#N/A,'Production data'!L25) -> #N/A | M18: =IF(Std!E31=0,#N/A,Std!E31) -> 57.943675 | O18: =IF('Input Laying'!V26=0,NA(),IF('Input Laying'!V26="",NA(),'Input Laying'!W26/'Input Laying'!O26*100)) -> #N/A | P18: =IF('Input Laying'!T26="",#N/A,'Input Laying'!T26/'Input Laying'!N26*100) -> #N/A | Q18: =IF('Input Laying'!U26="",#N/A,'Input Laying'!U26/'Input Laying'!N26*100) -> #N/A | R18: =IF('Input Laying'!V26="",#N/A,'Production data'!W25) | S18: ='Input Laying'!D26*7+'Graph values'!S17 -> 0 | T18: =IF(OR('Input Laying'!AF26="",'Input Laying'!D26=0,'Input Laying'!O26=0),"#N/A",'Input Laying'!AF26/'Input Laying'!D26/(AD18*7)*1000) -> #N/A | U18: =IF('Production data'!U25="",#N/A,'Production data'!U25) -> #N/A | V18: =IF('Production data'!V25="",#N/A,'Production data'!V25) -> #N/A | W18: =IF('Production data'!S25="",#N/A,'Production data'!S25) -> #N/A | X18: =IF('Production data'!T25="",#N/A,'Production data'!T25) -> #N/A | Y18: =IF('Input Laying'!E26="",#N/A,'Production data'!F25) -> #N/A | Z18: =IF('Production data'!G25="",#N/A,'Production data'!G25) -> 49.394709 | AD18: =IF('Input Laying'!AF26=0,0,(IF('Input Laying'!N26>0,1,IF('Input Laying'!O26>0,0,1))))+AD17 -> 0 | AE18: 28 | AF18: =IF(E18<10,#N/A,E18) -> 95.375174 | AG18: =AF18-0.45 -> 94.925174 | AH18: =AG18-0.45 -> 94.475174 | AI18: =AH18-1.5 -> 92.975174 | AJ18: =AI18-0.45 -> 92.525174 | AK18: =AJ18-0.45 -> 92.075174 | AL18: =AK18-0.45 -> 91.625174 | AM18: =G18 -> 60.753415 | AN18: =AM18-0.3 -> 60.453415 | AO18: =AN18-0.3 -> 60.153415 | AP18: =AO18-0.3 -> 59.853415 | AQ18: =AP18-0.3 -> 59.553415 | AR18: =AQ18-0.3 -> 59.253415 | AS18: =AR18-0.3 -> 58.953415 | AT18: =E18*7/100 -> 6.6762622 | AU18: =AT18+AU17 -> 49.755022 | AV18: 28 | AW18: =(G18*E18/100)*7 -> 405.60573 | AX18: =AX17+(AW18/1000) -> 2.8439674 | AZ18: 28 | BA18: =IF('Egg grading'!C22="",IF('Egg grading'!B22="","",'Egg grading'!B22),'Egg grading'!C22) -> 60.753415 | BC18: =IF(BC17="",'Egg grading'!K22,BC17+'Egg grading'!K22) | BD18: =IF(BD17="",'Egg grading'!L22,BD17+'Egg grading'!L22) | BE18: =IF(BE17="",'Egg grading'!M22,BE17+'Egg grading'!M22) | BF18: =IF(BF17="",'Egg grading'!N22,BF17+'Egg grading'!N22)
A19: ='Production data'!B26 -> 29 | B19: =IF('Production data'!C26="",#N/A,'Production data'!C26) -> #N/A | C19: =IF(OR('Input Laying'!E27=0,'Input Laying'!D26=0),#N/A,'Input Laying'!E27/'Input Laying'!D26*100*25) -> #N/A | D19: =IF(OR('Production data'!D26="",'Production data'!D26=0),0,'Production data'!D26) -> 0 | E19: =IF(OR(Std!B32="",Std!B32=0),0,Std!B32) -> 95.742619 | F19: =IF('Production data'!H26="",#N/A,'Production data'!H26) -> #N/A | G19: =IF(OR(Std!C32="",Std!C32=0),#N/A,Std!C32) -> 61.201798 | H19: =IF(I19<0,#N/A,I19) -> #N/A | I19: =('Input Laying'!AH27-1000)/25 -> -40 | J19: =IF((Std!D32-1000)/25<15,#N/A,(Std!D32-1000)/25) -> 32.48 | K19: =IF('Production data'!P26="",#N/A,'Production data'!P26) -> #N/A | L19: =IF('Production data'!L26="",#N/A,'Production data'!L26) -> #N/A | M19: =IF(Std!E32=0,#N/A,Std!E32) -> 58.596204 | O19: =IF('Input Laying'!V27=0,NA(),IF('Input Laying'!V27="",NA(),'Input Laying'!W27/'Input Laying'!O27*100)) -> #N/A | P19: =IF('Input Laying'!T27="",#N/A,'Input Laying'!T27/'Input Laying'!N27*100) -> #N/A | Q19: =IF('Input Laying'!U27="",#N/A,'Input Laying'!U27/'Input Laying'!N27*100) -> #N/A | R19: =IF('Input Laying'!V27="",#N/A,'Production data'!W26) | S19: ='Input Laying'!D27*7+'Graph values'!S18 -> 0 | T19: =IF(OR('Input Laying'!AF27="",'Input Laying'!D27=0,'Input Laying'!O27=0),"#N/A",'Input Laying'!AF27/'Input Laying'!D27/(AD19*7)*1000) -> #N/A | U19: =IF('Production data'!U26="",#N/A,'Production data'!U26) -> #N/A | V19: =IF('Production data'!V26="",#N/A,'Production data'!V26) -> #N/A | W19: =IF('Production data'!S26="",#N/A,'Production data'!S26) -> #N/A | X19: =IF('Production data'!T26="",#N/A,'Production data'!T26) -> #N/A | Y19: =IF('Input Laying'!E27="",#N/A,'Production data'!F26) -> #N/A | Z19: =IF('Production data'!G26="",#N/A,'Production data'!G26) -> 56.019485 | AD19: =IF('Input Laying'!AF27=0,0,(IF('Input Laying'!N27>0,1,IF('Input Laying'!O27>0,0,1))))+AD18 -> 0 | AE19: 29 | AF19: =IF(E19<10,#N/A,E19) -> 95.742619 | AG19: =AF19-0.45 -> 95.292619 | AH19: =AG19-0.45 -> 94.842619 | AI19: =AH19-1.5 -> 93.342619 | AJ19: =AI19-0.45 -> 92.892619 | AK19: =AJ19-0.45 -> 92.442619 | AL19: =AK19-0.45 -> 91.992619 | AM19: =G19 -> 61.201798 | AN19: =AM19-0.3 -> 60.901798 | AO19: =AN19-0.3 -> 60.601798 | AP19: =AO19-0.3 -> 60.301798 | AQ19: =AP19-0.3 -> 60.001798 | AR19: =AQ19-0.3 -> 59.701798 | AS19: =AR19-0.3 -> 59.401798 | AT19: =E19*7/100 -> 6.7019833 | AU19: =AT19+AU18 -> 56.457005 | AV19: 29 | AW19: =(G19*E19/100)*7 -> 410.17343 | AX19: =AX18+(AW19/1000) -> 3.2541409 | AZ19: 29 | BA19: =IF('Egg grading'!C23="",IF('Egg grading'!B23="","",'Egg grading'!B23),'Egg grading'!C23) -> 61.201798 | BC19: =IF(BC18="",'Egg grading'!K23,BC18+'Egg grading'!K23) | BD19: =IF(BD18="",'Egg grading'!L23,BD18+'Egg grading'!L23) | BE19: =IF(BE18="",'Egg grading'!M23,BE18+'Egg grading'!M23) | BF19: =IF(BF18="",'Egg grading'!N23,BF18+'Egg grading'!N23)
A20: ='Production data'!B27 -> 30 | B20: =IF('Production data'!C27="",#N/A,'Production data'!C27) -> #N/A | C20: =IF(OR('Input Laying'!E28=0,'Input Laying'!D27=0),#N/A,'Input Laying'!E28/'Input Laying'!D27*100*25) -> #N/A | D20: =IF(OR('Production data'!D27="",'Production data'!D27=0),0,'Production data'!D27) -> 0 | E20: =IF(OR(Std!B33="",Std!B33=0),0,Std!B33) -> 95.95184 | F20: =IF('Production data'!H27="",#N/A,'Production data'!H27) -> #N/A | G20: =IF(OR(Std!C33="",Std!C33=0),#N/A,Std!C33) -> 61.550558 | H20: =IF(I20<0,#N/A,I20) -> #N/A | I20: =('Input Laying'!AH28-1000)/25 -> -40 | J20: =IF((Std!D33-1000)/25<15,#N/A,(Std!D33-1000)/25) -> 32.8 | K20: =IF('Production data'!P27="",#N/A,'Production data'!P27) -> #N/A | L20: =IF('Production data'!L27="",#N/A,'Production data'!L27) -> #N/A | M20: =IF(Std!E33=0,#N/A,Std!E33) -> 59.058893 | O20: =IF('Input Laying'!V28=0,NA(),IF('Input Laying'!V28="",NA(),'Input Laying'!W28/'Input Laying'!O28*100)) -> #N/A | P20: =IF('Input Laying'!T28="",#N/A,'Input Laying'!T28/'Input Laying'!N28*100) -> #N/A | Q20: =IF('Input Laying'!U28="",#N/A,'Input Laying'!U28/'Input Laying'!N28*100) -> #N/A | R20: =IF('Input Laying'!V28="",#N/A,'Production data'!W27) | S20: ='Input Laying'!D28*7+'Graph values'!S19 -> 0 | T20: =IF(OR('Input Laying'!AF28="",'Input Laying'!D28=0,'Input Laying'!O28=0),"#N/A",'Input Laying'!AF28/'Input Laying'!D28/(AD20*7)*1000) -> #N/A | U20: =IF('Production data'!U27="",#N/A,'Production data'!U27) -> #N/A | V20: =IF('Production data'!V27="",#N/A,'Production data'!V27) -> #N/A | W20: =IF('Production data'!S27="",#N/A,'Production data'!S27) -> #N/A | X20: =IF('Production data'!T27="",#N/A,'Production data'!T27) -> #N/A | Y20: =IF('Input Laying'!E28="",#N/A,'Production data'!F27) -> #N/A | Z20: =IF('Production data'!G27="",#N/A,'Production data'!G27) -> 62.652291 | AD20: =IF('Input Laying'!AF28=0,0,(IF('Input Laying'!N28>0,1,IF('Input Laying'!O28>0,0,1))))+AD19 -> 0 | AE20: 30 | AF20: =IF(E20<10,#N/A,E20) -> 95.95184 | AG20: =AF20-0.45 -> 95.50184 | AH20: =AG20-0.45 -> 95.05184 | AI20: =AH20-1.5 -> 93.55184 | AJ20: =AI20-0.45 -> 93.10184 | AK20: =AJ20-0.45 -> 92.65184 | AL20: =AK20-0.45 -> 92.20184 | AM20: =G20 -> 61.550558 | AN20: =AM20-0.3 -> 61.250558 | AO20: =AN20-0.3 -> 60.950558 | AP20: =AO20-0.3 -> 60.650558 | AQ20: =AP20-0.3 -> 60.350558 | AR20: =AQ20-0.3 -> 60.050558 | AS20: =AR20-0.3 -> 59.750558 | AT20: =E20*7/100 -> 6.7166288 | AU20: =AT20+AU19 -> 63.173634 | AV20: 30 | AW20: =(G20*E20/100)*7 -> 413.41225 | AX20: =AX19+(AW20/1000) -> 3.6675531 | AZ20: 30 | BA20: =IF('Egg grading'!C24="",IF('Egg grading'!B24="","",'Egg grading'!B24),'Egg grading'!C24) -> 61.550558 | BC20: =IF(BC19="",'Egg grading'!K24,BC19+'Egg grading'!K24) | BD20: =IF(BD19="",'Egg grading'!L24,BD19+'Egg grading'!L24) | BE20: =IF(BE19="",'Egg grading'!M24,BE19+'Egg grading'!M24) | BF20: =IF(BF19="",'Egg grading'!N24,BF19+'Egg grading'!N24)
A21: ='Production data'!B28 -> 31 | B21: =IF('Production data'!C28="",#N/A,'Production data'!C28) -> #N/A | C21: =IF(OR('Input Laying'!E29=0,'Input Laying'!D28=0),#N/A,'Input Laying'!E29/'Input Laying'!D28*100*25) -> #N/A | D21: =IF(OR('Production data'!D28="",'Production data'!D28=0),0,'Production data'!D28) -> 0 | E21: =IF(OR(Std!B34="",Std!B34=0),0,Std!B34) -> 96.033533 | F21: =IF('Production data'!H28="",#N/A,'Production data'!H28) -> #N/A | G21: =IF(OR(Std!C34="",Std!C34=0),#N/A,Std!C34) -> 61.825253 | H21: =IF(I21<0,#N/A,I21) -> #N/A | I21: =('Input Laying'!AH29-1000)/25 -> -40 | J21: =IF((Std!D34-1000)/25<15,#N/A,(Std!D34-1000)/25) -> 33.16 | K21: =IF('Production data'!P28="",#N/A,'Production data'!P28) -> #N/A | L21: =IF('Production data'!L28="",#N/A,'Production data'!L28) -> #N/A | M21: =IF(Std!E34=0,#N/A,Std!E34) -> 59.372974 | O21: =IF('Input Laying'!V29=0,NA(),IF('Input Laying'!V29="",NA(),'Input Laying'!W29/'Input Laying'!O29*100)) -> #N/A | P21: =IF('Input Laying'!T29="",#N/A,'Input Laying'!T29/'Input Laying'!N29*100) -> #N/A | Q21: =IF('Input Laying'!U29="",#N/A,'Input Laying'!U29/'Input Laying'!N29*100) -> #N/A | R21: =IF('Input Laying'!V29="",#N/A,'Production data'!W28) | S21: ='Input Laying'!D29*7+'Graph values'!S20 -> 0 | T21: =IF(OR('Input Laying'!AF29="",'Input Laying'!D29=0,'Input Laying'!O29=0),"#N/A",'Input Laying'!AF29/'Input Laying'!D29/(AD21*7)*1000) -> #N/A | U21: =IF('Production data'!U28="",#N/A,'Production data'!U28) -> #N/A | V21: =IF('Production data'!V28="",#N/A,'Production data'!V28) -> #N/A | W21: =IF('Production data'!S28="",#N/A,'Production data'!S28) -> #N/A | X21: =IF('Production data'!T28="",#N/A,'Production data'!T28) -> #N/A | Y21: =IF('Input Laying'!E29="",#N/A,'Production data'!F28) -> #N/A | Z21: =IF('Production data'!G28="",#N/A,'Production data'!G28) -> 69.28429 | AD21: =IF('Input Laying'!AF29=0,0,(IF('Input Laying'!N29>0,1,IF('Input Laying'!O29>0,0,1))))+AD20 -> 0 | AE21: 31 | AF21: =IF(E21<10,#N/A,E21) -> 96.033533 | AG21: =AF21-0.45 -> 95.583533 | AH21: =AG21-0.45 -> 95.133533 | AI21: =AH21-1.5 -> 93.633533 | AJ21: =AI21-0.45 -> 93.183533 | AK21: =AJ21-0.45 -> 92.733533 | AL21: =AK21-0.45 -> 92.283533 | AM21: =G21 -> 61.825253 | AN21: =AM21-0.3 -> 61.525253 | AO21: =AN21-0.3 -> 61.225253 | AP21: =AO21-0.3 -> 60.925253 | AQ21: =AP21-0.3 -> 60.625253 | AR21: =AQ21-0.3 -> 60.325253 | AS21: =AR21-0.3 -> 60.025253 | AT21: =E21*7/100 -> 6.7223473 | AU21: =AT21+AU20 -> 69.895981 | AV21: 31 | AW21: =(G21*E21/100)*7 -> 415.61082 | AX21: =AX20+(AW21/1000) -> 4.0831639 | AZ21: 31 | BA21: =IF('Egg grading'!C25="",IF('Egg grading'!B25="","",'Egg grading'!B25),'Egg grading'!C25) -> 61.825253 | BC21: =IF(BC20="",'Egg grading'!K25,BC20+'Egg grading'!K25) | BD21: =IF(BD20="",'Egg grading'!L25,BD20+'Egg grading'!L25) | BE21: =IF(BE20="",'Egg grading'!M25,BE20+'Egg grading'!M25) | BF21: =IF(BF20="",'Egg grading'!N25,BF20+'Egg grading'!N25)
A22: ='Production data'!B29 -> 32 | B22: =IF('Production data'!C29="",#N/A,'Production data'!C29) -> #N/A | C22: =IF(OR('Input Laying'!E30=0,'Input Laying'!D29=0),#N/A,'Input Laying'!E30/'Input Laying'!D29*100*25) -> #N/A | D22: =IF(OR('Production data'!D29="",'Production data'!D29=0),0,'Production data'!D29) -> 0 | E22: =IF(OR(Std!B35="",Std!B35=0),0,Std!B35) -> 96.015272 | F22: =IF('Production data'!H29="",#N/A,'Production data'!H29) -> #N/A | G22: =IF(OR(Std!C35="",Std!C35=0),#N/A,Std!C35) -> 62.047698 | H22: =IF(I22<0,#N/A,I22) -> #N/A | I22: =('Input Laying'!AH30-1000)/25 -> -40 | J22: =IF((Std!D35-1000)/25<15,#N/A,(Std!D35-1000)/25) -> 33.52 | K22: =IF('Production data'!P29="",#N/A,'Production data'!P29) -> #N/A | L22: =IF('Production data'!L29="",#N/A,'Production data'!L29) -> #N/A | M22: =IF(Std!E35=0,#N/A,Std!E35) -> 59.575266 | O22: =IF('Input Laying'!V30=0,NA(),IF('Input Laying'!V30="",NA(),'Input Laying'!W30/'Input Laying'!O30*100)) -> #N/A | P22: =IF('Input Laying'!T30="",#N/A,'Input Laying'!T30/'Input Laying'!N30*100) -> #N/A | Q22: =IF('Input Laying'!U30="",#N/A,'Input Laying'!U30/'Input Laying'!N30*100) -> #N/A | R22: =IF('Input Laying'!V30="",#N/A,'Production data'!W29) | S22: ='Input Laying'!D30*7+'Graph values'!S21 -> 0 | T22: =IF(OR('Input Laying'!AF30="",'Input Laying'!D30=0,'Input Laying'!O30=0),"#N/A",'Input Laying'!AF30/'Input Laying'!D30/(AD22*7)*1000) -> #N/A | U22: =IF('Production data'!U29="",#N/A,'Production data'!U29) -> #N/A | V22: =IF('Production data'!V29="",#N/A,'Production data'!V29) -> #N/A | W22: =IF('Production data'!S29="",#N/A,'Production data'!S29) -> #N/A | X22: =IF('Production data'!T29="",#N/A,'Production data'!T29) -> #N/A | Y22: =IF('Input Laying'!E30="",#N/A,'Production data'!F29) -> #N/A | Z22: =IF('Production data'!G29="",#N/A,'Production data'!G29) -> 75.908575 | AD22: =IF('Input Laying'!AF30=0,0,(IF('Input Laying'!N30>0,1,IF('Input Laying'!O30>0,0,1))))+AD21 -> 0 | AE22: 32 | AF22: =IF(E22<10,#N/A,E22) -> 96.015272 | AG22: =AF22-0.45 -> 95.565272 | AH22: =AG22-0.45 -> 95.115272 | AI22: =AH22-1.5 -> 93.615272 | AJ22: =AI22-0.45 -> 93.165272 | AK22: =AJ22-0.45 -> 92.715272 | AL22: =AK22-0.45 -> 92.265272 | AM22: =G22 -> 62.047698 | AN22: =AM22-0.3 -> 61.747698 | AO22: =AN22-0.3 -> 61.447698 | AP22: =AO22-0.3 -> 61.147698 | AQ22: =AP22-0.3 -> 60.847698 | AR22: =AQ22-0.3 -> 60.547698 | AS22: =AR22-0.3 -> 60.247698 | AT22: =E22*7/100 -> 6.7210691 | AU22: =AT22+AU21 -> 76.61705 | AV22: 32 | AW22: =(G22*E22/100)*7 -> 417.02686 | AX22: =AX21+(AW22/1000) -> 4.5001908 | AZ22: 32 | BA22: =IF('Egg grading'!C26="",IF('Egg grading'!B26="","",'Egg grading'!B26),'Egg grading'!C26) -> 62.047698 | BC22: =IF(BC21="",'Egg grading'!K26,BC21+'Egg grading'!K26) | BD22: =IF(BD21="",'Egg grading'!L26,BD21+'Egg grading'!L26) | BE22: =IF(BE21="",'Egg grading'!M26,BE21+'Egg grading'!M26) | BF22: =IF(BF21="",'Egg grading'!N26,BF21+'Egg grading'!N26)
A23: ='Production data'!B30 -> 33 | B23: =IF('Production data'!C30="",#N/A,'Production data'!C30) -> #N/A | C23: =IF(OR('Input Laying'!E31=0,'Input Laying'!D30=0),#N/A,'Input Laying'!E31/'Input Laying'!D30*100*25) -> #N/A | D23: =IF(OR('Production data'!D30="",'Production data'!D30=0),0,'Production data'!D30) -> 0 | E23: =IF(OR(Std!B36="",Std!B36=0),0,Std!B36) -> 95.921519 | F23: =IF('Production data'!H30="",#N/A,'Production data'!H30) -> #N/A | G23: =IF(OR(Std!C36="",Std!C36=0),#N/A,Std!C36) -> 62.235968 | H23: =IF(I23<0,#N/A,I23) -> #N/A | I23: =('Input Laying'!AH31-1000)/25 -> -40 | J23: =IF((Std!D36-1000)/25<15,#N/A,(Std!D36-1000)/25) -> 33.88 | K23: =IF('Production data'!P30="",#N/A,'Production data'!P30) -> #N/A | L23: =IF('Production data'!L30="",#N/A,'Production data'!L30) -> #N/A | M23: =IF(Std!E36=0,#N/A,Std!E36) -> 59.697686 | O23: =IF('Input Laying'!V31=0,NA(),IF('Input Laying'!V31="",NA(),'Input Laying'!W31/'Input Laying'!O31*100)) -> #N/A | P23: =IF('Input Laying'!T31="",#N/A,'Input Laying'!T31/'Input Laying'!N31*100) -> #N/A | Q23: =IF('Input Laying'!U31="",#N/A,'Input Laying'!U31/'Input Laying'!N31*100) -> #N/A | R23: =IF('Input Laying'!V31="",#N/A,'Production data'!W30) | S23: ='Input Laying'!D31*7+'Graph values'!S22 -> 0 | T23: =IF(OR('Input Laying'!AF31="",'Input Laying'!D31=0,'Input Laying'!O31=0),"#N/A",'Input Laying'!AF31/'Input Laying'!D31/(AD23*7)*1000) -> #N/A | U23: =IF('Production data'!U30="",#N/A,'Production data'!U30) -> #N/A | V23: =IF('Production data'!V30="",#N/A,'Production data'!V30) -> #N/A | W23: =IF('Production data'!S30="",#N/A,'Production data'!S30) -> #N/A | X23: =IF('Production data'!T30="",#N/A,'Production data'!T30) -> #N/A | Y23: =IF('Input Laying'!E31="",#N/A,'Production data'!F30) -> #N/A | Z23: =IF('Production data'!G30="",#N/A,'Production data'!G30) -> 82.519947 | AD23: =IF('Input Laying'!AF31=0,0,(IF('Input Laying'!N31>0,1,IF('Input Laying'!O31>0,0,1))))+AD22 -> 0 | AE23: 33 | AF23: =IF(E23<10,#N/A,E23) -> 95.921519 | AG23: =AF23-0.45 -> 95.471519 | AH23: =AG23-0.45 -> 95.021519 | AI23: =AH23-1.5 -> 93.521519 | AJ23: =AI23-0.45 -> 93.071519 | AK23: =AJ23-0.45 -> 92.621519 | AL23: =AK23-0.45 -> 92.171519 | AM23: =G23 -> 62.235968 | AN23: =AM23-0.3 -> 61.935968 | AO23: =AN23-0.3 -> 61.635968 | AP23: =AO23-0.3 -> 61.335968 | AQ23: =AP23-0.3 -> 61.035968 | AR23: =AQ23-0.3 -> 60.735968 | AS23: =AR23-0.3 -> 60.435968 | AT23: =E23*7/100 -> 6.7145063 | AU23: =AT23+AU22 -> 83.331557 | AV23: 33 | AW23: =(G23*E23/100)*7 -> 417.8838 | AX23: =AX22+(AW23/1000) -> 4.9180746 | AZ23: 33 | BA23: =IF('Egg grading'!C27="",IF('Egg grading'!B27="","",'Egg grading'!B27),'Egg grading'!C27) -> 62.235968 | BC23: =IF(BC22="",'Egg grading'!K27,BC22+'Egg grading'!K27) | BD23: =IF(BD22="",'Egg grading'!L27,BD22+'Egg grading'!L27) | BE23: =IF(BE22="",'Egg grading'!M27,BE22+'Egg grading'!M27) | BF23: =IF(BF22="",'Egg grading'!N27,BF22+'Egg grading'!N27)
A24: ='Production data'!B31 -> 34 | B24: =IF('Production data'!C31="",#N/A,'Production data'!C31) -> #N/A | C24: =IF(OR('Input Laying'!E32=0,'Input Laying'!D31=0),#N/A,'Input Laying'!E32/'Input Laying'!D31*100*25) -> #N/A | D24: =IF(OR('Production data'!D31="",'Production data'!D31=0),0,'Production data'!D31) -> 0 | E24: =IF(OR(Std!B37="",Std!B37=0),0,Std!B37) -> 95.773613 | F24: =IF('Production data'!H31="",#N/A,'Production data'!H31) -> #N/A | G24: =IF(OR(Std!C37="",Std!C37=0),#N/A,Std!C37) -> 62.404396 | H24: =IF(I24<0,#N/A,I24) -> #N/A | I24: =('Input Laying'!AH32-1000)/25 -> -40 | J24: =IF((Std!D37-1000)/25<15,#N/A,(Std!D37-1000)/25) -> 34.16 | K24: =IF('Production data'!P31="",#N/A,'Production data'!P31) -> #N/A | L24: =IF('Production data'!L31="",#N/A,'Production data'!L31) -> #N/A | M24: =IF(Std!E37=0,#N/A,Std!E37) -> 59.766945 | O24: =IF('Input Laying'!V32=0,NA(),IF('Input Laying'!V32="",NA(),'Input Laying'!W32/'Input Laying'!O32*100)) -> #N/A | P24: =IF('Input Laying'!T32="",#N/A,'Input Laying'!T32/'Input Laying'!N32*100) -> #N/A | Q24: =IF('Input Laying'!U32="",#N/A,'Input Laying'!U32/'Input Laying'!N32*100) -> #N/A | R24: =IF('Input Laying'!V32="",#N/A,'Production data'!W31) | S24: ='Input Laying'!D32*7+'Graph values'!S23 -> 0 | T24: =IF(OR('Input Laying'!AF32="",'Input Laying'!D32=0,'Input Laying'!O32=0),"#N/A",'Input Laying'!AF32/'Input Laying'!D32/(AD24*7)*1000) -> #N/A | U24: =IF('Production data'!U31="",#N/A,'Production data'!U31) -> #N/A | V24: =IF('Production data'!V31="",#N/A,'Production data'!V31) -> #N/A | W24: =IF('Production data'!S31="",#N/A,'Production data'!S31) -> #N/A | X24: =IF('Production data'!T31="",#N/A,'Production data'!T31) -> #N/A | Y24: =IF('Input Laying'!E32="",#N/A,'Production data'!F31) -> #N/A | Z24: =IF('Production data'!G31="",#N/A,'Production data'!G31) -> 89.114688 | AD24: =IF('Input Laying'!AF32=0,0,(IF('Input Laying'!N32>0,1,IF('Input Laying'!O32>0,0,1))))+AD23 -> 0 | AE24: 34 | AF24: =IF(E24<10,#N/A,E24) -> 95.773613 | AG24: =AF24-0.45 -> 95.323613 | AH24: =AG24-0.45 -> 94.873613 | AI24: =AH24-1.5 -> 93.373613 | AJ24: =AI24-0.45 -> 92.923613 | AK24: =AJ24-0.45 -> 92.473613 | AL24: =AK24-0.45 -> 92.023613 | AM24: =G24 -> 62.404396 | AN24: =AM24-0.3 -> 62.104396 | AO24: =AN24-0.3 -> 61.804396 | AP24: =AO24-0.3 -> 61.504396 | AQ24: =AP24-0.3 -> 61.204396 | AR24: =AQ24-0.3 -> 60.904396 | AS24: =AR24-0.3 -> 60.604396 | AT24: =E24*7/100 -> 6.7041529 | AU24: =AT24+AU23 -> 90.03571 | AV24: 34 | AW24: =(G24*E24/100)*7 -> 418.36861 | AX24: =AX23+(AW24/1000) -> 5.3364432 | AZ24: 34 | BA24: =IF('Egg grading'!C28="",IF('Egg grading'!B28="","",'Egg grading'!B28),'Egg grading'!C28) -> 62.404396 | BC24: =IF(BC23="",'Egg grading'!K28,BC23+'Egg grading'!K28) | BD24: =IF(BD23="",'Egg grading'!L28,BD23+'Egg grading'!L28) | BE24: =IF(BE23="",'Egg grading'!M28,BE23+'Egg grading'!M28) | BF24: =IF(BF23="",'Egg grading'!N28,BF23+'Egg grading'!N28)
A25: ='Production data'!B32 -> 35 | B25: =IF('Production data'!C32="",#N/A,'Production data'!C32) -> #N/A | C25: =IF(OR('Input Laying'!E33=0,'Input Laying'!D32=0),#N/A,'Input Laying'!E33/'Input Laying'!D32*100*25) -> #N/A | D25: =IF(OR('Production data'!D32="",'Production data'!D32=0),0,'Production data'!D32) -> 0 | E25: =IF(OR(Std!B38="",Std!B38=0),0,Std!B38) -> 95.63 | F25: =IF('Production data'!H32="",#N/A,'Production data'!H32) -> #N/A | G25: =IF(OR(Std!C38="",Std!C38=0),#N/A,Std!C38) -> 62.563571 | H25: =IF(I25<0,#N/A,I25) -> #N/A | I25: =('Input Laying'!AH33-1000)/25 -> -40 | J25: =IF((Std!D38-1000)/25<15,#N/A,(Std!D38-1000)/25) -> 34.44 | K25: =IF('Production data'!P32="",#N/A,'Production data'!P32) -> #N/A | L25: =IF('Production data'!L32="",#N/A,'Production data'!L32) -> #N/A | M25: =IF(Std!E38=0,#N/A,Std!E38) -> 59.829543 | O25: =IF('Input Laying'!V33=0,NA(),IF('Input Laying'!V33="",NA(),'Input Laying'!W33/'Input Laying'!O33*100)) -> #N/A | P25: =IF('Input Laying'!T33="",#N/A,'Input Laying'!T33/'Input Laying'!N33*100) -> #N/A | Q25: =IF('Input Laying'!U33="",#N/A,'Input Laying'!U33/'Input Laying'!N33*100) -> #N/A | R25: =IF('Input Laying'!V33="",#N/A,'Production data'!W32) | S25: ='Input Laying'!D33*7+'Graph values'!S24 -> 0 | T25: =IF(OR('Input Laying'!AF33="",'Input Laying'!D33=0,'Input Laying'!O33=0),"#N/A",'Input Laying'!AF33/'Input Laying'!D33/(AD25*7)*1000) -> #N/A | U25: =IF('Production data'!U32="",#N/A,'Production data'!U32) -> #N/A | V25: =IF('Production data'!V32="",#N/A,'Production data'!V32) -> #N/A | W25: =IF('Production data'!S32="",#N/A,'Production data'!S32) -> #N/A | X25: =IF('Production data'!T32="",#N/A,'Production data'!T32) -> #N/A | Y25: =IF('Input Laying'!E33="",#N/A,'Production data'!F32) -> #N/A | Z25: =IF('Production data'!G32="",#N/A,'Production data'!G32) -> 95.693114 | AD25: =IF('Input Laying'!AF33=0,0,(IF('Input Laying'!N33>0,1,IF('Input Laying'!O33>0,0,1))))+AD24 -> 0 | AE25: 35 | AF25: =IF(E25<10,#N/A,E25) -> 95.63 | AG25: =AF25-0.45 -> 95.18 | AH25: =AG25-0.45 -> 94.73 | AI25: =AH25-1.5 -> 93.23 | AJ25: =AI25-0.45 -> 92.78 | AK25: =AJ25-0.45 -> 92.33 | AL25: =AK25-0.45 -> 91.88 | AM25: =G25 -> 62.563571 | AN25: =AM25-0.3 -> 62.263571 | AO25: =AN25-0.3 -> 61.963571 | AP25: =AO25-0.3 -> 61.663571 | AQ25: =AP25-0.3 -> 61.363571 | AR25: =AQ25-0.3 -> 61.063571 | AS25: =AR25-0.3 -> 60.763571 | AT25: =E25*7/100 -> 6.6941 | AU25: =AT25+AU24 -> 96.72981 | AV25: 35 | AW25: =(G25*E25/100)*7 -> 418.8068 | AX25: =AX24+(AW25/1000) -> 5.75525 | AZ25: 35 | BA25: =IF('Egg grading'!C29="",IF('Egg grading'!B29="","",'Egg grading'!B29),'Egg grading'!C29) -> 62.563571 | BC25: =IF(BC24="",'Egg grading'!K29,BC24+'Egg grading'!K29) | BD25: =IF(BD24="",'Egg grading'!L29,BD24+'Egg grading'!L29) | BE25: =IF(BE24="",'Egg grading'!M29,BE24+'Egg grading'!M29) | BF25: =IF(BF24="",'Egg grading'!N29,BF24+'Egg grading'!N29)
... A90: ='Production data'!B97 -> 100 | B90: =IF('Production data'!C97="",#N/A,'Production data'!C97) -> #N/A | C90: =IF(OR('Input Laying'!E98=0,'Input Laying'!D97=0),#N/A,'Input Laying'!E98/'Input Laying'!D97*100*25) -> #N/A | D90: =IF(OR('Production data'!D97="",'Production data'!D97=0),0,'Production data'!D97) -> 0 | E90: =IF(OR(Std!B103="",Std!B103=0),0,Std!B103) -> 69.758246 | F90: =IF('Production data'!H97="",#N/A,'Production data'!H97) -> #N/A | G90: =IF(OR(Std!C103="",Std!C103=0),#N/A,Std!C103) -> 65.044032 | H90: =IF(I90<0,#N/A,I90) -> #N/A | I90: =('Input Laying'!AH98-1000)/25 -> -40 | J90: =IF((Std!D103-1000)/25<15,#N/A,(Std!D103-1000)/25) -> 39.010531 | K90: =IF('Production data'!P97="",#N/A,'Production data'!P97) -> #N/A | L90: =IF('Production data'!L97="",#N/A,'Production data'!L97) -> #N/A | M90: =IF(Std!E103=0,#N/A,Std!E103) -> 45.373576 | O90: =IF('Input Laying'!V98=0,NA(),IF('Input Laying'!V98="",NA(),'Input Laying'!W98/'Input Laying'!O98*100)) -> #N/A | P90: =IF('Input Laying'!T98="",#N/A,'Input Laying'!T98/'Input Laying'!N98*100) -> #N/A | Q90: =IF('Input Laying'!U98="",#N/A,'Input Laying'!U98/'Input Laying'!N98*100) -> #N/A | R90: =IF('Input Laying'!V98="",#N/A,'Production data'!W97) | S90: ='Input Laying'!D98*7+'Graph values'!S89 -> 0 | T90: =IF(OR('Input Laying'!AF98="",'Input Laying'!D98=0,'Input Laying'!O98=0),"#N/A",'Input Laying'!AF98/'Input Laying'!D98/(AD90*7)*1000) -> #N/A | U90: =IF('Production data'!U97="",#N/A,'Production data'!U97) -> #N/A | V90: =IF('Production data'!V97="",#N/A,'Production data'!V97) -> #N/A | W90: =IF('Production data'!S97="",#N/A,'Production data'!S97) -> #N/A | X90: =IF('Production data'!T97="",#N/A,'Production data'!T97) -> #N/A | Y90: =IF('Input Laying'!E98="",#N/A,'Production data'!F97) -> #N/A | Z90: =IF('Production data'!G97="",#N/A,'Production data'!G97) -> 460.13022 | AD90: =IF('Input Laying'!AF98=0,0,(IF('Input Laying'!N98>0,1,IF('Input Laying'!O98>0,0,1))))+AD89 -> 0 | AE90: 100 | AF90: =IF(E90<10,#N/A,E90) -> 69.758246 | AG90: =AF90-0.45 -> 69.308246 | AH90: =AG90-0.45 -> 68.858246 | AI90: =AH90-1.5 -> 67.358246 | AJ90: =AI90-0.45 -> 66.908246 | AK90: =AJ90-0.45 -> 66.458246 | AL90: =AK90-0.45 -> 66.008246 | AM90: =G90 -> 65.044032 | AN90: =AM90-0.3 -> 64.744032 | AO90: =AN90-0.3 -> 64.444032 | AP90: =AO90-0.3 -> 64.144032 | AQ90: =AP90-0.3 -> 63.844032 | AR90: =AQ90-0.3 -> 63.544032 | AS90: =AR90-0.3 -> 63.244032 | AT90: =E90*7/100 -> 4.8830772 | AU90: =AT90+AU89 -> 479.24694 | AV90: 100 | AW90: =(G90*E90/100)*7 -> 317.61503 | AX90: =AX89+(AW90/1000) -> 30.244218 | AZ90: 100 | BA90: =IF('Egg grading'!C94="",IF('Egg grading'!B94="","",'Egg grading'!B94),'Egg grading'!C94) -> 65.044032 | BC90: =IF(BC89="",'Egg grading'!K94,BC89+'Egg grading'!K94) | BD90: =IF(BD89="",'Egg grading'!L94,BD89+'Egg grading'!L94) | BE90: =IF(BE89="",'Egg grading'!M94,BE89+'Egg grading'!M94) | BF90: =IF(BF89="",'Egg grading'!N94,BF89+'Egg grading'!N94)
A94: REARING
B95: =Language!B283 -> Mortality % | D95: =Language!B284 -> Body weight | E95: =Language!B285 -> Uniformity | F95: =Language!B286 -> Unif % | G95: =Language!B287 -> feed/water ratio | H95: =Language!B288 -> cum cons per bird | J95: =Language!B289 -> std min | N95: light | O95: offset | Q95: transfer | R95: cum transfert | S95: cal inter | T95: cal inter1 | U95: Coef | V95: coef à appliquer | X95: Nb mort corrigé | Y95: Nb mort corrigé Cumulé | Z95: Aliment corrigé | AA95: Aliment corrigé Cumulé | AB95: Eau corrigée | AC95: Eau corrigée cumulée
A96: 1 | B96: =OFFSET('Input Rearing'!J12,M96,0)*100000 -> 0 | C96: =B96/100000 -> 0 | D96: =IF(OFFSET('Input Rearing'!M12,M96,0)="",#N/A,OFFSET('Input Rearing'!M12,M96,0)) -> #N/A | E96: =IF(OFFSET('Input Rearing'!Q12,O96,0)="",#N/A,OFFSET('Input Rearing'!Q12,O96,0)*100) -> #N/A | F96: =E96/10000 -> #N/A | G96: =IF(OFFSET('Input Rearing'!U12,O96,0)="",#N/A,OFFSET('Input Rearing'!U12,O96,0)*500) -> #DIV/0! | H96: =OFFSET('Input Rearing'!AA12,M96,0) -> 0 | J96: =OFFSET('Input Rearing'!N18,M96,0) -> 63.8625 | K96: =Std!I4 -> 67.1375 | L96: =H96/D96 -> #N/A | M96: 0 | N96: =OFFSET('Input Rearing'!AA18,M96,0) -> 0 | O96: 0 | P96: 1 | Q96: =OFFSET('Input Rearing'!I12,'Graph values'!O96,0) -> 0 | R96: =Q96 -> 0 | S96: =IF(Q96=0,0,Q96) -> 0 | T96: =IF(S96=0,TRUE,FALSE) -> TRUE | U96: =IF(T96=TRUE,0,1-($Q$115/$Q$116)) -> 0 | V96: =IF(T96=FALSE,U96,IF(T97=FALSE,U97,IF(T98=FALSE,U98,IF(T99=FALSE,U99,IF(T100=FALSE,U100,IF(T101=FALSE,U101,IF(T102=FALSE,U102,IF(T103=FALSE,U103,V115)))))))) -> 1 | X96: =OFFSET('Input Rearing'!F12,O96,)*'Graph values'!V96 -> 0 | Y96: =X96 -> 0 | Z96: =OFFSET('Input Rearing'!X12,O96,0)*'Graph values'!V96 -> 0 | AA96: =Z96 -> 0 | AB96: =OFFSET('Input Rearing'!X12,O96,0)*'Graph values'!V96 -> 0 | AC96: =AB96 -> 0
A97: 2 | B97: =OFFSET('Input Rearing'!J13,M97,0)*100000 -> 0 | C97: =B97/100000 -> 0 | D97: =IF(OFFSET('Input Rearing'!M13,M97,0)="",#N/A,OFFSET('Input Rearing'!M13,M97,0)) -> #N/A | E97: =IF(OFFSET('Input Rearing'!Q13,O97,0)="",#N/A,OFFSET('Input Rearing'!Q13,O97,0)*100) -> #N/A | F97: =E97/10000 -> #N/A | G97: =IF(OFFSET('Input Rearing'!U13,O97,0)="",#N/A,OFFSET('Input Rearing'!U13,O97,0)*500) -> #DIV/0! | H97: =OFFSET('Input Rearing'!AA13,M97,0) -> 0 | J97: =OFFSET('Input Rearing'!N19,M97,0) -> 114.5625 | K97: =Std!I5 -> 120.4375 | L97: =H97/D97 -> #N/A | M97: =M96+6 -> 6 | O97: =O96+6 -> 6 | P97: 2 | Q97: =OFFSET('Input Rearing'!I13,'Graph values'!O97,0) -> 0 | R97: =R96+Q97 -> 0 | S97: =IF(Q97=0,S96,Q97) -> 0 | T97: =IF(S97=S96,TRUE,FALSE) -> TRUE | U97: =IF(T97=TRUE,U96,1-($Q$115/$Q$116)) -> 0 | V97: =IF(T97=FALSE,U97,IF(T98=FALSE,U98,IF(T99=FALSE,U99,IF(T100=FALSE,U100,IF(T101=FALSE,U101,IF(T102=FALSE,U102,IF(T103=FALSE,U103,IF(T104=FALSE,U104,V116)))))))) -> 1 | X97: =OFFSET('Input Rearing'!F13,O97,)*'Graph values'!V97 -> 0 | Y97: =X97+Y96 -> 0 | Z97: =OFFSET('Input Rearing'!X13,O97,0)*'Graph values'!V97 -> 0 | AA97: =Z97+AA96 -> 0 | AB97: =OFFSET('Input Rearing'!X13,O97,0)*'Graph values'!V97 -> 0 | AC97: =AB97+AC96 -> 0
A98: 3 | B98: =OFFSET('Input Rearing'!J14,M98,0)*100000 -> 0 | C98: =B98/100000 -> 0 | D98: =IF(OFFSET('Input Rearing'!M14,M98,0)="",#N/A,OFFSET('Input Rearing'!M14,M98,0)) -> #N/A | E98: =IF(OFFSET('Input Rearing'!Q14,O98,0)="",#N/A,OFFSET('Input Rearing'!Q14,O98,0)*100) -> #N/A | F98: =E98/10000 -> #N/A | G98: =IF(OFFSET('Input Rearing'!U14,O98,0)="",#N/A,OFFSET('Input Rearing'!U14,O98,0)*500) -> #DIV/0! | H98: =OFFSET('Input Rearing'!AA14,M98,0) -> 0 | J98: =OFFSET('Input Rearing'!N20,M98,0) -> 186.7125 | K98: =Std!I6 -> 196.2875 | L98: =H98/D98 -> #N/A | M98: =M97+6 -> 12 | O98: =O97+6 -> 12 | P98: 3 | Q98: =OFFSET('Input Rearing'!I14,'Graph values'!O98,0) -> 0 | R98: =R97+Q98 -> 0 | S98: =IF(Q98=0,S97,Q98) -> 0 | T98: =IF(S98=S97,TRUE,FALSE) -> TRUE | U98: =IF(T98=TRUE,U97,1-($Q$115/$Q$116)) -> 0 | V98: =IF(T98=FALSE,U98,IF(T99=FALSE,U99,IF(T100=FALSE,U100,IF(T101=FALSE,U101,IF(T102=FALSE,U102,IF(T103=FALSE,U103,IF(T104=FALSE,U104,IF(T105=FALSE,U105,V117)))))))) -> 1 | X98: =OFFSET('Input Rearing'!F14,O98,)*'Graph values'!V98 -> 0 | Y98: =X98+Y97 -> 0 | Z98: =OFFSET('Input Rearing'!X14,O98,0)*'Graph values'!V98 -> 0 | AA98: =Z98+AA97 -> 0 | AB98: =OFFSET('Input Rearing'!X14,O98,0)*'Graph values'!V98 -> 0 | AC98: =AB98+AC97 -> 0
A99: 4 | B99: =OFFSET('Input Rearing'!J15,M99,0)*100000 -> 0 | C99: =B99/100000 -> 0 | D99: =IF(OFFSET('Input Rearing'!M15,M99,0)="",#N/A,OFFSET('Input Rearing'!M15,M99,0)) -> #N/A | E99: =IF(OFFSET('Input Rearing'!Q15,O99,0)="",#N/A,OFFSET('Input Rearing'!Q15,O99,0)*100) -> #N/A | F99: =E99/10000 -> #N/A | G99: =IF(OFFSET('Input Rearing'!U15,O99,0)="",#N/A,OFFSET('Input Rearing'!U15,O99,0)*500) -> #DIV/0! | H99: =OFFSET('Input Rearing'!AA15,M99,0) -> 0 | J99: =OFFSET('Input Rearing'!N21,M99,0) -> 268.6125 | K99: =Std!I7 -> 282.3875 | L99: =H99/D99 -> #N/A | M99: =M98+6 -> 18 | O99: =O98+6 -> 18 | P99: 4 | Q99: =OFFSET('Input Rearing'!I15,'Graph values'!O99,0) -> 0 | R99: =R98+Q99 -> 0 | S99: =IF(Q99=0,S98,Q99) -> 0 | T99: =IF(S99=S98,TRUE,FALSE) -> TRUE | U99: =IF(T99=TRUE,U98,1-($Q$115/$Q$116)) -> 0 | V99: =IF(T99=FALSE,U99,IF(T100=FALSE,U100,IF(T101=FALSE,U101,IF(T102=FALSE,U102,IF(T103=FALSE,U103,IF(T104=FALSE,U104,IF(T105=FALSE,U105,IF(T106=FALSE,U106,V118)))))))) -> 1 | X99: =OFFSET('Input Rearing'!F15,O99,)*'Graph values'!V99 -> 0 | Y99: =X99+Y98 -> 0 | Z99: =OFFSET('Input Rearing'!X15,O99,0)*'Graph values'!V99 -> 0 | AA99: =Z99+AA98 -> 0 | AB99: =OFFSET('Input Rearing'!X15,O99,0)*'Graph values'!V99 -> 0 | AC99: =AB99+AC98 -> 0
A100: 5 | B100: =OFFSET('Input Rearing'!J16,M100,0)*100000 -> 0 | C100: =B100/100000 -> 0 | D100: =IF(OFFSET('Input Rearing'!M16,M100,0)="",#N/A,OFFSET('Input Rearing'!M16,M100,0)) -> #N/A | E100: =IF(OFFSET('Input Rearing'!Q16,O100,0)="",#N/A,OFFSET('Input Rearing'!Q16,O100,0)*100) -> #N/A | F100: =E100/10000 -> #N/A | G100: =IF(OFFSET('Input Rearing'!U16,O100,0)="",#N/A,OFFSET('Input Rearing'!U16,O100,0)*500) -> #DIV/0! | H100: =OFFSET('Input Rearing'!AA16,M100,0) -> 0 | J100: =OFFSET('Input Rearing'!N22,M100,0) -> 360.75 | K100: =Std!I8 -> 379.25 | L100: =H100/D100 -> #N/A | M100: =M99+6 -> 24 | O100: =O99+6 -> 24 | P100: 5 | Q100: =OFFSET('Input Rearing'!I16,'Graph values'!O100,0) -> 0 | R100: =R99+Q100 -> 0 | S100: =IF(Q100=0,S99,Q100) -> 0 | T100: =IF(S100=S99,TRUE,FALSE) -> TRUE | U100: =IF(T100=TRUE,U99,1-($Q$115/$Q$116)) -> 0 | V100: =IF(T100=FALSE,U100,IF(T101=FALSE,U101,IF(T102=FALSE,U102,IF(T103=FALSE,U103,IF(T104=FALSE,U104,IF(T105=FALSE,U105,IF(T106=FALSE,U106,IF(T107=FALSE,U107,V119)))))))) -> 1 | X100: =OFFSET('Input Rearing'!F16,O100,)*'Graph values'!V100 -> 0 | Y100: =X100+Y99 -> 0 | Z100: =OFFSET('Input Rearing'!X16,O100,0)*'Graph values'!V100 -> 0 | AA100: =Z100+AA99 -> 0 | AB100: =OFFSET('Input Rearing'!X16,O100,0)*'Graph values'!V100 -> 0 | AC100: =AB100+AC99 -> 0
A101: 6 | B101: =OFFSET('Input Rearing'!J17,M101,0)*100000 -> 0 | C101: =B101/100000 -> 0 | D101: =IF(OFFSET('Input Rearing'!M17,M101,0)="",#N/A,OFFSET('Input Rearing'!M17,M101,0)) -> #N/A | E101: =IF(OFFSET('Input Rearing'!Q17,O101,0)="",#N/A,OFFSET('Input Rearing'!Q17,O101,0)*100) -> #N/A | F101: =E101/10000 -> #N/A | G101: =IF(OFFSET('Input Rearing'!U17,O101,0)="",#N/A,OFFSET('Input Rearing'!U17,O101,0)*500) -> #DIV/0! | H101: =OFFSET('Input Rearing'!AA17,M101,0) -> 0 | J101: =OFFSET('Input Rearing'!N23,M101,0) -> 459.225 | K101: =Std!I9 -> 482.775 | L101: =H101/D101 -> #N/A | M101: =M100+6 -> 30 | O101: =O100+6 -> 30 | P101: 6 | Q101: =OFFSET('Input Rearing'!I17,'Graph values'!O101,0) -> 0 | R101: =R100+Q101 -> 0 | S101: =IF(Q101=0,S100,Q101) -> 0 | T101: =IF(S101=S100,TRUE,FALSE) -> TRUE | U101: =IF(T101=TRUE,U100,1-($Q$115/$Q$116)) -> 0 | V101: =IF(T101=FALSE,U101,IF(T102=FALSE,U102,IF(T103=FALSE,U103,IF(T104=FALSE,U104,IF(T105=FALSE,U105,IF(T106=FALSE,U106,IF(T107=FALSE,U107,IF(T108=FALSE,U108,V120)))))))) -> 1 | X101: =OFFSET('Input Rearing'!F17,O101,)*'Graph values'!V101 -> 0 | Y101: =X101+Y100 -> 0 | Z101: =OFFSET('Input Rearing'!X17,O101,0)*'Graph values'!V101 -> 0 | AA101: =Z101+AA100 -> 0 | AB101: =OFFSET('Input Rearing'!X17,O101,0)*'Graph values'!V101 -> 0 | AC101: =AB101+AC100 -> 0
A102: 7 | B102: =OFFSET('Input Rearing'!J18,M102,0)*100000 -> 0 | C102: =B102/100000 -> 0 | D102: =IF(OFFSET('Input Rearing'!M18,M102,0)="",#N/A,OFFSET('Input Rearing'!M18,M102,0)) -> #N/A | E102: =IF(OFFSET('Input Rearing'!Q18,O102,0)="",#N/A,OFFSET('Input Rearing'!Q18,O102,0)*100) -> #N/A | F102: =E102/10000 -> #N/A | G102: =IF(OFFSET('Input Rearing'!U18,O102,0)="",#N/A,OFFSET('Input Rearing'!U18,O102,0)*500) -> #DIV/0! | H102: =OFFSET('Input Rearing'!AA18,M102,0) -> 0 | J102: =OFFSET('Input Rearing'!N24,M102,0) -> 563.0625 | K102: =Std!I10 -> 591.9375 | L102: =H102/D102 -> #N/A | M102: =M101+6 -> 36 | O102: =O101+6 -> 36 | P102: 7 | Q102: =OFFSET('Input Rearing'!I18,'Graph values'!O102,0) -> 0 | R102: =R101+Q102 -> 0 | S102: =IF(Q102=0,S101,Q102) -> 0 | T102: =IF(S102=S101,TRUE,FALSE) -> TRUE | U102: =IF(T102=TRUE,U101,1-($Q$115/$Q$116)) -> 0 | V102: =IF(T102=FALSE,U102,IF(T103=FALSE,U103,IF(T104=FALSE,U104,IF(T105=FALSE,U105,IF(T106=FALSE,U106,IF(T107=FALSE,U107,IF(T108=FALSE,U108,IF(T109=FALSE,U109,V121)))))))) -> 1 | X102: =OFFSET('Input Rearing'!F18,O102,)*'Graph values'!V102 -> 0 | Y102: =X102+Y101 -> 0 | Z102: =OFFSET('Input Rearing'!X18,O102,0)*'Graph values'!V102 -> 0 | AA102: =Z102+AA101 -> 0 | AB102: =OFFSET('Input Rearing'!X18,O102,0)*'Graph values'!V102 -> 0 | AC102: =AB102+AC101 -> 0
A103: 8 | B103: =OFFSET('Input Rearing'!J19,M103,0)*100000 -> 0 | C103: =B103/100000 -> 0 | D103: =IF(OFFSET('Input Rearing'!M19,M103,0)="",#N/A,OFFSET('Input Rearing'!M19,M103,0)) -> #N/A | E103: =IF(OFFSET('Input Rearing'!Q19,O103,0)="",#N/A,OFFSET('Input Rearing'!Q19,O103,0)*100) -> #N/A | F103: =E103/10000 -> #N/A | G103: =IF(OFFSET('Input Rearing'!U19,O103,0)="",#N/A,OFFSET('Input Rearing'!U19,O103,0)*500) -> #DIV/0! | H103: =OFFSET('Input Rearing'!AA19,M103,0) -> 0 | J103: =OFFSET('Input Rearing'!N25,M103,0) -> 669.3375 | K103: =Std!I11 -> 703.6625 | L103: =H103/D103 -> #N/A | M103: =M102+6 -> 42 | O103: =O102+6 -> 42 | P103: 8 | Q103: =OFFSET('Input Rearing'!I19,'Graph values'!O103,0) -> 0 | R103: =R102+Q103 -> 0 | S103: =IF(Q103=0,S102,Q103) -> 0 | T103: =IF(S103=S102,TRUE,FALSE) -> TRUE | U103: =IF(T103=TRUE,U102,1-($Q$115/$Q$116)) -> 0 | V103: =IF(T103=FALSE,U103,IF(T104=FALSE,U104,IF(T105=FALSE,U105,IF(T106=FALSE,U106,IF(T107=FALSE,U107,IF(T108=FALSE,U108,IF(T109=FALSE,U109,IF(T110=FALSE,U110,V122)))))))) -> 1 | X103: =OFFSET('Input Rearing'!F19,O103,)*'Graph values'!V103 -> 0 | Y103: =X103+Y102 -> 0 | Z103: =OFFSET('Input Rearing'!X19,O103,0)*'Graph values'!V103 -> 0 | AA103: =Z103+AA102 -> 0 | AB103: =OFFSET('Input Rearing'!X19,O103,0)*'Graph values'!V103 -> 0 | AC103: =AB103+AC102 -> 0
A104: 9 | B104: =OFFSET('Input Rearing'!J20,M104,0)*100000 -> 0 | C104: =B104/100000 -> 0 | D104: =IF(OFFSET('Input Rearing'!M20,M104,0)="",#N/A,OFFSET('Input Rearing'!M20,M104,0)) -> #N/A | E104: =IF(OFFSET('Input Rearing'!Q20,O104,0)="",#N/A,OFFSET('Input Rearing'!Q20,O104,0)*100) -> #N/A | F104: =E104/10000 -> #N/A | G104: =IF(OFFSET('Input Rearing'!U20,O104,0)="",#N/A,OFFSET('Input Rearing'!U20,O104,0)*500) -> #DIV/0! | H104: =OFFSET('Input Rearing'!AA20,M104,0) -> 0 | J104: =OFFSET('Input Rearing'!N26,M104,0) -> 773.6625 | K104: =Std!I12 -> 813.3375 | L104: =H104/D104 -> #N/A | M104: =M103+6 -> 48 | O104: =O103+6 -> 48 | P104: 9 | Q104: =OFFSET('Input Rearing'!I20,'Graph values'!O104,0) -> 0 | R104: =R103+Q104 -> 0 | S104: =IF(Q104=0,S103,Q104) -> 0 | T104: =IF(S104=S103,TRUE,FALSE) -> TRUE | U104: =IF(T104=TRUE,U103,1-($Q$115/$Q$116)) -> 0 | V104: =IF(T104=FALSE,U104,IF(T105=FALSE,U105,IF(T106=FALSE,U106,IF(T107=FALSE,U107,IF(T108=FALSE,U108,IF(T109=FALSE,U109,IF(T110=FALSE,U110,IF(T111=FALSE,U111,V123)))))))) -> 1 | X104: =OFFSET('Input Rearing'!F20,O104,)*'Graph values'!V104 -> 0 | Y104: =X104+Y103 -> 0 | Z104: =OFFSET('Input Rearing'!X20,O104,0)*'Graph values'!V104 -> 0 | AA104: =Z104+AA103 -> 0 | AB104: =OFFSET('Input Rearing'!X20,O104,0)*'Graph values'!V104 -> 0 | AC104: =AB104+AC103 -> 0
A105: 10 | B105: =OFFSET('Input Rearing'!J21,M105,0)*100000 -> 0 | C105: =B105/100000 -> 0 | D105: =IF(OFFSET('Input Rearing'!M21,M105,0)="",#N/A,OFFSET('Input Rearing'!M21,M105,0)) -> #N/A | E105: =IF(OFFSET('Input Rearing'!Q21,O105,0)="",#N/A,OFFSET('Input Rearing'!Q21,O105,0)*100) -> #N/A | F105: =E105/10000 -> #N/A | G105: =IF(OFFSET('Input Rearing'!U21,O105,0)="",#N/A,OFFSET('Input Rearing'!U21,O105,0)*500) -> #DIV/0! | H105: =OFFSET('Input Rearing'!AA21,M105,0) -> 0 | J105: =OFFSET('Input Rearing'!N27,M105,0) -> 872.1375 | K105: =Std!I13 -> 916.8625 | L105: =H105/D105 -> #N/A | M105: =M104+6 -> 54 | O105: =O104+6 -> 54 | P105: 10 | Q105: =OFFSET('Input Rearing'!I21,'Graph values'!O105,0) -> 0 | R105: =R104+Q105 -> 0 | S105: =IF(Q105=0,S104,Q105) -> 0 | T105: =IF(S105=S104,TRUE,FALSE) -> TRUE | U105: =IF(T105=TRUE,U104,1-($Q$115/$Q$116)) -> 0 | V105: =IF(T105=FALSE,U105,IF(T106=FALSE,U106,IF(T107=FALSE,U107,IF(T108=FALSE,U108,IF(T109=FALSE,U109,IF(T110=FALSE,U110,IF(T111=FALSE,U111,IF(T112=FALSE,U112,V124)))))))) -> 1 | X105: =OFFSET('Input Rearing'!F21,O105,)*'Graph values'!V105 -> 0 | Y105: =X105+Y104 -> 0 | Z105: =OFFSET('Input Rearing'!X21,O105,0)*'Graph values'!V105 -> 0 | AA105: =Z105+AA104 -> 0 | AB105: =OFFSET('Input Rearing'!X21,O105,0)*'Graph values'!V105 -> 0 | AC105: =AB105+AC104 -> 0
A106: 11 | B106: =OFFSET('Input Rearing'!J22,M106,0)*100000 -> 0 | C106: =B106/100000 -> 0 | D106: =IF(OFFSET('Input Rearing'!M22,M106,0)="",#N/A,OFFSET('Input Rearing'!M22,M106,0)) -> #N/A | E106: =IF(OFFSET('Input Rearing'!Q22,O106,0)="",#N/A,OFFSET('Input Rearing'!Q22,O106,0)*100) -> #N/A | F106: =E106/10000 -> #N/A | G106: =IF(OFFSET('Input Rearing'!U22,O106,0)="",#N/A,OFFSET('Input Rearing'!U22,O106,0)*500) -> #DIV/0! | H106: =OFFSET('Input Rearing'!AA22,M106,0) -> 0 | J106: =OFFSET('Input Rearing'!N28,M106,0) -> 964.275 | K106: =Std!I14 -> 1013.725 | L106: =H106/D106 -> #N/A | M106: =M105+6 -> 60 | O106: =O105+6 -> 60 | P106: 11 | Q106: =OFFSET('Input Rearing'!I22,'Graph values'!O106,0) -> 0 | R106: =R105+Q106 -> 0 | S106: =IF(Q106=0,S105,Q106) -> 0 | T106: =IF(S106=S105,TRUE,FALSE) -> TRUE | U106: =IF(T106=TRUE,U105,1-($Q$115/$Q$116)) -> 0 | V106: =IF(T106=FALSE,U106,IF(T107=FALSE,U107,IF(T108=FALSE,U108,IF(T109=FALSE,U109,IF(T110=FALSE,U110,IF(T111=FALSE,U111,IF(T112=FALSE,U112,IF(T113=FALSE,U113,1)))))))) -> 1 | X106: =OFFSET('Input Rearing'!F22,O106,)*'Graph values'!V106 -> 0 | Y106: =X106+Y105 -> 0 | Z106: =OFFSET('Input Rearing'!X22,O106,0)*'Graph values'!V106 -> 0 | AA106: =Z106+AA105 -> 0 | AB106: =OFFSET('Input Rearing'!X22,O106,0)*'Graph values'!V106 -> 0 | AC106: =AB106+AC105 -> 0
A107: 12 | B107: =OFFSET('Input Rearing'!J23,M107,0)*100000 -> 0 | C107: =B107/100000 -> 0 | D107: =IF(OFFSET('Input Rearing'!M23,M107,0)="",#N/A,OFFSET('Input Rearing'!M23,M107,0)) -> #N/A | E107: =IF(OFFSET('Input Rearing'!Q23,O107,0)="",#N/A,OFFSET('Input Rearing'!Q23,O107,0)*100) -> #N/A | F107: =E107/10000 -> #N/A | G107: =IF(OFFSET('Input Rearing'!U23,O107,0)="",#N/A,OFFSET('Input Rearing'!U23,O107,0)*500) -> #DIV/0! | H107: =OFFSET('Input Rearing'!AA23,M107,0) -> 0 | J107: =OFFSET('Input Rearing'!N29,M107,0) -> 1049.5875 | K107: =Std!I15 -> 1103.4125 | L107: =H107/D107 -> #N/A | M107: =M106+6 -> 66 | O107: =O106+6 -> 66 | P107: 12 | Q107: =OFFSET('Input Rearing'!I23,'Graph values'!O107,0) -> 0 | R107: =R106+Q107 -> 0 | S107: =IF(Q107=0,S106,Q107) -> 0 | T107: =IF(S107=S106,TRUE,FALSE) -> TRUE | U107: =IF(T107=TRUE,U106,1-($Q$115/$Q$116)) -> 0 | V107: =IF(T107=FALSE,U107,IF(T108=FALSE,U108,IF(T109=FALSE,U109,IF(T110=FALSE,U110,IF(T111=FALSE,U111,IF(T112=FALSE,U112,IF(T113=FALSE,U113,1))))))) -> 1 | X107: =OFFSET('Input Rearing'!F23,O107,)*'Graph values'!V107 -> 0 | Y107: =X107+Y106 -> 0 | Z107: =OFFSET('Input Rearing'!X23,O107,0)*'Graph values'!V107 -> 0 | AA107: =Z107+AA106 -> 0 | AB107: =OFFSET('Input Rearing'!X23,O107,0)*'Graph values'!V107 -> 0 | AC107: =AB107+AC106 -> 0
A108: 13 | B108: =OFFSET('Input Rearing'!J24,M108,0)*100000 -> 0 | C108: =B108/100000 -> 0 | D108: =IF(OFFSET('Input Rearing'!M24,M108,0)="",#N/A,OFFSET('Input Rearing'!M24,M108,0)) -> #N/A | E108: =IF(OFFSET('Input Rearing'!Q24,O108,0)="",#N/A,OFFSET('Input Rearing'!Q24,O108,0)*100) -> #N/A | F108: =E108/10000 -> #N/A | G108: =IF(OFFSET('Input Rearing'!U24,O108,0)="",#N/A,OFFSET('Input Rearing'!U24,O108,0)*500) -> #DIV/0! | H108: =OFFSET('Input Rearing'!AA24,M108,0) -> 0 | J108: =OFFSET('Input Rearing'!N30,M108,0) -> 1131.975 | K108: =Std!I16 -> 1190.025 | L108: =H108/D108 -> #N/A | M108: =M107+6 -> 72 | O108: =O107+6 -> 72 | P108: 13 | Q108: =OFFSET('Input Rearing'!I24,'Graph values'!O108,0) -> 0 | R108: =R107+Q108 -> 0 | S108: =IF(Q108=0,S107,Q108) -> 0 | T108: =IF(S108=S107,TRUE,FALSE) -> TRUE | U108: =IF(T108=TRUE,U107,1-($Q$115/$Q$116)) -> 0 | V108: =IF(T108=FALSE,U108,IF(T109=FALSE,U109,IF(T110=FALSE,U110,IF(T111=FALSE,U111,IF(T112=FALSE,U112,IF(T113=FALSE,U113,1)))))) -> 1 | X108: =OFFSET('Input Rearing'!F24,O108,)*'Graph values'!V108 -> 0 | Y108: =X108+Y107 -> 0 | Z108: =OFFSET('Input Rearing'!X24,O108,0)*'Graph values'!V108 -> 0 | AA108: =Z108+AA107 -> 0 | AB108: =OFFSET('Input Rearing'!X24,O108,0)*'Graph values'!V108 -> 0 | AC108: =AB108+AC107 -> 0
A109: 14 | B109: =OFFSET('Input Rearing'!J25,M109,0)*100000 -> 0 | C109: =B109/100000 -> 0 | D109: =IF(OFFSET('Input Rearing'!M25,M109,0)="",#N/A,OFFSET('Input Rearing'!M25,M109,0)) -> #N/A | E109: =IF(OFFSET('Input Rearing'!Q25,O109,0)="",#N/A,OFFSET('Input Rearing'!Q25,O109,0)*100) -> #N/A | F109: =E109/10000 -> #N/A | G109: =IF(OFFSET('Input Rearing'!U25,O109,0)="",#N/A,OFFSET('Input Rearing'!U25,O109,0)*500) -> #DIV/0! | H109: =OFFSET('Input Rearing'!AA25,M109,0) -> 0 | J109: =OFFSET('Input Rearing'!N31,M109,0) -> 1206.5625 | K109: =Std!I17 -> 1268.4375 | L109: =H109/D109 -> #N/A | M109: =M108+6 -> 78 | O109: =O108+6 -> 78 | P109: 14 | Q109: =OFFSET('Input Rearing'!I25,'Graph values'!O109,0) -> 0 | R109: =R108+Q109 -> 0 | S109: =IF(Q109=0,S108,Q109) -> 0 | T109: =IF(S109=S108,TRUE,FALSE) -> TRUE | U109: =IF(T109=TRUE,U108,1-($Q$115/$Q$116)) -> 0 | V109: =IF(T109=FALSE,U109,IF(T110=FALSE,U110,IF(T111=FALSE,U111,IF(T112=FALSE,U112,IF(T113=FALSE,U113,1))))) -> 1 | X109: =OFFSET('Input Rearing'!F25,O109,)*'Graph values'!V109 -> 0 | Y109: =X109+Y108 -> 0 | Z109: =OFFSET('Input Rearing'!X25,O109,0)*'Graph values'!V109 -> 0 | AA109: =Z109+AA108 -> 0 | AB109: =OFFSET('Input Rearing'!X25,O109,0)*'Graph values'!V109 -> 0 | AC109: =AB109+AC108 -> 0
A110: 15 | B110: =OFFSET('Input Rearing'!J26,M110,0)*100000 -> 0 | C110: =B110/100000 -> 0 | D110: =IF(OFFSET('Input Rearing'!M26,M110,0)="",#N/A,OFFSET('Input Rearing'!M26,M110,0)) -> #N/A | E110: =IF(OFFSET('Input Rearing'!Q26,O110,0)="",#N/A,OFFSET('Input Rearing'!Q26,O110,0)*100) -> #N/A | F110: =E110/10000 -> #N/A | G110: =IF(OFFSET('Input Rearing'!U26,O110,0)="",#N/A,OFFSET('Input Rearing'!U26,O110,0)*500) -> #DIV/0! | H110: =OFFSET('Input Rearing'!AA26,M110,0) -> 0 | J110: =OFFSET('Input Rearing'!N32,M110,0) -> 1274.8125 | K110: =Std!I18 -> 1340.1875 | L110: =H110/D110 -> #N/A | M110: =M109+6 -> 84 | O110: =O109+6 -> 84 | P110: 15 | Q110: =OFFSET('Input Rearing'!I26,'Graph values'!O110,0) -> 0 | R110: =R109+Q110 -> 0 | S110: =IF(Q110=0,S109,Q110) -> 0 | T110: =IF(S110=S109,TRUE,FALSE) -> TRUE | U110: =IF(T110=TRUE,U109,1-($Q$115/$Q$116)) -> 0 | V110: =IF(T110=FALSE,U110,IF(T111=FALSE,U111,IF(T112=FALSE,U112,IF(T113=FALSE,U113,1)))) -> 1 | X110: =OFFSET('Input Rearing'!F26,O110,)*'Graph values'!V110 -> 0 | Y110: =X110+Y109 -> 0 | Z110: =OFFSET('Input Rearing'!X26,O110,0)*'Graph values'!V110 -> 0 | AA110: =Z110+AA109 -> 0 | AB110: =OFFSET('Input Rearing'!X26,O110,0)*'Graph values'!V110 -> 0 | AC110: =AB110+AC109 -> 0
A111: 16 | B111: =OFFSET('Input Rearing'!J27,M111,0)*100000 -> 0 | C111: =B111/100000 -> 0 | D111: =IF(OFFSET('Input Rearing'!M27,M111,0)="",#N/A,OFFSET('Input Rearing'!M27,M111,0)) -> #N/A | E111: =IF(OFFSET('Input Rearing'!Q27,O111,0)="",#N/A,OFFSET('Input Rearing'!Q27,O111,0)*100) -> #N/A | F111: =E111/10000 -> #N/A | G111: =IF(OFFSET('Input Rearing'!U27,O111,0)="",#N/A,OFFSET('Input Rearing'!U27,O111,0)*500) -> #DIV/0! | H111: =OFFSET('Input Rearing'!AA27,M111,0) -> 0 | J111: =OFFSET('Input Rearing'!N33,M111,0) -> 1343.0625 | K111: =Std!I19 -> 1411.9375 | L111: =H111/D111 -> #N/A | M111: =M110+6 -> 90 | O111: =O110+6 -> 90 | P111: 16 | Q111: =OFFSET('Input Rearing'!I27,'Graph values'!O111,0) -> 0 | R111: =R110+Q111 -> 0 | S111: =IF(Q111=0,S110,Q111) -> 0 | T111: =IF(S111=S110,TRUE,FALSE) -> TRUE | U111: =IF(T111=TRUE,U110,1-($Q$115/$Q$116)) -> 0 | V111: =IF(T111=FALSE,U111,IF(T112=FALSE,U112,IF(T113=FALSE,U113,1))) -> 1 | X111: =OFFSET('Input Rearing'!F27,O111,)*'Graph values'!V111 -> 0 | Y111: =X111+Y110 -> 0 | Z111: =OFFSET('Input Rearing'!X27,O111,0)*'Graph values'!V111 -> 0 | AA111: =Z111+AA110 -> 0 | AB111: =OFFSET('Input Rearing'!X27,O111,0)*'Graph values'!V111 -> 0 | AC111: =AB111+AC110 -> 0
A112: 17 | B112: =OFFSET('Input Rearing'!J28,M112,0)*100000 -> 0 | C112: =B112/100000 -> 0 | D112: =IF(OFFSET('Input Rearing'!M28,M112,0)="",#N/A,OFFSET('Input Rearing'!M28,M112,0)) -> #N/A | E112: =IF(OFFSET('Input Rearing'!Q28,O112,0)="",#N/A,OFFSET('Input Rearing'!Q28,O112,0)*100) -> #N/A | F112: =E112/10000 -> #N/A | G112: =IF(OFFSET('Input Rearing'!U28,O112,0)="",#N/A,OFFSET('Input Rearing'!U28,O112,0)*500) -> #DIV/0! | H112: =OFFSET('Input Rearing'!AA28,M112,0) -> 0 | J112: =OFFSET('Input Rearing'!N34,M112,0) -> 1403.5125 | K112: =Std!I20 -> 1475.4875 | L112: =H112/D112 -> #N/A | M112: =M111+6 -> 96 | O112: =O111+6 -> 96 | P112: 17 | Q112: =OFFSET('Input Rearing'!I28,'Graph values'!O112,0) -> 0 | R112: =R111+Q112 -> 0 | S112: =IF(Q112=0,S111,Q112) -> 0 | T112: =IF(S112=S111,TRUE,FALSE) -> TRUE | U112: =IF(T112=TRUE,U111,1-($Q$115/$Q$116)) -> 0 | V112: =IF(T112=FALSE,U112,IF(T113=FALSE,U113,1)) -> 1 | X112: =OFFSET('Input Rearing'!F28,O112,)*'Graph values'!V112 -> 0 | Y112: =X112+Y111 -> 0 | Z112: =OFFSET('Input Rearing'!X28,O112,0)*'Graph values'!V112 -> 0 | AA112: =Z112+AA111 -> 0 | AB112: =OFFSET('Input Rearing'!X28,O112,0)*'Graph values'!V112 -> 0 | AC112: =AB112+AC111 -> 0
A113: 18 | B113: =OFFSET('Input Rearing'!J29,M113,0)*100000 -> 0 | C113: =B113/100000 -> 0 | D113: =IF(OFFSET('Input Rearing'!M29,M113,0)="",#N/A,OFFSET('Input Rearing'!M29,M113,0)) -> #N/A | E113: =IF(OFFSET('Input Rearing'!Q29,O113,0)="",#N/A,OFFSET('Input Rearing'!Q29,O113,0)*100) -> #N/A | F113: =E113/10000 -> #N/A | G113: =IF(OFFSET('Input Rearing'!U29,O113,0)="",#N/A,OFFSET('Input Rearing'!U29,O113,0)*500) -> #DIV/0! | H113: =OFFSET('Input Rearing'!AA29,M113,0) -> 0 | J113: =OFFSET('Input Rearing'!N35,M113,0) -> 1462.5 | K113: =Std!I21 -> 1537.5 | L113: =H113/D113 -> #N/A | M113: =M112+6 -> 102 | O113: =O112+6 -> 102 | P113: 18 | Q113: =OFFSET('Input Rearing'!I29,'Graph values'!O113,0) -> 0 | R113: =R112+Q113 -> 0 | S113: =IF(Q113=0,S112,Q113) -> 0 | T113: =IF(S113=S112,TRUE,FALSE) -> TRUE | U113: =IF(T113=TRUE,U112,1-($Q$115/$Q$116)) -> 0 | V113: =IF(T113=FALSE,U113,1) -> 1 | X113: =OFFSET('Input Rearing'!F29,O113,)*'Graph values'!V113 -> 0 | Y113: =X113+Y112 -> 0 | Z113: =OFFSET('Input Rearing'!X29,O113,0)*'Graph values'!V113 -> 0 | AA113: =Z113+AA112 -> 0 | AB113: =OFFSET('Input Rearing'!X29,O113,0)*'Graph values'!V113 -> 0 | AC113: =AB113+AC112 -> 0
P115: somme tranfert | Q115: =Q113+Q112+Q111+Q110+Q109+Q108+Q107+Q106+Q105+Q104+Q103+Q102+Q101+Q100+Q99+Q98+Q97+Q96 -> 0 | V115: =IF(T104=FALSE,U104,IF(T105=FALSE,U105,IF(T106=FALSE,U106,IF(T107=FALSE,U107,IF(T108=FALSE,U108,IF(T109=FALSE,U109,IF(T110=FALSE,U110,IF(T111=FALSE,U111,W115)))))))) -> 1 | W115: =IF(T111=FALSE,U111,IF(T112=FALSE,U112,IF(T113=FALSE,U113,1))) -> 1
B116: max | C116: max | D116: last | E116: last | F116: max | P116: nb poule mep | Q116: ='Input Rearing'!G3 -> 10000 | V116: =IF(T105=FALSE,U105,IF(T106=FALSE,U106,IF(T107=FALSE,U107,IF(T108=FALSE,U108,IF(T109=FALSE,U109,IF(T110=FALSE,U110,IF(T111=FALSE,U111,IF(T112=FALSE,U112,W116)))))))) -> 1 | W116: =IF(T112=FALSE,U112,IF(T113=FALSE,U113,1)) -> 1
A117: Laying chart summary data | B117: =Language!B346 -> AEW | C117: =Language!B347 -> Egg/hh | D117: =Language!B348 -> FCR | E117: =Language!B349 -> FCR egg | F117: =Language!B350 -> Cum feed cons | G117: =Language!B351 -> Week | H117: test last week | P117: effectif corrigé | Q117: =Q116-Q115 -> 10000 | V117: =IF(T106=FALSE,U106,IF(T107=FALSE,U107,IF(T108=FALSE,U108,IF(T109=FALSE,U109,IF(T110=FALSE,U110,IF(T111=FALSE,U111,IF(T112=FALSE,U112,IF(T113=FALSE,U113,W117)))))))) -> 1 | W117: =IF(T113=FALSE,U113,1) -> 1
B118: =MAX('Production data'!J14:J97) -> 0 | C118: =MAX('Production data'!F14:F97) -> 0 | D118: =VLOOKUP(9^9,'Production data'!V14:V97,1) -> #N/A | E118: =VLOOKUP(9^9,'Production data'!$T$14:$T$97,1) -> #N/A | F118: =MAX(T7:T90) -> 0 | G118: =MAX(H118:H205) -> 0 | H118: =IF('Input Laying'!N11=0,0,'Input Laying'!C11) -> 0 | V118: =IF(T107=FALSE,U107,IF(T108=FALSE,U108,IF(T109=FALSE,U109,IF(T110=FALSE,U110,IF(T111=FALSE,U111,IF(T112=FALSE,U112,IF(T113=FALSE,U113,1))))))) -> 1 | W118: =IF(T114=FALSE,U114,1) -> 0
H119: =IF('Input Laying'!N12=0,0,'Input Laying'!C12) -> 0 | V119: =IF(T108=FALSE,U108,IF(T109=FALSE,U109,IF(T110=FALSE,U110,IF(T111=FALSE,U111,IF(T112=FALSE,U112,IF(T113=FALSE,U113,1)))))) -> 1 | W119: =IF(T115=FALSE,U115,1) -> 0
H120: =IF('Input Laying'!N13=0,0,'Input Laying'!C13) -> 0 | V120: =IF(T109=FALSE,U109,IF(T110=FALSE,U110,IF(T111=FALSE,U111,IF(T112=FALSE,U112,IF(T113=FALSE,U113,1))))) -> 1 | W120: =IF(T116=FALSE,U116,1) -> 0
H121: =IF('Input Laying'!N14=0,0,'Input Laying'!C14) -> 0 | V121: =IF(T110=FALSE,U110,IF(T111=FALSE,U111,IF(T112=FALSE,U112,IF(T113=FALSE,U113,1)))) -> 1
H122: =IF('Input Laying'!N15=0,0,'Input Laying'!C15) -> 0 | V122: =IF(T111=FALSE,U111,IF(T112=FALSE,U112,IF(T113=FALSE,U113,1))) -> 1
H123: =IF('Input Laying'!N16=0,0,'Input Laying'!C16) -> 0 | V123: =IF(T112=FALSE,U112,IF(T113=FALSE,U113,1)) -> 1
H124: =IF('Input Laying'!N17=0,0,'Input Laying'!C17) -> 0 | V124: =IF(T113=FALSE,U113,1) -> 1
H125: =IF('Input Laying'!N18=0,0,'Input Laying'!C18) -> 0 | V125: =IF(T114=FALSE,U114,1) -> 0
H126: =IF('Input Laying'!N19=0,0,'Input Laying'!C19) -> 0 | V126: =IF(T115=FALSE,U115,1) -> 0
H127: =IF('Input Laying'!N20=0,0,'Input Laying'!C20) -> 0 | V127: =IF(T116=FALSE,U116,1) -> 0
H128: =IF('Input Laying'!N21=0,0,'Input Laying'!C21) -> 0 | V128: =IF(T117=FALSE,U117,1) -> 0
H129: =IF('Input Laying'!N22=0,0,'Input Laying'!C22) -> 0 | V129: =IF(T118=FALSE,U118,1) -> 0
H130: =IF('Input Laying'!N23=0,0,'Input Laying'!C23) -> 0 | V130: =IF(T119=FALSE,U119,1) -> 0
H131: =IF('Input Laying'!N24=0,0,'Input Laying'!C24) -> 0 | V131: =IF(T120=FALSE,U120,1) -> 0
H132: =IF('Input Laying'!N25=0,0,'Input Laying'!C25) -> 0
H133: =IF('Input Laying'!N26=0,0,'Input Laying'!C26) -> 0
H134: =IF('Input Laying'!N27=0,0,'Input Laying'!C27) -> 0
H135: =IF('Input Laying'!N28=0,0,'Input Laying'!C28) -> 0
H136: =IF('Input Laying'!N29=0,0,'Input Laying'!C29) -> 0
H137: =IF('Input Laying'!N30=0,0,'Input Laying'!C30) -> 0
H138: =IF('Input Laying'!N31=0,0,'Input Laying'!C31) -> 0
H139: =IF('Input Laying'!N32=0,0,'Input Laying'!C32) -> 0
H140: =IF('Input Laying'!N33=0,0,'Input Laying'!C33) -> 0
H141: =IF('Input Laying'!N34=0,0,'Input Laying'!C34) -> 0
H142: =IF('Input Laying'!N35=0,0,'Input Laying'!C35) -> 0
H143: =IF('Input Laying'!N36=0,0,'Input Laying'!C36) -> 0
... H215: =IF('Input Laying'!N108=0,0,'Input Laying'!C108) -> 0

Sheet GHOST_SHEET
A1: CS | B1: Global | E1: data rearing | P1: data laying
A2: hatch date | B2: =C19 -> 0 | D2: rearing farm | E2: =IF('Input Rearing'!G1="","",'Input Rearing'!G1) | P2: number of layer housed | Q2: ='Input Laying'!$G$6 -> 0
A3: breed | B3: =IF('General Input'!B17="","",'General Input'!B17) -> ISA BROWN | D3: DOC housed | E3: =IF(OR('Graph values'!Q117="",'Graph values'!Q117=0),"",'Graph values'!Q117) -> 10000 | F3: weeks | G3: mortality | H3: transfer | I3: bodyweight | J3: uniformity | K3: water | L3: feed | M3: light duration | N3: light on at | O3: comments | Q3: depletion | R3: ponte semaine | S3: seconds farm | T3: seconds packing | U3: AEW | V3: WATER | W3: feed price /ton | X3: feed intake | Y3: feed EOW | Z3: uniformity | AA3: bdy weight | AB3: comments
A4: housing sys | B4: =IF(ISNA(Diverse!N2),"",Diverse!N2) | D4: rearing housing sys | E4: =IF(ISNA(Diverse!O15),"",Diverse!O15) | F4: 1 | G4: =IF(OR('Graph values'!X96="",'Graph values'!X96=0),"",'Graph values'!X96) | H4: =IF(OR('Graph values'!Q96="",'Graph values'!Q96=0),"",'Graph values'!Q96) | I4: =IF(ISNA('Graph values'!D96),"",'Graph values'!D96) | J4: =IF(ISNA('Graph values'!F96*100),"",'Graph values'!F96*100) | K4: =OFFSET('Input Rearing'!S12,'Graph values'!O96,0) -> 0 | L4: ='Graph values'!Z96 -> 0 | M4: =OFFSET('Input Rearing'!AC12,'Graph values'!O96,0) | N4: =OFFSET('Input Rearing'!AE12,'Graph values'!O96,0) | O4: =OFFSET('Input Rearing'!AF12,'Graph values'!O96,0) -> 0 | P4: 17 | Q4: =IF(OR('Input Laying'!E15="",'Input Laying'!E15=0),"",'Input Laying'!E15) | R4: =IF(OR('Input Laying'!N15="",'Input Laying'!N15=0),"",'Input Laying'!N15) | S4: =IF(OR('Input Laying'!T15="",'Input Laying'!T15=0),"",'Input Laying'!T15) | T4: =IF(OR('Input Laying'!U15="",'Input Laying'!U15=0),"",'Input Laying'!U15) | U4: =IF(OR('Input Laying'!X15="",'Input Laying'!X15=0),"",'Input Laying'!X15) | V4: =IF(OR('Input Laying'!Z15="",'Input Laying'!Z15=0),"",'Input Laying'!Z15) | W4: =IF('Input Laying'!AC15="","",'Input Laying'!AC15) | X4: =IF('Input Laying'!AD15="","",'Input Laying'!AD15) | Y4: =IF('Input Laying'!AE15="","",'Input Laying'!AE15) | Z4: =IF('Input Laying'!AG15="","",'Input Laying'!AG15) | AA4: =IF(OR('Input Laying'!AH15=0,'Input Laying'!AH15=""),"",'Input Laying'!AH15) | AB4: =IF('Input Laying'!AJ15="","",'Input Laying'!AJ15)
A5: producer | B5: =(IF('General Input'!B19="","",'General Input'!B19)) | D5: house nr | E5: =IF('Input Rearing'!G7="","",'Input Rearing'!G7) | F5: 2 | G5: =IF(OR('Graph values'!X97="",'Graph values'!X97=0),"",'Graph values'!X97) | H5: =IF(OR('Graph values'!Q97="",'Graph values'!Q97=0),"",'Graph values'!Q97) | I5: =IF(ISNA('Graph values'!D97),"",'Graph values'!D97) | J5: =IF(ISNA('Graph values'!F97*100),"",'Graph values'!F97*100) | K5: =OFFSET('Input Rearing'!S13,'Graph values'!O97,0) -> 0 | L5: ='Graph values'!Z97 -> 0 | M5: =OFFSET('Input Rearing'!AC13,'Graph values'!O97,0) | N5: =OFFSET('Input Rearing'!AE13,'Graph values'!O97,0) | O5: =OFFSET('Input Rearing'!AF13,'Graph values'!O97,0) -> 0 | P5: 18 | Q5: =IF(OR('Input Laying'!E16="",'Input Laying'!E16=0),"",'Input Laying'!E16) | R5: =IF(OR('Input Laying'!N16="",'Input Laying'!N16=0),"",'Input Laying'!N16) | S5: =IF(OR('Input Laying'!T16="",'Input Laying'!T16=0),"",'Input Laying'!T16) | T5: =IF(OR('Input Laying'!U16="",'Input Laying'!U16=0),"",'Input Laying'!U16) | U5: =IF(OR('Input Laying'!X16="",'Input Laying'!X16=0),"",'Input Laying'!X16) | V5: =IF(OR('Input Laying'!Z16="",'Input Laying'!Z16=0),"",'Input Laying'!Z16) | W5: =IF('Input Laying'!AC16="","",'Input Laying'!AC16) | X5: =IF('Input Laying'!AD16="","",'Input Laying'!AD16) | Y5: =IF('Input Laying'!AE16="","",'Input Laying'!AE16) | Z5: =IF('Input Laying'!AG16="","",'Input Laying'!AG16) | AA5: =IF(OR('Input Laying'!AH16=0,'Input Laying'!AH16=""),"",'Input Laying'!AH16) | AB5: =IF('Input Laying'!AJ16="","",'Input Laying'!AJ16)
A6: farm | B6: =IF('General Input'!B20="","",'General Input'!B20) | F6: 3 | G6: =IF(OR('Graph values'!X98="",'Graph values'!X98=0),"",'Graph values'!X98) | H6: =IF(OR('Graph values'!Q98="",'Graph values'!Q98=0),"",'Graph values'!Q98) | I6: =IF(ISNA('Graph values'!D98),"",'Graph values'!D98) | J6: =IF(ISNA('Graph values'!F98*100),"",'Graph values'!F98*100) | K6: =OFFSET('Input Rearing'!S14,'Graph values'!O98,0) -> 0 | L6: ='Graph values'!Z98 -> 0 | M6: =OFFSET('Input Rearing'!AC14,'Graph values'!O98,0) | N6: =OFFSET('Input Rearing'!AE14,'Graph values'!O98,0) | O6: =OFFSET('Input Rearing'!AF14,'Graph values'!O98,0) -> 0 | P6: 19 | Q6: =IF(OR('Input Laying'!E17="",'Input Laying'!E17=0),"",'Input Laying'!E17) | R6: =IF(OR('Input Laying'!N17="",'Input Laying'!N17=0),"",'Input Laying'!N17) | S6: =IF(OR('Input Laying'!T17="",'Input Laying'!T17=0),"",'Input Laying'!T17) | T6: =IF(OR('Input Laying'!U17="",'Input Laying'!U17=0),"",'Input Laying'!U17) | U6: =IF(OR('Input Laying'!X17="",'Input Laying'!X17=0),"",'Input Laying'!X17) | V6: =IF(OR('Input Laying'!Z17="",'Input Laying'!Z17=0),"",'Input Laying'!Z17) | W6: =IF('Input Laying'!AC17="","",'Input Laying'!AC17) | X6: =IF('Input Laying'!AD17="","",'Input Laying'!AD17) | Y6: =IF('Input Laying'!AE17="","",'Input Laying'!AE17) | Z6: =IF('Input Laying'!AG17="","",'Input Laying'!AG17) | AA6: =IF(OR('Input Laying'!AH17=0,'Input Laying'!AH17=""),"",'Input Laying'!AH17) | AB6: =IF('Input Laying'!AJ17="","",'Input Laying'!AJ17)
A7: house | B7: =IF('General Input'!B21="","",'General Input'!B21) | F7: 4 | G7: =IF(OR('Graph values'!X99="",'Graph values'!X99=0),"",'Graph values'!X99) | H7: =IF(OR('Graph values'!Q99="",'Graph values'!Q99=0),"",'Graph values'!Q99) | I7: =IF(ISNA('Graph values'!D99),"",'Graph values'!D99) | J7: =IF(ISNA('Graph values'!F99*100),"",'Graph values'!F99*100) | K7: =OFFSET('Input Rearing'!S15,'Graph values'!O99,0) -> 0 | L7: ='Graph values'!Z99 -> 0 | M7: =OFFSET('Input Rearing'!AC15,'Graph values'!O99,0) | N7: =OFFSET('Input Rearing'!AE15,'Graph values'!O99,0) | O7: =OFFSET('Input Rearing'!AF15,'Graph values'!O99,0) -> 0 | P7: 20 | Q7: =IF(OR('Input Laying'!E18="",'Input Laying'!E18=0),"",'Input Laying'!E18) | R7: =IF(OR('Input Laying'!N18="",'Input Laying'!N18=0),"",'Input Laying'!N18) | S7: =IF(OR('Input Laying'!T18="",'Input Laying'!T18=0),"",'Input Laying'!T18) | T7: =IF(OR('Input Laying'!U18="",'Input Laying'!U18=0),"",'Input Laying'!U18) | U7: =IF(OR('Input Laying'!X18="",'Input Laying'!X18=0),"",'Input Laying'!X18) | V7: =IF(OR('Input Laying'!Z18="",'Input Laying'!Z18=0),"",'Input Laying'!Z18) | W7: =IF('Input Laying'!AC18="","",'Input Laying'!AC18) | X7: =IF('Input Laying'!AD18="","",'Input Laying'!AD18) | Y7: =IF('Input Laying'!AE18="","",'Input Laying'!AE18) | Z7: =IF('Input Laying'!AG18="","",'Input Laying'!AG18) | AA7: =IF(OR('Input Laying'!AH18=0,'Input Laying'!AH18=""),"",'Input Laying'!AH18) | AB7: =IF('Input Laying'!AJ18="","",'Input Laying'!AJ18)
A8: country | B8: ='General Input'!B22 -> 0 | F8: 5 | G8: =IF(OR('Graph values'!X100="",'Graph values'!X100=0),"",'Graph values'!X100) | H8: =IF(OR('Graph values'!Q100="",'Graph values'!Q100=0),"",'Graph values'!Q100) | I8: =IF(ISNA('Graph values'!D100),"",'Graph values'!D100) | J8: =IF(ISNA('Graph values'!F100*100),"",'Graph values'!F100*100) | K8: =OFFSET('Input Rearing'!S16,'Graph values'!O100,0) -> 0 | L8: ='Graph values'!Z100 -> 0 | M8: =OFFSET('Input Rearing'!AC16,'Graph values'!O100,0) | N8: =OFFSET('Input Rearing'!AE16,'Graph values'!O100,0) | O8: =OFFSET('Input Rearing'!AF16,'Graph values'!O100,0) -> 0 | P8: 21 | Q8: =IF(OR('Input Laying'!E19="",'Input Laying'!E19=0),"",'Input Laying'!E19) | R8: =IF(OR('Input Laying'!N19="",'Input Laying'!N19=0),"",'Input Laying'!N19) | S8: =IF(OR('Input Laying'!T19="",'Input Laying'!T19=0),"",'Input Laying'!T19) | T8: =IF(OR('Input Laying'!U19="",'Input Laying'!U19=0),"",'Input Laying'!U19) | U8: =IF(OR('Input Laying'!X19="",'Input Laying'!X19=0),"",'Input Laying'!X19) | V8: =IF(OR('Input Laying'!Z19="",'Input Laying'!Z19=0),"",'Input Laying'!Z19) | W8: =IF('Input Laying'!AC19="","",'Input Laying'!AC19) | X8: =IF('Input Laying'!AD19="","",'Input Laying'!AD19) | Y8: =IF('Input Laying'!AE19="","",'Input Laying'!AE19) | Z8: =IF('Input Laying'!AG19="","",'Input Laying'!AG19) | AA8: =IF(OR('Input Laying'!AH19=0,'Input Laying'!AH19=""),"",'Input Laying'!AH19) | AB8: =IF('Input Laying'!AJ19="","",'Input Laying'!AJ19)
A9: version | B9: 919071L | F9: 6 | G9: =IF(OR('Graph values'!X101="",'Graph values'!X101=0),"",'Graph values'!X101) | H9: =IF(OR('Graph values'!Q101="",'Graph values'!Q101=0),"",'Graph values'!Q101) | I9: =IF(ISNA('Graph values'!D101),"",'Graph values'!D101) | J9: =IF(ISNA('Graph values'!F101*100),"",'Graph values'!F101*100) | K9: =OFFSET('Input Rearing'!S17,'Graph values'!O101,0) -> 0 | L9: ='Graph values'!Z101 -> 0 | M9: =OFFSET('Input Rearing'!AC17,'Graph values'!O101,0) | N9: =OFFSET('Input Rearing'!AE17,'Graph values'!O101,0) | O9: =OFFSET('Input Rearing'!AF17,'Graph values'!O101,0) -> 0 | P9: 22 | Q9: =IF(OR('Input Laying'!E20="",'Input Laying'!E20=0),"",'Input Laying'!E20) | R9: =IF(OR('Input Laying'!N20="",'Input Laying'!N20=0),"",'Input Laying'!N20) | S9: =IF(OR('Input Laying'!T20="",'Input Laying'!T20=0),"",'Input Laying'!T20) | T9: =IF(OR('Input Laying'!U20="",'Input Laying'!U20=0),"",'Input Laying'!U20) | U9: =IF(OR('Input Laying'!X20="",'Input Laying'!X20=0),"",'Input Laying'!X20) | V9: =IF(OR('Input Laying'!Z20="",'Input Laying'!Z20=0),"",'Input Laying'!Z20) | W9: =IF('Input Laying'!AC20="","",'Input Laying'!AC20) | X9: =IF('Input Laying'!AD20="","",'Input Laying'!AD20) | Y9: =IF('Input Laying'!AE20="","",'Input Laying'!AE20) | Z9: =IF('Input Laying'!AG20="","",'Input Laying'!AG20) | AA9: =IF(OR('Input Laying'!AH20=0,'Input Laying'!AH20=""),"",'Input Laying'!AH20) | AB9: =IF('Input Laying'!AJ20="","",'Input Laying'!AJ20)
A10: email sent to | B10: =IF('General Input'!B24="","",'General Input'!B24) | F10: 7 | G10: =IF(OR('Graph values'!X102="",'Graph values'!X102=0),"",'Graph values'!X102) | H10: =IF(OR('Graph values'!Q102="",'Graph values'!Q102=0),"",'Graph values'!Q102) | I10: =IF(ISNA('Graph values'!D102),"",'Graph values'!D102) | J10: =IF(ISNA('Graph values'!F102*100),"",'Graph values'!F102*100) | K10: =OFFSET('Input Rearing'!S18,'Graph values'!O102,0) -> 0 | L10: ='Graph values'!Z102 -> 0 | M10: =OFFSET('Input Rearing'!AC18,'Graph values'!O102,0) | N10: =OFFSET('Input Rearing'!AE18,'Graph values'!O102,0) | O10: =OFFSET('Input Rearing'!AF18,'Graph values'!O102,0) -> 0 | P10: 23 | Q10: =IF(OR('Input Laying'!E21="",'Input Laying'!E21=0),"",'Input Laying'!E21) | R10: =IF(OR('Input Laying'!N21="",'Input Laying'!N21=0),"",'Input Laying'!N21) | S10: =IF(OR('Input Laying'!T21="",'Input Laying'!T21=0),"",'Input Laying'!T21) | T10: =IF(OR('Input Laying'!U21="",'Input Laying'!U21=0),"",'Input Laying'!U21) | U10: =IF(OR('Input Laying'!X21="",'Input Laying'!X21=0),"",'Input Laying'!X21) | V10: =IF(OR('Input Laying'!Z21="",'Input Laying'!Z21=0),"",'Input Laying'!Z21) | W10: =IF('Input Laying'!AC21="","",'Input Laying'!AC21) | X10: =IF('Input Laying'!AD21="","",'Input Laying'!AD21) | Y10: =IF('Input Laying'!AE21="","",'Input Laying'!AE21) | Z10: =IF('Input Laying'!AG21="","",'Input Laying'!AG21) | AA10: =IF(OR('Input Laying'!AH21=0,'Input Laying'!AH21=""),"",'Input Laying'!AH21) | AB10: =IF('Input Laying'!AJ21="","",'Input Laying'!AJ21)
A11: filename | B11: =IF('General Input'!B26="#N/A",DEFAULT,'General Input'!B26) -> 000100 ISA BROWN - | F11: 8 | G11: =IF(OR('Graph values'!X103="",'Graph values'!X103=0),"",'Graph values'!X103) | H11: =IF(OR('Graph values'!Q103="",'Graph values'!Q103=0),"",'Graph values'!Q103) | I11: =IF(ISNA('Graph values'!D103),"",'Graph values'!D103) | J11: =IF(ISNA('Graph values'!F103*100),"",'Graph values'!F103*100) | K11: =OFFSET('Input Rearing'!S19,'Graph values'!O103,0) -> 0 | L11: ='Graph values'!Z103 -> 0 | M11: =OFFSET('Input Rearing'!AC19,'Graph values'!O103,0) | N11: =OFFSET('Input Rearing'!AE19,'Graph values'!O103,0) | O11: =OFFSET('Input Rearing'!AF19,'Graph values'!O103,0) -> 0 | P11: 24 | Q11: =IF(OR('Input Laying'!E22="",'Input Laying'!E22=0),"",'Input Laying'!E22) | R11: =IF(OR('Input Laying'!N22="",'Input Laying'!N22=0),"",'Input Laying'!N22) | S11: =IF(OR('Input Laying'!T22="",'Input Laying'!T22=0),"",'Input Laying'!T22) | T11: =IF(OR('Input Laying'!U22="",'Input Laying'!U22=0),"",'Input Laying'!U22) | U11: =IF(OR('Input Laying'!X22="",'Input Laying'!X22=0),"",'Input Laying'!X22) | V11: =IF(OR('Input Laying'!Z22="",'Input Laying'!Z22=0),"",'Input Laying'!Z22) | W11: =IF('Input Laying'!AC22="","",'Input Laying'!AC22) | X11: =IF('Input Laying'!AD22="","",'Input Laying'!AD22) | Y11: =IF('Input Laying'!AE22="","",'Input Laying'!AE22) | Z11: =IF('Input Laying'!AG22="","",'Input Laying'!AG22) | AA11: =IF(OR('Input Laying'!AH22=0,'Input Laying'!AH22=""),"",'Input Laying'!AH22) | AB11: =IF('Input Laying'!AJ22="","",'Input Laying'!AJ22)
A12: object | B12: =CONCATENATE(B5," ",B6," ",B7) | F12: 9 | G12: =IF(OR('Graph values'!X104="",'Graph values'!X104=0),"",'Graph values'!X104) | H12: =IF(OR('Graph values'!Q104="",'Graph values'!Q104=0),"",'Graph values'!Q104) | I12: =IF(ISNA('Graph values'!D104),"",'Graph values'!D104) | J12: =IF(ISNA('Graph values'!F104*100),"",'Graph values'!F104*100) | K12: =OFFSET('Input Rearing'!S20,'Graph values'!O104,0) -> 0 | L12: ='Graph values'!Z104 -> 0 | M12: =OFFSET('Input Rearing'!AC20,'Graph values'!O104,0) | N12: =OFFSET('Input Rearing'!AE20,'Graph values'!O104,0) | O12: =OFFSET('Input Rearing'!AF20,'Graph values'!O104,0) -> 0 | P12: 25 | Q12: =IF(OR('Input Laying'!E23="",'Input Laying'!E23=0),"",'Input Laying'!E23) | R12: =IF(OR('Input Laying'!N23="",'Input Laying'!N23=0),"",'Input Laying'!N23) | S12: =IF(OR('Input Laying'!T23="",'Input Laying'!T23=0),"",'Input Laying'!T23) | T12: =IF(OR('Input Laying'!U23="",'Input Laying'!U23=0),"",'Input Laying'!U23) | U12: =IF(OR('Input Laying'!X23="",'Input Laying'!X23=0),"",'Input Laying'!X23) | V12: =IF(OR('Input Laying'!Z23="",'Input Laying'!Z23=0),"",'Input Laying'!Z23) | W12: =IF('Input Laying'!AC23="","",'Input Laying'!AC23) | X12: =IF('Input Laying'!AD23="","",'Input Laying'!AD23) | Y12: =IF('Input Laying'!AE23="","",'Input Laying'!AE23) | Z12: =IF('Input Laying'!AG23="","",'Input Laying'!AG23) | AA12: =IF(OR('Input Laying'!AH23=0,'Input Laying'!AH23=""),"",'Input Laying'!AH23) | AB12: =IF('Input Laying'!AJ23="","",'Input Laying'!AJ23)
F13: 10 | G13: =IF(OR('Graph values'!X105="",'Graph values'!X105=0),"",'Graph values'!X105) | H13: =IF(OR('Graph values'!Q105="",'Graph values'!Q105=0),"",'Graph values'!Q105) | I13: =IF(ISNA('Graph values'!D105),"",'Graph values'!D105) | J13: =IF(ISNA('Graph values'!F105*100),"",'Graph values'!F105*100) | K13: =OFFSET('Input Rearing'!S21,'Graph values'!O105,0) -> 0 | L13: ='Graph values'!Z105 -> 0 | M13: =OFFSET('Input Rearing'!AC21,'Graph values'!O105,0) | N13: =OFFSET('Input Rearing'!AE21,'Graph values'!O105,0) | O13: =OFFSET('Input Rearing'!AF21,'Graph values'!O105,0) -> 0 | P13: 26 | Q13: =IF(OR('Input Laying'!E24="",'Input Laying'!E24=0),"",'Input Laying'!E24) | R13: =IF(OR('Input Laying'!N24="",'Input Laying'!N24=0),"",'Input Laying'!N24) | S13: =IF(OR('Input Laying'!T24="",'Input Laying'!T24=0),"",'Input Laying'!T24) | T13: =IF(OR('Input Laying'!U24="",'Input Laying'!U24=0),"",'Input Laying'!U24) | U13: =IF(OR('Input Laying'!X24="",'Input Laying'!X24=0),"",'Input Laying'!X24) | V13: =IF(OR('Input Laying'!Z24="",'Input Laying'!Z24=0),"",'Input Laying'!Z24) | W13: =IF('Input Laying'!AC24="","",'Input Laying'!AC24) | X13: =IF('Input Laying'!AD24="","",'Input Laying'!AD24) | Y13: =IF('Input Laying'!AE24="","",'Input Laying'!AE24) | Z13: =IF('Input Laying'!AG24="","",'Input Laying'!AG24) | AA13: =IF(OR('Input Laying'!AH24=0,'Input Laying'!AH24=""),"",'Input Laying'!AH24) | AB13: =IF('Input Laying'!AJ24="","",'Input Laying'!AJ24)
B14: Hatch date | F14: 11 | G14: =IF(OR('Graph values'!X106="",'Graph values'!X106=0),"",'Graph values'!X106) | H14: =IF(OR('Graph values'!Q106="",'Graph values'!Q106=0),"",'Graph values'!Q106) | I14: =IF(ISNA('Graph values'!D106),"",'Graph values'!D106) | J14: =IF(ISNA('Graph values'!F106*100),"",'Graph values'!F106*100) | K14: =OFFSET('Input Rearing'!S22,'Graph values'!O106,0) -> 0 | L14: ='Graph values'!Z106 -> 0 | M14: =OFFSET('Input Rearing'!AC22,'Graph values'!O106,0) | N14: =OFFSET('Input Rearing'!AE22,'Graph values'!O106,0) | O14: =OFFSET('Input Rearing'!AF22,'Graph values'!O106,0) -> 0 | P14: 27 | Q14: =IF(OR('Input Laying'!E25="",'Input Laying'!E25=0),"",'Input Laying'!E25) | R14: =IF(OR('Input Laying'!N25="",'Input Laying'!N25=0),"",'Input Laying'!N25) | S14: =IF(OR('Input Laying'!T25="",'Input Laying'!T25=0),"",'Input Laying'!T25) | T14: =IF(OR('Input Laying'!U25="",'Input Laying'!U25=0),"",'Input Laying'!U25) | U14: =IF(OR('Input Laying'!X25="",'Input Laying'!X25=0),"",'Input Laying'!X25) | V14: =IF(OR('Input Laying'!Z25="",'Input Laying'!Z25=0),"",'Input Laying'!Z25) | W14: =IF('Input Laying'!AC25="","",'Input Laying'!AC25) | X14: =IF('Input Laying'!AD25="","",'Input Laying'!AD25) | Y14: =IF('Input Laying'!AE25="","",'Input Laying'!AE25) | Z14: =IF('Input Laying'!AG25="","",'Input Laying'!AG25) | AA14: =IF(OR('Input Laying'!AH25=0,'Input Laying'!AH25=""),"",'Input Laying'!AH25) | AB14: =IF('Input Laying'!AJ25="","",'Input Laying'!AJ25)
A15: complete year | B15: =IF(B16="","",B16+2000) -> 2000 | F15: 12 | G15: =IF(OR('Graph values'!X107="",'Graph values'!X107=0),"",'Graph values'!X107) | H15: =IF(OR('Graph values'!Q107="",'Graph values'!Q107=0),"",'Graph values'!Q107) | I15: =IF(ISNA('Graph values'!D107),"",'Graph values'!D107) | J15: =IF(ISNA('Graph values'!F107*100),"",'Graph values'!F107*100) | K15: =OFFSET('Input Rearing'!S23,'Graph values'!O107,0) -> 0 | L15: ='Graph values'!Z107 -> 0 | M15: =OFFSET('Input Rearing'!AC23,'Graph values'!O107,0) | N15: =OFFSET('Input Rearing'!AE23,'Graph values'!O107,0) | O15: =OFFSET('Input Rearing'!AF23,'Graph values'!O107,0) -> 0 | P15: 28 | Q15: =IF(OR('Input Laying'!E26="",'Input Laying'!E26=0),"",'Input Laying'!E26) | R15: =IF(OR('Input Laying'!N26="",'Input Laying'!N26=0),"",'Input Laying'!N26) | S15: =IF(OR('Input Laying'!T26="",'Input Laying'!T26=0),"",'Input Laying'!T26) | T15: =IF(OR('Input Laying'!U26="",'Input Laying'!U26=0),"",'Input Laying'!U26) | U15: =IF(OR('Input Laying'!X26="",'Input Laying'!X26=0),"",'Input Laying'!X26) | V15: =IF(OR('Input Laying'!Z26="",'Input Laying'!Z26=0),"",'Input Laying'!Z26) | W15: =IF('Input Laying'!AC26="","",'Input Laying'!AC26) | X15: =IF('Input Laying'!AD26="","",'Input Laying'!AD26) | Y15: =IF('Input Laying'!AE26="","",'Input Laying'!AE26) | Z15: =IF('Input Laying'!AG26="","",'Input Laying'!AG26) | AA15: =IF(OR('Input Laying'!AH26=0,'Input Laying'!AH26=""),"",'Input Laying'!AH26) | AB15: =IF('Input Laying'!AJ26="","",'Input Laying'!AJ26)
A16: year | B16: =Diverse!C2 -> 00 | C16: =IF(ISNA(B16),"",B16) -> 00 | F16: 13 | G16: =IF(OR('Graph values'!X108="",'Graph values'!X108=0),"",'Graph values'!X108) | H16: =IF(OR('Graph values'!Q108="",'Graph values'!Q108=0),"",'Graph values'!Q108) | I16: =IF(ISNA('Graph values'!D108),"",'Graph values'!D108) | J16: =IF(ISNA('Graph values'!F108*100),"",'Graph values'!F108*100) | K16: =OFFSET('Input Rearing'!S24,'Graph values'!O108,0) -> 0 | L16: ='Graph values'!Z108 -> 0 | M16: =OFFSET('Input Rearing'!AC24,'Graph values'!O108,0) | N16: =OFFSET('Input Rearing'!AE24,'Graph values'!O108,0) | O16: =OFFSET('Input Rearing'!AF24,'Graph values'!O108,0) -> 0 | P16: 29 | Q16: =IF(OR('Input Laying'!E27="",'Input Laying'!E27=0),"",'Input Laying'!E27) | R16: =IF(OR('Input Laying'!N27="",'Input Laying'!N27=0),"",'Input Laying'!N27) | S16: =IF(OR('Input Laying'!T27="",'Input Laying'!T27=0),"",'Input Laying'!T27) | T16: =IF(OR('Input Laying'!U27="",'Input Laying'!U27=0),"",'Input Laying'!U27) | U16: =IF(OR('Input Laying'!X27="",'Input Laying'!X27=0),"",'Input Laying'!X27) | V16: =IF(OR('Input Laying'!Z27="",'Input Laying'!Z27=0),"",'Input Laying'!Z27) | W16: =IF('Input Laying'!AC27="","",'Input Laying'!AC27) | X16: =IF('Input Laying'!AD27="","",'Input Laying'!AD27) | Y16: =IF('Input Laying'!AE27="","",'Input Laying'!AE27) | Z16: =IF('Input Laying'!AG27="","",'Input Laying'!AG27) | AA16: =IF(OR('Input Laying'!AH27=0,'Input Laying'!AH27=""),"",'Input Laying'!AH27) | AB16: =IF('Input Laying'!AJ27="","",'Input Laying'!AJ27)
A17: month | B17: =Diverse!E2 -> 01 | C17: =IF(ISNA(B17),"",B17) -> 01 | F17: 14 | G17: =IF(OR('Graph values'!X109="",'Graph values'!X109=0),"",'Graph values'!X109) | H17: =IF(OR('Graph values'!Q109="",'Graph values'!Q109=0),"",'Graph values'!Q109) | I17: =IF(ISNA('Graph values'!D109),"",'Graph values'!D109) | J17: =IF(ISNA('Graph values'!F109*100),"",'Graph values'!F109*100) | K17: =OFFSET('Input Rearing'!S25,'Graph values'!O109,0) -> 0 | L17: ='Graph values'!Z109 -> 0 | M17: =OFFSET('Input Rearing'!AC25,'Graph values'!O109,0) | N17: =OFFSET('Input Rearing'!AE25,'Graph values'!O109,0) | O17: =OFFSET('Input Rearing'!AF25,'Graph values'!O109,0) -> 0 | P17: 30 | Q17: =IF(OR('Input Laying'!E28="",'Input Laying'!E28=0),"",'Input Laying'!E28) | R17: =IF(OR('Input Laying'!N28="",'Input Laying'!N28=0),"",'Input Laying'!N28) | S17: =IF(OR('Input Laying'!T28="",'Input Laying'!T28=0),"",'Input Laying'!T28) | T17: =IF(OR('Input Laying'!U28="",'Input Laying'!U28=0),"",'Input Laying'!U28) | U17: =IF(OR('Input Laying'!X28="",'Input Laying'!X28=0),"",'Input Laying'!X28) | V17: =IF(OR('Input Laying'!Z28="",'Input Laying'!Z28=0),"",'Input Laying'!Z28) | W17: =IF('Input Laying'!AC28="","",'Input Laying'!AC28) | X17: =IF('Input Laying'!AD28="","",'Input Laying'!AD28) | Y17: =IF('Input Laying'!AE28="","",'Input Laying'!AE28) | Z17: =IF('Input Laying'!AG28="","",'Input Laying'!AG28) | AA17: =IF(OR('Input Laying'!AH28=0,'Input Laying'!AH28=""),"",'Input Laying'!AH28) | AB17: =IF('Input Laying'!AJ28="","",'Input Laying'!AJ28)
A18: day | B18: =Diverse!H2 -> 00 | C18: =IF(ISNA(B18),"",B18) -> 00 | F18: 15 | G18: =IF(OR('Graph values'!X110="",'Graph values'!X110=0),"",'Graph values'!X110) | H18: =IF(OR('Graph values'!Q110="",'Graph values'!Q110=0),"",'Graph values'!Q110) | I18: =IF(ISNA('Graph values'!D110),"",'Graph values'!D110) | J18: =IF(ISNA('Graph values'!F110*100),"",'Graph values'!F110*100) | K18: =OFFSET('Input Rearing'!S26,'Graph values'!O110,0) -> 0 | L18: ='Graph values'!Z110 -> 0 | M18: =OFFSET('Input Rearing'!AC26,'Graph values'!O110,0) | N18: =OFFSET('Input Rearing'!AE26,'Graph values'!O110,0) | O18: =OFFSET('Input Rearing'!AF26,'Graph values'!O110,0) -> 0 | P18: 31 | Q18: =IF(OR('Input Laying'!E29="",'Input Laying'!E29=0),"",'Input Laying'!E29) | R18: =IF(OR('Input Laying'!N29="",'Input Laying'!N29=0),"",'Input Laying'!N29) | S18: =IF(OR('Input Laying'!T29="",'Input Laying'!T29=0),"",'Input Laying'!T29) | T18: =IF(OR('Input Laying'!U29="",'Input Laying'!U29=0),"",'Input Laying'!U29) | U18: =IF(OR('Input Laying'!X29="",'Input Laying'!X29=0),"",'Input Laying'!X29) | V18: =IF(OR('Input Laying'!Z29="",'Input Laying'!Z29=0),"",'Input Laying'!Z29) | W18: =IF('Input Laying'!AC29="","",'Input Laying'!AC29) | X18: =IF('Input Laying'!AD29="","",'Input Laying'!AD29) | Y18: =IF('Input Laying'!AE29="","",'Input Laying'!AE29) | Z18: =IF('Input Laying'!AG29="","",'Input Laying'!AG29) | AA18: =IF(OR('Input Laying'!AH29=0,'Input Laying'!AH29=""),"",'Input Laying'!AH29) | AB18: =IF('Input Laying'!AJ29="","",'Input Laying'!AJ29)
A19: Full date | B19: ='General Input'!B14 -> 0 | C19: ='General Input'!B14 -> 0 | F19: 16 | G19: =IF(OR('Graph values'!X111="",'Graph values'!X111=0),"",'Graph values'!X111) | H19: =IF(OR('Graph values'!Q111="",'Graph values'!Q111=0),"",'Graph values'!Q111) | I19: =IF(ISNA('Graph values'!D111),"",'Graph values'!D111) | J19: =IF(ISNA('Graph values'!F111*100),"",'Graph values'!F111*100) | K19: =OFFSET('Input Rearing'!S27,'Graph values'!O111,0) -> 0 | L19: ='Graph values'!Z111 -> 0 | M19: =OFFSET('Input Rearing'!AC27,'Graph values'!O111,0) | N19: =OFFSET('Input Rearing'!AE27,'Graph values'!O111,0) | O19: =OFFSET('Input Rearing'!AF27,'Graph values'!O111,0) -> 0 | P19: 32 | Q19: =IF(OR('Input Laying'!E30="",'Input Laying'!E30=0),"",'Input Laying'!E30) | R19: =IF(OR('Input Laying'!N30="",'Input Laying'!N30=0),"",'Input Laying'!N30) | S19: =IF(OR('Input Laying'!T30="",'Input Laying'!T30=0),"",'Input Laying'!T30) | T19: =IF(OR('Input Laying'!U30="",'Input Laying'!U30=0),"",'Input Laying'!U30) | U19: =IF(OR('Input Laying'!X30="",'Input Laying'!X30=0),"",'Input Laying'!X30) | V19: =IF(OR('Input Laying'!Z30="",'Input Laying'!Z30=0),"",'Input Laying'!Z30) | W19: =IF('Input Laying'!AC30="","",'Input Laying'!AC30) | X19: =IF('Input Laying'!AD30="","",'Input Laying'!AD30) | Y19: =IF('Input Laying'!AE30="","",'Input Laying'!AE30) | Z19: =IF('Input Laying'!AG30="","",'Input Laying'!AG30) | AA19: =IF(OR('Input Laying'!AH30=0,'Input Laying'!AH30=""),"",'Input Laying'!AH30) | AB19: =IF('Input Laying'!AJ30="","",'Input Laying'!AJ30)
F20: 17 | G20: =IF(OR('Graph values'!X112="",'Graph values'!X112=0),"",'Graph values'!X112) | H20: =IF(OR('Graph values'!Q112="",'Graph values'!Q112=0),"",'Graph values'!Q112) | I20: =IF(ISNA('Graph values'!D112),"",'Graph values'!D112) | J20: =IF(ISNA('Graph values'!F112*100),"",'Graph values'!F112*100) | K20: =OFFSET('Input Rearing'!S28,'Graph values'!O112,0) -> 0 | L20: ='Graph values'!Z112 -> 0 | M20: =OFFSET('Input Rearing'!AC28,'Graph values'!O112,0) | N20: =OFFSET('Input Rearing'!AE28,'Graph values'!O112,0) | O20: =OFFSET('Input Rearing'!AF28,'Graph values'!O112,0) -> 0 | P20: 33 | Q20: =IF(OR('Input Laying'!E31="",'Input Laying'!E31=0),"",'Input Laying'!E31) | R20: =IF(OR('Input Laying'!N31="",'Input Laying'!N31=0),"",'Input Laying'!N31) | S20: =IF(OR('Input Laying'!T31="",'Input Laying'!T31=0),"",'Input Laying'!T31) | T20: =IF(OR('Input Laying'!U31="",'Input Laying'!U31=0),"",'Input Laying'!U31) | U20: =IF(OR('Input Laying'!X31="",'Input Laying'!X31=0),"",'Input Laying'!X31) | V20: =IF(OR('Input Laying'!Z31="",'Input Laying'!Z31=0),"",'Input Laying'!Z31) | W20: =IF('Input Laying'!AC31="","",'Input Laying'!AC31) | X20: =IF('Input Laying'!AD31="","",'Input Laying'!AD31) | Y20: =IF('Input Laying'!AE31="","",'Input Laying'!AE31) | Z20: =IF('Input Laying'!AG31="","",'Input Laying'!AG31) | AA20: =IF(OR('Input Laying'!AH31=0,'Input Laying'!AH31=""),"",'Input Laying'!AH31) | AB20: =IF('Input Laying'!AJ31="","",'Input Laying'!AJ31)
B21: Rearing transfer date | F21: 18 | G21: =IF(OR('Graph values'!X113="",'Graph values'!X113=0),"",'Graph values'!X113) | H21: =IF(OR('Graph values'!Q113="",'Graph values'!Q113=0),"",'Graph values'!Q113) | I21: =IF(ISNA('Graph values'!D113),"",'Graph values'!D113) | J21: =IF(ISNA('Graph values'!F113*100),"",'Graph values'!F113*100) | K21: =OFFSET('Input Rearing'!S29,'Graph values'!O113,0) -> 0 | L21: ='Graph values'!Z113 -> 0 | M21: =OFFSET('Input Rearing'!AC29,'Graph values'!O113,0) | N21: =OFFSET('Input Rearing'!AE29,'Graph values'!O113,0) | O21: =OFFSET('Input Rearing'!AF29,'Graph values'!O113,0) -> 0 | P21: 34 | Q21: =IF(OR('Input Laying'!E32="",'Input Laying'!E32=0),"",'Input Laying'!E32) | R21: =IF(OR('Input Laying'!N32="",'Input Laying'!N32=0),"",'Input Laying'!N32) | S21: =IF(OR('Input Laying'!T32="",'Input Laying'!T32=0),"",'Input Laying'!T32) | T21: =IF(OR('Input Laying'!U32="",'Input Laying'!U32=0),"",'Input Laying'!U32) | U21: =IF(OR('Input Laying'!X32="",'Input Laying'!X32=0),"",'Input Laying'!X32) | V21: =IF(OR('Input Laying'!Z32="",'Input Laying'!Z32=0),"",'Input Laying'!Z32) | W21: =IF('Input Laying'!AC32="","",'Input Laying'!AC32) | X21: =IF('Input Laying'!AD32="","",'Input Laying'!AD32) | Y21: =IF('Input Laying'!AE32="","",'Input Laying'!AE32) | Z21: =IF('Input Laying'!AG32="","",'Input Laying'!AG32) | AA21: =IF(OR('Input Laying'!AH32=0,'Input Laying'!AH32=""),"",'Input Laying'!AH32) | AB21: =IF('Input Laying'!AJ32="","",'Input Laying'!AJ32)
A22: year | B22: =YEAR(B25) -> 1900 | P22: 35 | Q22: =IF(OR('Input Laying'!E33="",'Input Laying'!E33=0),"",'Input Laying'!E33) | R22: =IF(OR('Input Laying'!N33="",'Input Laying'!N33=0),"",'Input Laying'!N33) | S22: =IF(OR('Input Laying'!T33="",'Input Laying'!T33=0),"",'Input Laying'!T33) | T22: =IF(OR('Input Laying'!U33="",'Input Laying'!U33=0),"",'Input Laying'!U33) | U22: =IF(OR('Input Laying'!X33="",'Input Laying'!X33=0),"",'Input Laying'!X33) | V22: =IF(OR('Input Laying'!Z33="",'Input Laying'!Z33=0),"",'Input Laying'!Z33) | W22: =IF('Input Laying'!AC33="","",'Input Laying'!AC33) | X22: =IF('Input Laying'!AD33="","",'Input Laying'!AD33) | Y22: =IF('Input Laying'!AE33="","",'Input Laying'!AE33) | Z22: =IF('Input Laying'!AG33="","",'Input Laying'!AG33) | AA22: =IF(OR('Input Laying'!AH33=0,'Input Laying'!AH33=""),"",'Input Laying'!AH33) | AB22: =IF('Input Laying'!AJ33="","",'Input Laying'!AJ33)
A23: month | B23: =MONTH(B25) -> 1 | P23: 36 | Q23: =IF(OR('Input Laying'!E34="",'Input Laying'!E34=0),"",'Input Laying'!E34) | R23: =IF(OR('Input Laying'!N34="",'Input Laying'!N34=0),"",'Input Laying'!N34) | S23: =IF(OR('Input Laying'!T34="",'Input Laying'!T34=0),"",'Input Laying'!T34) | T23: =IF(OR('Input Laying'!U34="",'Input Laying'!U34=0),"",'Input Laying'!U34) | U23: =IF(OR('Input Laying'!X34="",'Input Laying'!X34=0),"",'Input Laying'!X34) | V23: =IF(OR('Input Laying'!Z34="",'Input Laying'!Z34=0),"",'Input Laying'!Z34) | W23: =IF('Input Laying'!AC34="","",'Input Laying'!AC34) | X23: =IF('Input Laying'!AD34="","",'Input Laying'!AD34) | Y23: =IF('Input Laying'!AE34="","",'Input Laying'!AE34) | Z23: =IF('Input Laying'!AG34="","",'Input Laying'!AG34) | AA23: =IF(OR('Input Laying'!AH34=0,'Input Laying'!AH34=""),"",'Input Laying'!AH34) | AB23: =IF('Input Laying'!AJ34="","",'Input Laying'!AJ34)
A24: day | B24: =DAY(B25) -> 0 | P24: 37 | Q24: =IF(OR('Input Laying'!E35="",'Input Laying'!E35=0),"",'Input Laying'!E35) | R24: =IF(OR('Input Laying'!N35="",'Input Laying'!N35=0),"",'Input Laying'!N35) | S24: =IF(OR('Input Laying'!T35="",'Input Laying'!T35=0),"",'Input Laying'!T35) | T24: =IF(OR('Input Laying'!U35="",'Input Laying'!U35=0),"",'Input Laying'!U35) | U24: =IF(OR('Input Laying'!X35="",'Input Laying'!X35=0),"",'Input Laying'!X35) | V24: =IF(OR('Input Laying'!Z35="",'Input Laying'!Z35=0),"",'Input Laying'!Z35) | W24: =IF('Input Laying'!AC35="","",'Input Laying'!AC35) | X24: =IF('Input Laying'!AD35="","",'Input Laying'!AD35) | Y24: =IF('Input Laying'!AE35="","",'Input Laying'!AE35) | Z24: =IF('Input Laying'!AG35="","",'Input Laying'!AG35) | AA24: =IF(OR('Input Laying'!AH35=0,'Input Laying'!AH35=""),"",'Input Laying'!AH35) | AB24: =IF('Input Laying'!AJ35="","",'Input Laying'!AJ35)
A25: Full date | B25: ='Input Laying'!G5 -> 0 | C25: =IF(ISNA(B25),"",B25) -> 0 | P25: 38 | Q25: =IF(OR('Input Laying'!E36="",'Input Laying'!E36=0),"",'Input Laying'!E36) | R25: =IF(OR('Input Laying'!N36="",'Input Laying'!N36=0),"",'Input Laying'!N36) | S25: =IF(OR('Input Laying'!T36="",'Input Laying'!T36=0),"",'Input Laying'!T36) | T25: =IF(OR('Input Laying'!U36="",'Input Laying'!U36=0),"",'Input Laying'!U36) | U25: =IF(OR('Input Laying'!X36="",'Input Laying'!X36=0),"",'Input Laying'!X36) | V25: =IF(OR('Input Laying'!Z36="",'Input Laying'!Z36=0),"",'Input Laying'!Z36) | W25: =IF('Input Laying'!AC36="","",'Input Laying'!AC36) | X25: =IF('Input Laying'!AD36="","",'Input Laying'!AD36) | Y25: =IF('Input Laying'!AE36="","",'Input Laying'!AE36) | Z25: =IF('Input Laying'!AG36="","",'Input Laying'!AG36) | AA25: =IF(OR('Input Laying'!AH36=0,'Input Laying'!AH36=""),"",'Input Laying'!AH36) | AB25: =IF('Input Laying'!AJ36="","",'Input Laying'!AJ36)
P26: 39 | Q26: =IF(OR('Input Laying'!E37="",'Input Laying'!E37=0),"",'Input Laying'!E37) | R26: =IF(OR('Input Laying'!N37="",'Input Laying'!N37=0),"",'Input Laying'!N37) | S26: =IF(OR('Input Laying'!T37="",'Input Laying'!T37=0),"",'Input Laying'!T37) | T26: =IF(OR('Input Laying'!U37="",'Input Laying'!U37=0),"",'Input Laying'!U37) | U26: =IF(OR('Input Laying'!X37="",'Input Laying'!X37=0),"",'Input Laying'!X37) | V26: =IF(OR('Input Laying'!Z37="",'Input Laying'!Z37=0),"",'Input Laying'!Z37) | W26: =IF('Input Laying'!AC37="","",'Input Laying'!AC37) | X26: =IF('Input Laying'!AD37="","",'Input Laying'!AD37) | Y26: =IF('Input Laying'!AE37="","",'Input Laying'!AE37) | Z26: =IF('Input Laying'!AG37="","",'Input Laying'!AG37) | AA26: =IF(OR('Input Laying'!AH37=0,'Input Laying'!AH37=""),"",'Input Laying'!AH37) | AB26: =IF('Input Laying'!AJ37="","",'Input Laying'!AJ37)
P27: 40 | Q27: =IF(OR('Input Laying'!E38="",'Input Laying'!E38=0),"",'Input Laying'!E38) | R27: =IF(OR('Input Laying'!N38="",'Input Laying'!N38=0),"",'Input Laying'!N38) | S27: =IF(OR('Input Laying'!T38="",'Input Laying'!T38=0),"",'Input Laying'!T38) | T27: =IF(OR('Input Laying'!U38="",'Input Laying'!U38=0),"",'Input Laying'!U38) | U27: =IF(OR('Input Laying'!X38="",'Input Laying'!X38=0),"",'Input Laying'!X38) | V27: =IF(OR('Input Laying'!Z38="",'Input Laying'!Z38=0),"",'Input Laying'!Z38) | W27: =IF('Input Laying'!AC38="","",'Input Laying'!AC38) | X27: =IF('Input Laying'!AD38="","",'Input Laying'!AD38) | Y27: =IF('Input Laying'!AE38="","",'Input Laying'!AE38) | Z27: =IF('Input Laying'!AG38="","",'Input Laying'!AG38) | AA27: =IF(OR('Input Laying'!AH38=0,'Input Laying'!AH38=""),"",'Input Laying'!AH38) | AB27: =IF('Input Laying'!AJ38="","",'Input Laying'!AJ38)
P28: 41 | Q28: =IF(OR('Input Laying'!E39="",'Input Laying'!E39=0),"",'Input Laying'!E39) | R28: =IF(OR('Input Laying'!N39="",'Input Laying'!N39=0),"",'Input Laying'!N39) | S28: =IF(OR('Input Laying'!T39="",'Input Laying'!T39=0),"",'Input Laying'!T39) | T28: =IF(OR('Input Laying'!U39="",'Input Laying'!U39=0),"",'Input Laying'!U39) | U28: =IF(OR('Input Laying'!X39="",'Input Laying'!X39=0),"",'Input Laying'!X39) | V28: =IF(OR('Input Laying'!Z39="",'Input Laying'!Z39=0),"",'Input Laying'!Z39) | W28: =IF('Input Laying'!AC39="","",'Input Laying'!AC39) | X28: =IF('Input Laying'!AD39="","",'Input Laying'!AD39) | Y28: =IF('Input Laying'!AE39="","",'Input Laying'!AE39) | Z28: =IF('Input Laying'!AG39="","",'Input Laying'!AG39) | AA28: =IF(OR('Input Laying'!AH39=0,'Input Laying'!AH39=""),"",'Input Laying'!AH39) | AB28: =IF('Input Laying'!AJ39="","",'Input Laying'!AJ39)
P29: 42 | Q29: =IF(OR('Input Laying'!E40="",'Input Laying'!E40=0),"",'Input Laying'!E40) | R29: =IF(OR('Input Laying'!N40="",'Input Laying'!N40=0),"",'Input Laying'!N40) | S29: =IF(OR('Input Laying'!T40="",'Input Laying'!T40=0),"",'Input Laying'!T40) | T29: =IF(OR('Input Laying'!U40="",'Input Laying'!U40=0),"",'Input Laying'!U40) | U29: =IF(OR('Input Laying'!X40="",'Input Laying'!X40=0),"",'Input Laying'!X40) | V29: =IF(OR('Input Laying'!Z40="",'Input Laying'!Z40=0),"",'Input Laying'!Z40) | W29: =IF('Input Laying'!AC40="","",'Input Laying'!AC40) | X29: =IF('Input Laying'!AD40="","",'Input Laying'!AD40) | Y29: =IF('Input Laying'!AE40="","",'Input Laying'!AE40) | Z29: =IF('Input Laying'!AG40="","",'Input Laying'!AG40) | AA29: =IF(OR('Input Laying'!AH40=0,'Input Laying'!AH40=""),"",'Input Laying'!AH40) | AB29: =IF('Input Laying'!AJ40="","",'Input Laying'!AJ40)
P30: 43 | Q30: =IF(OR('Input Laying'!E41="",'Input Laying'!E41=0),"",'Input Laying'!E41) | R30: =IF(OR('Input Laying'!N41="",'Input Laying'!N41=0),"",'Input Laying'!N41) | S30: =IF(OR('Input Laying'!T41="",'Input Laying'!T41=0),"",'Input Laying'!T41) | T30: =IF(OR('Input Laying'!U41="",'Input Laying'!U41=0),"",'Input Laying'!U41) | U30: =IF(OR('Input Laying'!X41="",'Input Laying'!X41=0),"",'Input Laying'!X41) | V30: =IF(OR('Input Laying'!Z41="",'Input Laying'!Z41=0),"",'Input Laying'!Z41) | W30: =IF('Input Laying'!AC41="","",'Input Laying'!AC41) | X30: =IF('Input Laying'!AD41="","",'Input Laying'!AD41) | Y30: =IF('Input Laying'!AE41="","",'Input Laying'!AE41) | Z30: =IF('Input Laying'!AG41="","",'Input Laying'!AG41) | AA30: =IF(OR('Input Laying'!AH41=0,'Input Laying'!AH41=""),"",'Input Laying'!AH41) | AB30: =IF('Input Laying'!AJ41="","",'Input Laying'!AJ41)
P31: 44 | Q31: =IF(OR('Input Laying'!E42="",'Input Laying'!E42=0),"",'Input Laying'!E42) | R31: =IF(OR('Input Laying'!N42="",'Input Laying'!N42=0),"",'Input Laying'!N42) | S31: =IF(OR('Input Laying'!T42="",'Input Laying'!T42=0),"",'Input Laying'!T42) | T31: =IF(OR('Input Laying'!U42="",'Input Laying'!U42=0),"",'Input Laying'!U42) | U31: =IF(OR('Input Laying'!X42="",'Input Laying'!X42=0),"",'Input Laying'!X42) | V31: =IF(OR('Input Laying'!Z42="",'Input Laying'!Z42=0),"",'Input Laying'!Z42) | W31: =IF('Input Laying'!AC42="","",'Input Laying'!AC42) | X31: =IF('Input Laying'!AD42="","",'Input Laying'!AD42) | Y31: =IF('Input Laying'!AE42="","",'Input Laying'!AE42) | Z31: =IF('Input Laying'!AG42="","",'Input Laying'!AG42) | AA31: =IF(OR('Input Laying'!AH42=0,'Input Laying'!AH42=""),"",'Input Laying'!AH42) | AB31: =IF('Input Laying'!AJ42="","",'Input Laying'!AJ42)
P32: 45 | Q32: =IF(OR('Input Laying'!E43="",'Input Laying'!E43=0),"",'Input Laying'!E43) | R32: =IF(OR('Input Laying'!N43="",'Input Laying'!N43=0),"",'Input Laying'!N43) | S32: =IF(OR('Input Laying'!T43="",'Input Laying'!T43=0),"",'Input Laying'!T43) | T32: =IF(OR('Input Laying'!U43="",'Input Laying'!U43=0),"",'Input Laying'!U43) | U32: =IF(OR('Input Laying'!X43="",'Input Laying'!X43=0),"",'Input Laying'!X43) | V32: =IF(OR('Input Laying'!Z43="",'Input Laying'!Z43=0),"",'Input Laying'!Z43) | W32: =IF('Input Laying'!AC43="","",'Input Laying'!AC43) | X32: =IF('Input Laying'!AD43="","",'Input Laying'!AD43) | Y32: =IF('Input Laying'!AE43="","",'Input Laying'!AE43) | Z32: =IF('Input Laying'!AG43="","",'Input Laying'!AG43) | AA32: =IF(OR('Input Laying'!AH43=0,'Input Laying'!AH43=""),"",'Input Laying'!AH43) | AB32: =IF('Input Laying'!AJ43="","",'Input Laying'!AJ43)
P33: 46 | Q33: =IF(OR('Input Laying'!E44="",'Input Laying'!E44=0),"",'Input Laying'!E44) | R33: =IF(OR('Input Laying'!N44="",'Input Laying'!N44=0),"",'Input Laying'!N44) | S33: =IF(OR('Input Laying'!T44="",'Input Laying'!T44=0),"",'Input Laying'!T44) | T33: =IF(OR('Input Laying'!U44="",'Input Laying'!U44=0),"",'Input Laying'!U44) | U33: =IF(OR('Input Laying'!X44="",'Input Laying'!X44=0),"",'Input Laying'!X44) | V33: =IF(OR('Input Laying'!Z44="",'Input Laying'!Z44=0),"",'Input Laying'!Z44) | W33: =IF('Input Laying'!AC44="","",'Input Laying'!AC44) | X33: =IF('Input Laying'!AD44="","",'Input Laying'!AD44) | Y33: =IF('Input Laying'!AE44="","",'Input Laying'!AE44) | Z33: =IF('Input Laying'!AG44="","",'Input Laying'!AG44) | AA33: =IF(OR('Input Laying'!AH44=0,'Input Laying'!AH44=""),"",'Input Laying'!AH44) | AB33: =IF('Input Laying'!AJ44="","",'Input Laying'!AJ44)
P34: 47 | Q34: =IF(OR('Input Laying'!E45="",'Input Laying'!E45=0),"",'Input Laying'!E45) | R34: =IF(OR('Input Laying'!N45="",'Input Laying'!N45=0),"",'Input Laying'!N45) | S34: =IF(OR('Input Laying'!T45="",'Input Laying'!T45=0),"",'Input Laying'!T45) | T34: =IF(OR('Input Laying'!U45="",'Input Laying'!U45=0),"",'Input Laying'!U45) | U34: =IF(OR('Input Laying'!X45="",'Input Laying'!X45=0),"",'Input Laying'!X45) | V34: =IF(OR('Input Laying'!Z45="",'Input Laying'!Z45=0),"",'Input Laying'!Z45) | W34: =IF('Input Laying'!AC45="","",'Input Laying'!AC45) | X34: =IF('Input Laying'!AD45="","",'Input Laying'!AD45) | Y34: =IF('Input Laying'!AE45="","",'Input Laying'!AE45) | Z34: =IF('Input Laying'!AG45="","",'Input Laying'!AG45) | AA34: =IF(OR('Input Laying'!AH45=0,'Input Laying'!AH45=""),"",'Input Laying'!AH45) | AB34: =IF('Input Laying'!AJ45="","",'Input Laying'!AJ45)
P35: 48 | Q35: =IF(OR('Input Laying'!E46="",'Input Laying'!E46=0),"",'Input Laying'!E46) | R35: =IF(OR('Input Laying'!N46="",'Input Laying'!N46=0),"",'Input Laying'!N46) | S35: =IF(OR('Input Laying'!T46="",'Input Laying'!T46=0),"",'Input Laying'!T46) | T35: =IF(OR('Input Laying'!U46="",'Input Laying'!U46=0),"",'Input Laying'!U46) | U35: =IF(OR('Input Laying'!X46="",'Input Laying'!X46=0),"",'Input Laying'!X46) | V35: =IF(OR('Input Laying'!Z46="",'Input Laying'!Z46=0),"",'Input Laying'!Z46) | W35: =IF('Input Laying'!AC46="","",'Input Laying'!AC46) | X35: =IF('Input Laying'!AD46="","",'Input Laying'!AD46) | Y35: =IF('Input Laying'!AE46="","",'Input Laying'!AE46) | Z35: =IF('Input Laying'!AG46="","",'Input Laying'!AG46) | AA35: =IF(OR('Input Laying'!AH46=0,'Input Laying'!AH46=""),"",'Input Laying'!AH46) | AB35: =IF('Input Laying'!AJ46="","",'Input Laying'!AJ46)
P36: 49 | Q36: =IF(OR('Input Laying'!E47="",'Input Laying'!E47=0),"",'Input Laying'!E47) | R36: =IF(OR('Input Laying'!N47="",'Input Laying'!N47=0),"",'Input Laying'!N47) | S36: =IF(OR('Input Laying'!T47="",'Input Laying'!T47=0),"",'Input Laying'!T47) | T36: =IF(OR('Input Laying'!U47="",'Input Laying'!U47=0),"",'Input Laying'!U47) | U36: =IF(OR('Input Laying'!X47="",'Input Laying'!X47=0),"",'Input Laying'!X47) | V36: =IF(OR('Input Laying'!Z47="",'Input Laying'!Z47=0),"",'Input Laying'!Z47) | W36: =IF('Input Laying'!AC47="","",'Input Laying'!AC47) | X36: =IF('Input Laying'!AD47="","",'Input Laying'!AD47) | Y36: =IF('Input Laying'!AE47="","",'Input Laying'!AE47) | Z36: =IF('Input Laying'!AG47="","",'Input Laying'!AG47) | AA36: =IF(OR('Input Laying'!AH47=0,'Input Laying'!AH47=""),"",'Input Laying'!AH47) | AB36: =IF('Input Laying'!AJ47="","",'Input Laying'!AJ47)
P37: 50 | Q37: =IF(OR('Input Laying'!E48="",'Input Laying'!E48=0),"",'Input Laying'!E48) | R37: =IF(OR('Input Laying'!N48="",'Input Laying'!N48=0),"",'Input Laying'!N48) | S37: =IF(OR('Input Laying'!T48="",'Input Laying'!T48=0),"",'Input Laying'!T48) | T37: =IF(OR('Input Laying'!U48="",'Input Laying'!U48=0),"",'Input Laying'!U48) | U37: =IF(OR('Input Laying'!X48="",'Input Laying'!X48=0),"",'Input Laying'!X48) | V37: =IF(OR('Input Laying'!Z48="",'Input Laying'!Z48=0),"",'Input Laying'!Z48) | W37: =IF('Input Laying'!AC48="","",'Input Laying'!AC48) | X37: =IF('Input Laying'!AD48="","",'Input Laying'!AD48) | Y37: =IF('Input Laying'!AE48="","",'Input Laying'!AE48) | Z37: =IF('Input Laying'!AG48="","",'Input Laying'!AG48) | AA37: =IF(OR('Input Laying'!AH48=0,'Input Laying'!AH48=""),"",'Input Laying'!AH48) | AB37: =IF('Input Laying'!AJ48="","",'Input Laying'!AJ48)
... P87: 100 | Q87: =IF(OR('Input Laying'!E98="",'Input Laying'!E98=0),"",'Input Laying'!E98) | R87: =IF(OR('Input Laying'!N98="",'Input Laying'!N98=0),"",'Input Laying'!N98) | S87: =IF(OR('Input Laying'!T98="",'Input Laying'!T98=0),"",'Input Laying'!T98) | T87: =IF(OR('Input Laying'!U98="",'Input Laying'!U98=0),"",'Input Laying'!U98) | U87: =IF(OR('Input Laying'!X98="",'Input Laying'!X98=0),"",'Input Laying'!X98) | V87: =IF(OR('Input Laying'!Z98="",'Input Laying'!Z98=0),"",'Input Laying'!Z98) | W87: =IF('Input Laying'!AC98="","",'Input Laying'!AC98) | X87: =IF('Input Laying'!AD98="","",'Input Laying'!AD98) | Y87: =IF('Input Laying'!AE98="","",'Input Laying'!AE98) | Z87: =IF('Input Laying'!AG98="","",'Input Laying'!AG98) | AA87: =IF(OR('Input Laying'!AH98=0,'Input Laying'!AH98=""),"",'Input Laying'!AH98) | AB87: =IF('Input Laying'!AJ98="","",'Input Laying'!AJ98)

Sheet Diverse
B1: Year | D1: Month | G1: Day | J1: Product | M1: Housing system laying | Q1: Country | U1: Gradings | X1: Currencies
B2: =YEAR('General Input'!B14) -> 1900 | C2: =IF(RIGHT(B2,2)<10,"0"&RIGHT(B2,2),RIGHT(B2,2)) -> 00 | D2: =MONTH('General Input'!B14) -> 1 | E2: =IF(D2<10,"0"&D2,D2) -> 01 | G2: =DAY('General Input'!B14) -> 0 | H2: =IF(G2<10,"0"&G2,G2) -> 00 | J2: =VLOOKUP('General Input'!B17,J4:K40,2,FALSE) -> IB | K2: =IF(ISNA(J2),"",J2) -> IB | N2: =VLOOKUP('General Input'!B18,Diverse!N3:O10,2,FALSE) -> #N/A | O2: =IF(ISNA(N2),"",N2) | R2: =VLOOKUP('General Input'!B22,R3:S252,2) -> #N/A | S2: =IF(ISNA(R2),"",R2) | X2: =VLOOKUP('General Input'!B23,Diverse!X4:X170,1,FALSE) -> #N/A | Y2: =IF(ISNA(X2),"",X2)
F3: 1 | M3: 1 | Q3: 1 | U3: 40 | W3: 1 | AC3: Language
B4: 2008 | C4: 08 | D4: =Language!B236 -> January | E4: 01 | F4: 2 | G4: 01 | H4: 1 | M4: 2 | N4: =Language!B249 -> Cage | O4: cg | Q4: 2 | R4: Afghanistan | S4: AF | U4: 41 | W4: 2 | X4: AED | Y4: afghani | Z4: Afghanistan | AC4: Deutsch
B5: 2009 | C5: 09 | D5: =Language!B237 -> February | E5: 02 | F5: 3 | G5: 02 | H5: 2 | J5: BABCOCK B400 | K5: BCW400 | M5: 3 | N5: =Language!B250 -> Barn | O5: br | Q5: 3 | R5: Åland Islands | S5: AX | U5: 42 | W5: 3 | X5: AFN | Y5: ariary | Z5: Madagascar | AC5: English
B6: 2010 | C6: 10 | D6: =Language!B238 -> March | E6: 03 | F6: 4 | G6: 03 | H6: 3 | J6: BABCOCK BROWN | K6: BCB | M6: 4 | N6: =Language!B251 -> Free range | O6: fr | Q6: 4 | R6: Albania | S6: AL | U6: 43 | W6: 4 | X6: ALL | Y6: baht | Z6: Thaïlande | AC6: Español
B7: 2011 | C7: 11 | D7: =Language!B239 -> April | E7: 04 | F7: 5 | G7: 04 | H7: 4 | J7: BABCOCK COLUMBIAN BLACK TAIL | K7: CBT | M7: 5 | N7: =Language!B252 -> Free range multi tier | O7: mt | Q7: 5 | R7: Algeria | S7: DZ | U7: 44 | W7: 5 | X7: AMD | Y7: balboa | Z7: Panama | AC7: Français
B8: 2012 | C8: 12 | D8: =Language!B240 -> May | E8: 05 | F8: 6 | G8: 05 | H8: 5 | J8: BABCOCK WHITE | K8: BCW | M8: 6 | N8: =Language!B253 -> Aviary | O8: vo | Q8: 6 | R8: American Samoa | S8: AS | U8: 45 | W8: 6 | X8: ANG | Y8: birr | Z8: Éthiopie | AC8: Indonesia
B9: 2013 | C9: 13 | D9: =Language!B241 -> June | E9: 06 | F9: 7 | G9: 06 | H9: 6 | J9: BOVANS BLACK | K9: BBL | M9: 7 | N9: =Language!B254 -> Enriched cage | O9: ec | Q9: 7 | R9: Andorra | S9: AD | U9: 46 | W9: 7 | X9: AOA | Y9: bolivar | Z9: Vénézuéla | AC9: Italiano
B10: 2014 | C10: 14 | D10: =Language!B242 -> July | E10: 07 | F10: 8 | G10: 07 | H10: 7 | J10: BOVANS BROWN | K10: BB | M10: 8 | N10: =Language!B255 -> Organic | O10: or | Q10: 8 | R10: Angola | S10: AO | U10: 47 | W10: 8 | X10: ARS | Y10: cedi | Z10: Ghana | AC10: Nederland
B11: 2015 | C11: 15 | D11: =Language!B243 -> August | E11: 08 | F11: 9 | G11: 08 | H11: 8 | J11: BOVANS BROWN (GOLDLINE) | K11: BBR | M11: 9 | Q11: 9 | R11: Anguilla | S11: AI | U11: 48 | W11: 9 | X11: AUD | Y11: colon | Z11: Costa Rica | AC11: Polski
B12: 2016 | C12: 16 | D12: =Language!B244 -> September | E12: 09 | F12: 10 | G12: 09 | H12: 9 | J12: BOVANS GOLDLINE | K12: BG | M12: 10 | Q12: 10 | R12: Antarctica | S12: AQ | U12: 49 | W12: 10 | X12: AWG | Y12: colon | Z12: Salvador | AC12: Português
B13: 2017 | C13: 17 | D13: =Language!B245 -> October | E13: 10 | F13: 11 | G13: 10 | H13: 10 | J13: BOVANS NERA | K13: BN | M13: 11 | Q13: 11 | R13: Antigua and Barbuda | S13: AG | U13: 50 | W13: 11 | X13: AZN | Y13: cordoba d'or | Z13: Nicaragua | AC13: Slovenský
B14: 2018 | C14: 18 | D14: =Language!B246 -> November | E14: 11 | F14: 12 | G14: 11 | H14: 11 | J14: BOVANS SPERWER | K14: SP | Q14: 12 | R14: Argentina | S14: AR | U14: 51 | W14: 12 | X14: BAM | Y14: couronne | Z14: Suède | AC14: South Slavic
B15: 2019 | C15: 19 | D15: =Language!B247 -> December | E15: 12 | F15: 13 | G15: 12 | H15: 12 | J15: BOVANS TINTED | K15: BT | N15: Housing system rearing | O15: =VLOOKUP('Input Rearing'!G5,Diverse!N16:O19,2,FALSE) -> #N/A | Q15: 13 | R15: Armenia | S15: AM | U15: 52 | W15: 13 | X15: BBD | Y15: couronne | Z15: Islande | AC15: русский
B16: 2020 | C16: 20 | G16: 13 | H16: 13 | J16: BOVANS WHITE | K16: BW | M16: 1 | Q16: 14 | R16: Aruba | S16: AW | U16: 53 | W16: 14 | X16: BDT | Y16: couronne | Z16: Norvège | AC16: العربية
G17: 14 | H17: 14 | J17: DEKALB AMBERLINK | K17: DA | M17: 2 | N17: =Language!B249 -> Cage | O17: cg | Q17: 15 | R17: Australia | S17: AU | U17: 54 | W17: 15 | X17: BGL | Y17: couronne | Z17: République Tchèque | AC17: 한국의
G18: 15 | H18: 15 | J18: DEKALB BETA | K18: BE | M18: 3 | N18: =Language!B250 -> Barn | O18: br | Q18: 16 | R18: Austria | S18: AT | U18: 55 | W18: 16 | X18: BHD | Y18: couronne | Z18: Danemark | AC18: 中国
G19: 16 | H19: 16 | J19: DEKALB BLACK | K19: DBL | M19: 4 | N19: =Language!B253 -> Aviary | O19: vo | Q19: 17 | R19: Azerbaijan | S19: AZ | U19: 56 | W19: 17 | X19: BIF | Y19: couronne | Z19: Estonie | AC19: 日本の
G20: 17 | H20: 17 | J20: DEKALB BROWN | K20: DB | Q20: 18 | R20: Bahamas | S20: BS | U20: 57 | W20: 18 | X20: BMD | Y20: dalasi | Z20: Gambie
G21: 18 | H21: 18 | J21: DEKALB RUBY | K21: DR | Q21: 19 | R21: Bahrain | S21: BH | U21: 58 | W21: 19 | X21: BND | Y21: denar | Z21: Macédoine
G22: 19 | H22: 19 | J22: DEKALB TX | K22: TX | Q22: 20 | R22: Bangladesh | S22: BD | U22: 59 | W22: 20 | X22: BRL | Y22: dinar | Z22: Irak
G23: 20 | H23: 20 | J23: DEKALB WHITE | K23: DW | Q23: 21 | R23: Barbados | S23: BB | U23: 60 | W23: 21 | X23: BSD | Y23: dinar | Z23: Koweït
A24: TEST LANGUE | B24: =IF(Language!B354="mm/dd/yy;@","ENG",IF(Language!B354="yy/mm/dd;@","CHI","DEF")) -> DEF | G24: 21 | H24: 21 | J24: HISEX BROWN | K24: HB | Q24: 22 | R24: Belarus | S24: BY | U24: 61 | W24: 22 | X24: BTN | Y24: dinar | Z24: Algérie
G25: 22 | H25: 22 | J25: HISEX FREILAND | K25: HF | Q25: 23 | R25: Belgium | S25: BE | U25: 62 | W25: 23 | X25: BWP | Y25: dinar | Z25: Libye
A26: FORMULE ENG | B26: =CONCATENATE(IF(MONTH(A35)<10,"0",""),MONTH(A35)," / ",DAY(A29)," - ",DAY(A35)," / ",YEAR(A35)) -> 01 / 0 - 0 / 1900 | C26: =CONCATENATE(IF(MONTH(A40)<10,"0",""),MONTH(A40)," / ",DAY(A34)," - ",DAY(A40)," / ",YEAR(A40)) -> 01 / 0 - 0 / 1900 | G26: 23 | H26: 23 | J26: HISEX TINTED | K26: HT | Q26: 24 | R26: Belize | S26: BZ | U26: 63 | W26: 24 | X26: BYR | Y26: dinar | Z26: Jordanie
A27: FORMULE CHI | B27: =CONCATENATE(,YEAR(A35)," / ",IF(MONTH(A35)<10,"0",""),MONTH(A35)," / ",DAY(A29)," - ",DAY(A35)) -> 1900 / 01 / 0 - 0 | C27: =CONCATENATE(,YEAR(A40)," / ",IF(MONTH(A40)<10,"0",""),MONTH(A40)," / ",DAY(A34)," - ",DAY(A40)) -> 1900 / 01 / 0 - 0 | G27: 24 | H27: 24 | J27: HISEX WHITE | K27: HW | Q27: 25 | R27: Benin | S27: BJ | U27: 64 | W27: 25 | X27: BZD | Y27: dinar | Z27: Bahreïn
G28: 25 | H28: 25 | J28: ISA BROWN | K28: IB | Q28: 26 | R28: Bermuda | S28: BM | U28: 65 | W28: 26 | X28: CAD | Y28: dinar | Z28: Tunisie
G29: 26 | H29: 26 | J29: ISA BROWN PREMIUM | K29: IBP | Q29: 27 | R29: Bhutan | S29: BT | U29: 66 | W29: 27 | X29: CDF | Y29: dinar | Z29: Yougoslavie
G30: 27 | H30: 27 | J30: ISA GOLDEN COMET | K30: GC | Q30: 28 | R30: Bolivia (Plurinational State of) | S30: BO | U30: 67 | W30: 28 | X30: CHF | Y30: dirham | Z30: Émirats Arabes Unis
A31: Date min | B31: 1 | G31: 28 | H31: 28 | J31: ISA RIR LOURD | K31: RIRL | Q31: 29 | R31: Bonaire, Sint Eustatius and Saba | S31: BQ | U31: 68 | W31: 29 | X31: CLP | Y31: dirham | Z31: Maroc
A32: Date max | B32: =TODAY() -> 44708 | G32: 29 | H32: 29 | J32: ISA SUSSEX | K32: SU | Q32: 30 | R32: Bosnia and Herzegovina | S32: BA | U32: 69 | W32: 30 | X32: CNH | Y32: dobra | Z32: São Tomé-et-Principe
G33: 30 | H33: 30 | J33: ISA TINTED | K33: IT | Q33: 31 | R33: Botswana | S33: BW | U33: 70 | W33: 31 | X33: CNY | Y33: dollar | Z33: Tuvalu
G34: 31 | H34: 31 | J34: ISA WARREN | K34: WA | Q34: 32 | R34: Bouvet Island | S34: BV | U34: 71 | W34: 32 | X34: COP | Y34: dollar | Z34: Australie
H35: 32 | J35: ISA WHITE | K35: IW | Q35: 33 | R35: Brazil | S35: BR | U35: 72 | W35: 33 | X35: CRC | Y35: dollar | Z35: Singapour
H36: 33 | J36: RED | K36: RIR | Q36: 34 | R36: British Indian Ocean Territory | S36: IO | U36: 73 | W36: 34 | X36: CUP | Y36: dollar | Z36: Bermudes
H37: 34 | J37: SHAVER BLACK | K37: SBL | Q37: 35 | R37: Brunei Darussalam | S37: BN | U37: 74 | W37: 35 | X37: CVE | Y37: dollar | Z37: Brunei
H38: 35 | J38: SHAVER BROWN | K38: SB | Q38: 36 | R38: Bulgaria | S38: BG | U38: 75 | W38: 36 | X38: CZK | Y38: dollar | Z38: Trinité-et-Tobago
H39: 36 | J39: SHAVER RED | K39: SR | Q39: 37 | R39: Burkina Faso | S39: BF | U39: 76 | W39: 37 | X39: DJF | Y39: dollar | Z39: Îles Caïmans
H40: 37 | J40: SHAVER WHITE | K40: SW | Q40: 38 | R40: Burundi | S40: BI | U40: 77 | W40: 38 | X40: DKK | Y40: dollar | Z40: Bahamas
Q41: 39 | R41: Cambodia | S41: KH | U41: 78 | W41: 39 | X41: DOP | Y41: dollar | Z41: Iles Salomon
B42: Year | D42: Month | G42: Day | Q42: 40 | R42: Cameroon | S42: CM | U42: 79 | W42: 40 | X42: DZD | Y42: dollar | Z42: Zimbabwe
B43: =VLOOKUP('Input Laying'!K5,B44:C57,1,FALSE) -> #N/A | D43: =VLOOKUP('Input Laying'!I5,D44:E56,2,FALSE) -> #N/A | E43: =IF(ISNA(D43),"",D43) | Q43: 41 | R43: Canada | S43: CA | U43: 80 | W43: 41 | X43: EEK | Y43: dollar | Z43: Nouvelle Zélande
Q44: 42 | R44: Cabo Verde | S44: CV | W44: 42 | X44: EGP | Y44: dollar | Z44: Belize
B45: 2008 | C45: 08 | D45: =Language!B236 -> January | E45: 01 | G45: 01 | Q45: 43 | R45: Cayman Islands | S45: KY | W45: 43 | X45: ERN | Y45: dollar | Z45: Jamaïque
B46: 2009 | C46: 09 | D46: =Language!B237 -> February | E46: 02 | G46: 02 | Q46: 44 | R46: Central African Republic | S46: CF | W46: 44 | X46: ETB | Y46: dollar | Z46: Canada
B47: 2010 | C47: 10 | D47: =Language!B238 -> March | E47: 03 | G47: 03 | Q47: 45 | R47: Chad | S47: TD | W47: 45 | X47: EUR | Y47: dollar | Z47: Etats-Unis d'Amérique
B48: 2011 | C48: 11 | D48: =Language!B239 -> April | E48: 04 | G48: 04 | Q48: 46 | R48: Chile | S48: CL | W48: 46 | X48: FJD | Y48: dollar | Z48: Fidji
B49: 2012 | C49: 12 | D49: =Language!B240 -> May | E49: 05 | G49: 05 | Q49: 47 | R49: China | S49: CN | W49: 47 | X49: FKP | Y49: dollar | Z49: Barbade
B50: 2013 | C50: 13 | D50: =Language!B241 -> June | E50: 06 | G50: 06 | Q50: 48 | R50: Christmas Island | S50: CX | W50: 48 | X50: GBP | Y50: dollar | Z50: Hong Kong
B51: 2014 | C51: 14 | D51: =Language!B242 -> July | E51: 07 | G51: 07 | Q51: 49 | R51: Cocos (Keeling) Islands | S51: CC | W51: 49 | X51: GEL | Y51: dollar | Z51: Guyana
B52: 2015 | C52: 15 | D52: =Language!B243 -> August | E52: 08 | G52: 08 | Q52: 50 | R52: Colombia | S52: CO | W52: 50 | X52: GGP | Y52: dollar | Z52: Namibie
B53: 2016 | C53: 16 | D53: =Language!B244 -> September | E53: 09 | G53: 09 | Q53: 51 | R53: Comoros | S53: KM | W53: 51 | X53: GHC | Y53: dollar | Z53: Taïwan
B54: 2017 | C54: 17 | D54: =Language!B245 -> October | E54: 10 | G54: 10 | Q54: 52 | R54: Congo | S54: CG | W54: 52 | X54: GIP | Y54: dollar | Z54: Libéria
